Workbook
Name c_country: Analysis!$C$6
Name c_from: Analysis!$C$8
Name c_genre: Analysis!$C$7
Name c_rg: Analysis!$C$5
Name c_to: Analysis!$C$9
Name c_type: Analysis!$C$4
Name d_all: Data!$A$2:$A$8808
Name d_cast: Data!$U$2:$U$8808
Name d_ctry: Data!$R$2:$R$8808
Name d_dirk: Data!$T$2:$T$8808
Name d_dv: Data!$P$2:$P$8808
Name d_genre: Data!$S$2:$S$8808
Name d_mo: Data!$N$2:$N$8808
Name d_pc: Data!$Q$2:$Q$8808
Name d_rating: Data!$I$2:$I$8808
Name d_rg: Data!$O$2:$O$8808
Name d_ry: Data!$H$2:$H$8808
Name d_title: Data!$C$2:$C$8808
Name d_type: Data!$B$2:$B$8808
Name d_ya: Data!$M$2:$M$8808
Name list_country: Lists!$C$2:$C$125
Name list_genre: Lists!$D$2:$D$44
Name list_rg: Lists!$B$2:$B$7
Name list_type: Lists!$A$2:$A$4
Name list_year: Lists!$E$2:$E$98

Sheet About (2)
B1: PROJECT GUIDE & DOCUMENTATION
B2: ← Back to Dashboard
B5: PROJECT DETAILS (edit the highlighted cells)
B6: Project title | C6: Netflix Content Analytics – Interactive Excel Dashboard
B7: Prepared by | C7: [Your Name]
B8: Enrollment / Roll No. | C8: [Roll Number]
B9: Course / Department | C9: [Course – Final Year]
B10: Guide / Supervisor | C10: [Guide Name]
B11: Academic year | C11: [20XX – 20XX]
B13: OBJECTIVE
B14: Aim | C14: To analyse Netflix's catalogue of Movies and TV Shows – what is available, where it comes from, who it is made for and how it has grown – using an interactive Excel dashboard.
B15: Dataset | C15: netflix_titles.csv – 8,807 titles × 12 columns (type, title, director, cast, country, date added, release year, rating, duration, genres, description).
B17: HOW TO USE THE DASHBOARD
B18: 1. Filters | C18: On the Dashboard use the six drop-downs (Type, Audience, Country, Genre, Release-year from / to). Every KPI, chart and insight updates instantly.
B19: 2. Reset | C19: Set Type / Audience / Country / Genre back to 'All' and the years to 1925 – 2021.
B20: 3. Title Explorer | C20: Look up any title for full details, or press F9 on that sheet for a random pick.
B21: 4. Navigation | C21: Use the links in the Dashboard header to jump between sheets.
B23: SHEETS
B24: Dashboard | C24: Presentation layer – filters, 6 KPI cards, 11 charts and auto-generated insights.
B25: Title Explorer | C25: Search-by-title card built with MATCH / INDEX, plus a random-title generator.
B26: Analysis | C26: Calculation engine – all summary tables (COUNTIFS) that feed the charts; includes Top-10 ranking tables.
B27: Data | C27: Cleaned dataset + 9 helper columns (red headers) built with formulas.
B28: Lists | C28: Source lists for drop-downs and the rating → audience-group mapping table.
B30: EXCEL TECHNIQUES USED
B31: Formulas | C31: COUNTIFS (multi-criteria with wildcards), AVERAGEIFS, INDEX / MATCH, LARGE, VLOOKUP, SUBSTITUTE, TEXT, IFERROR, RANDBETWEEN, YEAR, MONTH
B32: Named ranges | C32: Data columns (d_type, d_ry, d_genre …) and filter criteria (c_type, c_from …) keep formulas short and readable
B33: Dynamic Top-10 | C33: Score column with a row-based tie-breaker + LARGE / MATCH → live-ranked tables without dynamic-array functions (works in every Excel version)
B34: Multi-value fields | C34: Country, genre, director and cast are pipe-delimited ('|Drama|Comedy|') in helper columns so a title counts once for EACH country / genre / person
B35: Data validation | C35: Drop-down filters (named lists) and the title search box
B36: Conditional formatting | C36: Active filters turn pink; data-bars on ranking tables
B37: Charts | C37: Line, doughnut, column and bar charts linked to formula ranges, so they react to the filters
B38: Navigation & printing | C38: Internal hyperlinks, frozen filter bar, landscape fit-to-width print setup
B40: DATA CLEANING STEPS
B41: Missing director / cast / country | C41: Replaced blanks with 'Unknown' (director 2,634; cast 825; country 831 records).
B42: Date added | C42: Text such as 'September 25, 2021' converted to real Excel dates (10 records have no date and are excluded from year/month charts only).
B43: Rating column errors | C43: 3 records had runtime values (e.g. '74 min') in the rating field – moved to duration, rating set to 'Not Rated'; 4 blank ratings also set to 'Not Rated'.
B44: Rating groups | C44: Kids (TV-Y, TV-Y7, TV-G, G) · Older Kids (TV-PG, PG) · Teens (TV-14, PG-13) · Adults (TV-MA, R, NC-17) · Not Rated (NR, UR). Editable in Lists!F:G.
B45: Whitespace | C45: Leading / trailing spaces and stray commas trimmed from text fields.
B47: NOTES & LIMITATIONS
B48: Directors / actors | C48: Ranked from the 30 most frequent directors and 40 most frequent actors in the full dataset (counting every name across all rows would need dynamic arrays); the Top-10 shown is live-ranked within those candidates.
B49: Country attribution | C49: A co-production is counted once for each credited country, so country totals add up to more than the number of titles.
B50: {=B1:C50} -> 0 | C50: Data runs to 2021; 'date added' ranges 2008 – 2021.

Sheet DASHBOARD
B1: NETFLIX CONTENT ANALYTICS DASHBOARD
B2: Interactive insights on 8,800+ Movies & TV Shows | use the filters below to slice every KPI and chart | R2: Title Explorer | T2: Analysis | V2: Data | X2: About
B4: ▼ TYPE | F4: ▼ AUDIENCE (RATING GROUP) | J4: ▼ COUNTRY | N4: ▼ GENRE | R4: ▼ RELEASE YEAR FROM | V4: ▼ RELEASE YEAR TO
B5: Movie | F5: Teens | J5: India | N5: Action & Adventure | R5: 1925 | V5: 2017
B8: TOTAL TITLES | F8: MOVIES | J8: TV SHOWS | N8: COUNTRIES | R8: AVG MOVIE LENGTH | V8: AVG TV SEASONS
B9: =Analysis!$C$15 -> 92 | F9: =Analysis!$C$13 -> 92 | J9: =Analysis!$C$14 -> 0 | N9: =COUNTIFS(Analysis!$C$104:$C$226,">0",Analysis!$B$104:$B$226,"<>Unknown") -> 5 | R9: =Analysis!$C$96 -> 144 | V9: =Analysis!$C$97 -> n/a
B11: =TEXT($R$5,"0")&" – "&TEXT($V$5,"0")&" releases" -> 1925 – 2017 releases | F11: =TEXT(Analysis!$D$13,"0.0%")&" of view" -> 100.0% of view | J11: =TEXT(Analysis!$D$14,"0.0%")&" of view" -> 0.0% of view | N11: =IF(Analysis!$B$230="","–","Top: "&Analysis!$B$230) -> Top: India | R11: ="minutes per movie" -> minutes per movie | V11: ="seasons per show" -> seasons per show
B13: TRENDS & MIX
B29: GEOGRAPHY, GENRE & RELEASE ERA
B46: WHEN & HOW LONG
B63: TALENT SPOTLIGHT

Sheet Title Explorer
B1: TITLE EXPLORER | Z1: =IFERROR(MATCH($B$6,d_title,0),0) -> 3686
B2: ← Back to Dashboard
B5: ▼ PICK OR TYPE A TITLE (exact name, any letter case) — click the cell, then the arrow
B6: Stranger Things
B7: =IF(ISNUMBER(MATCH($B$6,d_title,0)),"✔ Match found","✖ Title not found – check spelling or pick from the dropdown") -> ✔ Match found
B9: Title | C9: =IF($Z$1=0,"–",INDEX(Data!$C$2:$C$8808,$Z$1)) -> Stranger Things
B10: Type | C10: =IF($Z$1=0,"–",INDEX(Data!$B$2:$B$8808,$Z$1)) -> TV Show
B11: Release year | C11: =IF($Z$1=0,"–",INDEX(Data!$H$2:$H$8808,$Z$1)) -> 2019
B12: Added to Netflix | C12: =IF($Z$1=0,"–",IF(INDEX(Data!$G$2:$G$8808,$Z$1)="","Unknown",INDEX(Data!$G$2:$G$8808,$Z$1))) -> 43650
B13: Rating | C13: =IF($Z$1=0,"–",INDEX(Data!$I$2:$I$8808,$Z$1)) -> TV-14
B14: Audience group | C14: =IF($Z$1=0,"–",INDEX(Data!$O$2:$O$8808,$Z$1)) -> Teens
B15: Duration | C15: =IF($Z$1=0,"–",INDEX(Data!$J$2:$J$8808,$Z$1)) -> 3 Seasons
B16: Country | C16: =IF($Z$1=0,"–",INDEX(Data!$F$2:$F$8808,$Z$1)) -> United States
B17: Director | C17: =IF($Z$1=0,"–",INDEX(Data!$D$2:$D$8808,$Z$1)) -> Unknown
B18: Cast | C18: =IF($Z$1=0,"–",INDEX(Data!$E$2:$E$8808,$Z$1)) -> Winona Ryder, David Harbour, Finn Wolfhard, Millie Bobby Brown, Gaten Matarazzo, Caleb McLaughlin, Natalia Dyer, Charlie Heaton, Cara Buono, Noah Schnapp, Matthew Modine, Joe Keery, Dacre Montgomery, Sadie Sink, Paul Reiser, Sean Astin
B19: Genres | C19: =IF($Z$1=0,"–",INDEX(Data!$K$2:$K$8808,$Z$1)) -> TV Horror, TV Mysteries, TV Sci-Fi & Fantasy
B20: Description | C20: =IF($Z$1=0,"–",INDEX(Data!$L$2:$L$8808,$Z$1)) -> When a young boy vanishes, a small town uncovers a mystery involving secret experiments, terrifying supernatural forces and one strange little girl.

Sheet Analysis
B1: ANALYSIS ENGINE | every table recalculates from the Dashboard filters
B2: ← Back to Dashboard
B3: FILTER CRITERIA (read from Dashboard)
B4: Type | C4: =IF(DASHBOARD!$B$5="All","*",DASHBOARD!$B$5) -> Movie
B5: Rating group | C5: =IF(DASHBOARD!$F$5="All","*",DASHBOARD!$F$5) -> Teens
B6: Country (key) | C6: =IF(DASHBOARD!$J$5="All","*","*|"&DASHBOARD!$J$5&"|*") -> *|India|*
B7: Genre (key) | C7: =IF(DASHBOARD!$N$5="All","*","*|"&DASHBOARD!$N$5&"|*") -> *|Action & Adventure|*
B8: Release year ≥ | C8: =">="&DASHBOARD!$R$5 -> >=1925
B9: Release year ≤ | C9: ="<="&DASHBOARD!$V$5 -> <=2017
B11: 1 · CONTENT TYPE
B12: Type | C12: Titles | D12: Share
B13: Movie | C13: =COUNTIFS(d_type,c_type,d_rg,c_rg,d_ctry,c_country,d_genre,c_genre,d_ry,c_from,d_ry,c_to,d_type,"Movie") -> 92 | D13: =IFERROR(C13/SUM($C$13:$C$14),0) -> 1
B14: TV Show | C14: =COUNTIFS(d_type,c_type,d_rg,c_rg,d_ctry,c_country,d_genre,c_genre,d_ry,c_from,d_ry,c_to,d_type,"TV Show") -> 0 | D14: =IFERROR(C14/SUM($C$13:$C$14),0) -> 0
B15: Total (current view) | C15: =SUM(C13:C14) -> 92
B16: All titles (no filter) | C16: =COUNTA(d_all) -> 8807
B19: 2 · AUDIENCE / RATING GROUP
B20: Group | C20: Titles | D20: Share
B21: Adults | C21: =COUNTIFS(d_type,c_type,d_rg,c_rg,d_ctry,c_country,d_genre,c_genre,d_ry,c_from,d_ry,c_to,d_rg,"Adults") -> 0 | D21: =IFERROR(C21/SUM($C$21:$C$25),0) -> 0
B22: Teens | C22: =COUNTIFS(d_type,c_type,d_rg,c_rg,d_ctry,c_country,d_genre,c_genre,d_ry,c_from,d_ry,c_to,d_rg,"Teens") -> 92 | D22: =IFERROR(C22/SUM($C$21:$C$25),0) -> 1
B23: Older Kids | C23: =COUNTIFS(d_type,c_type,d_rg,c_rg,d_ctry,c_country,d_genre,c_genre,d_ry,c_from,d_ry,c_to,d_rg,"Older Kids") -> 0 | D23: =IFERROR(C23/SUM($C$21:$C$25),0) -> 0
B24: Kids | C24: =COUNTIFS(d_type,c_type,d_rg,c_rg,d_ctry,c_country,d_genre,c_genre,d_ry,c_from,d_ry,c_to,d_rg,"Kids") -> 0 | D24: =IFERROR(C24/SUM($C$21:$C$25),0) -> 0
B25: Not Rated | C25: =COUNTIFS(d_type,c_type,d_rg,c_rg,d_ctry,c_country,d_genre,c_genre,d_ry,c_from,d_ry,c_to,d_rg,"Not Rated") -> 0 | D25: =IFERROR(C25/SUM($C$21:$C$25),0) -> 0
B28: 3 · TITLES ADDED PER YEAR
B29: Year Added | C29: Movies | D29: TV Shows | E29: Total
B30: 2008 | C30: =COUNTIFS(d_type,c_type,d_rg,c_rg,d_ctry,c_country,d_genre,c_genre,d_ry,c_from,d_ry,c_to,d_ya,$B30,d_type,"Movie") -> 0 | D30: =COUNTIFS(d_type,c_type,d_rg,c_rg,d_ctry,c_country,d_genre,c_genre,d_ry,c_from,d_ry,c_to,d_ya,$B30,d_type,"TV Show") -> 0 | E30: =C30+D30 -> 0
B31: 2009 | C31: =COUNTIFS(d_type,c_type,d_rg,c_rg,d_ctry,c_country,d_genre,c_genre,d_ry,c_from,d_ry,c_to,d_ya,$B31,d_type,"Movie") -> 0 | D31: =COUNTIFS(d_type,c_type,d_rg,c_rg,d_ctry,c_country,d_genre,c_genre,d_ry,c_from,d_ry,c_to,d_ya,$B31,d_type,"TV Show") -> 0 | E31: =C31+D31 -> 0
B32: 2010 | C32: =COUNTIFS(d_type,c_type,d_rg,c_rg,d_ctry,c_country,d_genre,c_genre,d_ry,c_from,d_ry,c_to,d_ya,$B32,d_type,"Movie") -> 0 | D32: =COUNTIFS(d_type,c_type,d_rg,c_rg,d_ctry,c_country,d_genre,c_genre,d_ry,c_from,d_ry,c_to,d_ya,$B32,d_type,"TV Show") -> 0 | E32: =C32+D32 -> 0
B33: 2011 | C33: =COUNTIFS(d_type,c_type,d_rg,c_rg,d_ctry,c_country,d_genre,c_genre,d_ry,c_from,d_ry,c_to,d_ya,$B33,d_type,"Movie") -> 0 | D33: =COUNTIFS(d_type,c_type,d_rg,c_rg,d_ctry,c_country,d_genre,c_genre,d_ry,c_from,d_ry,c_to,d_ya,$B33,d_type,"TV Show") -> 0 | E33: =C33+D33 -> 0
B34: 2012 | C34: =COUNTIFS(d_type,c_type,d_rg,c_rg,d_ctry,c_country,d_genre,c_genre,d_ry,c_from,d_ry,c_to,d_ya,$B34,d_type,"Movie") -> 0 | D34: =COUNTIFS(d_type,c_type,d_rg,c_rg,d_ctry,c_country,d_genre,c_genre,d_ry,c_from,d_ry,c_to,d_ya,$B34,d_type,"TV Show") -> 0 | E34: =C34+D34 -> 0
B35: 2013 | C35: =COUNTIFS(d_type,c_type,d_rg,c_rg,d_ctry,c_country,d_genre,c_genre,d_ry,c_from,d_ry,c_to,d_ya,$B35,d_type,"Movie") -> 0 | D35: =COUNTIFS(d_type,c_type,d_rg,c_rg,d_ctry,c_country,d_genre,c_genre,d_ry,c_from,d_ry,c_to,d_ya,$B35,d_type,"TV Show") -> 0 | E35: =C35+D35 -> 0
B36: 2014 | C36: =COUNTIFS(d_type,c_type,d_rg,c_rg,d_ctry,c_country,d_genre,c_genre,d_ry,c_from,d_ry,c_to,d_ya,$B36,d_type,"Movie") -> 0 | D36: =COUNTIFS(d_type,c_type,d_rg,c_rg,d_ctry,c_country,d_genre,c_genre,d_ry,c_from,d_ry,c_to,d_ya,$B36,d_type,"TV Show") -> 0 | E36: =C36+D36 -> 0
B37: 2015 | C37: =COUNTIFS(d_type,c_type,d_rg,c_rg,d_ctry,c_country,d_genre,c_genre,d_ry,c_from,d_ry,c_to,d_ya,$B37,d_type,"Movie") -> 0 | D37: =COUNTIFS(d_type,c_type,d_rg,c_rg,d_ctry,c_country,d_genre,c_genre,d_ry,c_from,d_ry,c_to,d_ya,$B37,d_type,"TV Show") -> 0 | E37: =C37+D37 -> 0
B38: 2016 | C38: =COUNTIFS(d_type,c_type,d_rg,c_rg,d_ctry,c_country,d_genre,c_genre,d_ry,c_from,d_ry,c_to,d_ya,$B38,d_type,"Movie") -> 0 | D38: =COUNTIFS(d_type,c_type,d_rg,c_rg,d_ctry,c_country,d_genre,c_genre,d_ry,c_from,d_ry,c_to,d_ya,$B38,d_type,"TV Show") -> 0 | E38: =C38+D38 -> 0
B39: 2017 | C39: =COUNTIFS(d_type,c_type,d_rg,c_rg,d_ctry,c_country,d_genre,c_genre,d_ry,c_from,d_ry,c_to,d_ya,$B39,d_type,"Movie") -> 20 | D39: =COUNTIFS(d_type,c_type,d_rg,c_rg,d_ctry,c_country,d_genre,c_genre,d_ry,c_from,d_ry,c_to,d_ya,$B39,d_type,"TV Show") -> 0 | E39: =C39+D39 -> 20
B40: 2018 | C40: =COUNTIFS(d_type,c_type,d_rg,c_rg,d_ctry,c_country,d_genre,c_genre,d_ry,c_from,d_ry,c_to,d_ya,$B40,d_type,"Movie") -> 38 | D40: =COUNTIFS(d_type,c_type,d_rg,c_rg,d_ctry,c_country,d_genre,c_genre,d_ry,c_from,d_ry,c_to,d_ya,$B40,d_type,"TV Show") -> 0 | E40: =C40+D40 -> 38
B41: 2019 | C41: =COUNTIFS(d_type,c_type,d_rg,c_rg,d_ctry,c_country,d_genre,c_genre,d_ry,c_from,d_ry,c_to,d_ya,$B41,d_type,"Movie") -> 11 | D41: =COUNTIFS(d_type,c_type,d_rg,c_rg,d_ctry,c_country,d_genre,c_genre,d_ry,c_from,d_ry,c_to,d_ya,$B41,d_type,"TV Show") -> 0 | E41: =C41+D41 -> 11
... B43: 2021 | C43: =COUNTIFS(d_type,c_type,d_rg,c_rg,d_ctry,c_country,d_genre,c_genre,d_ry,c_from,d_ry,c_to,d_ya,$B43,d_type,"Movie") -> 7 | D43: =COUNTIFS(d_type,c_type,d_rg,c_rg,d_ctry,c_country,d_genre,c_genre,d_ry,c_from,d_ry,c_to,d_ya,$B43,d_type,"TV Show") -> 0 | E43: =C43+D43 -> 7
B46: 4 · TITLES BY RELEASE YEAR
B47: Label | C47: From | D47: To | E47: Titles
B48: <2010 | C48: 0 | D48: 2009 | E48: =COUNTIFS(d_type,c_type,d_rg,c_rg,d_ctry,c_country,d_genre,c_genre,d_ry,c_from,d_ry,c_to,d_ry,">="&C48,d_ry,"<="&D48) -> 37
B49: 2010 | C49: 2010 | D49: 2010 | E49: =COUNTIFS(d_type,c_type,d_rg,c_rg,d_ctry,c_country,d_genre,c_genre,d_ry,c_from,d_ry,c_to,d_ry,">="&C49,d_ry,"<="&D49) -> 1
B50: 2011 | C50: 2011 | D50: 2011 | E50: =COUNTIFS(d_type,c_type,d_rg,c_rg,d_ctry,c_country,d_genre,c_genre,d_ry,c_from,d_ry,c_to,d_ry,">="&C50,d_ry,"<="&D50) -> 8
B51: 2012 | C51: 2012 | D51: 2012 | E51: =COUNTIFS(d_type,c_type,d_rg,c_rg,d_ctry,c_country,d_genre,c_genre,d_ry,c_from,d_ry,c_to,d_ry,">="&C51,d_ry,"<="&D51) -> 5
B52: 2013 | C52: 2013 | D52: 2013 | E52: =COUNTIFS(d_type,c_type,d_rg,c_rg,d_ctry,c_country,d_genre,c_genre,d_ry,c_from,d_ry,c_to,d_ry,">="&C52,d_ry,"<="&D52) -> 8
B53: 2014 | C53: 2014 | D53: 2014 | E53: =COUNTIFS(d_type,c_type,d_rg,c_rg,d_ctry,c_country,d_genre,c_genre,d_ry,c_from,d_ry,c_to,d_ry,">="&C53,d_ry,"<="&D53) -> 6
B54: 2015 | C54: 2015 | D54: 2015 | E54: =COUNTIFS(d_type,c_type,d_rg,c_rg,d_ctry,c_country,d_genre,c_genre,d_ry,c_from,d_ry,c_to,d_ry,">="&C54,d_ry,"<="&D54) -> 7
B55: 2016 | C55: 2016 | D55: 2016 | E55: =COUNTIFS(d_type,c_type,d_rg,c_rg,d_ctry,c_country,d_genre,c_genre,d_ry,c_from,d_ry,c_to,d_ry,">="&C55,d_ry,"<="&D55) -> 9
B56: 2017 | C56: 2017 | D56: 2017 | E56: =COUNTIFS(d_type,c_type,d_rg,c_rg,d_ctry,c_country,d_genre,c_genre,d_ry,c_from,d_ry,c_to,d_ry,">="&C56,d_ry,"<="&D56) -> 11
B57: 2018 | C57: 2018 | D57: 2018 | E57: =COUNTIFS(d_type,c_type,d_rg,c_rg,d_ctry,c_country,d_genre,c_genre,d_ry,c_from,d_ry,c_to,d_ry,">="&C57,d_ry,"<="&D57) -> 0
B58: 2019 | C58: 2019 | D58: 2019 | E58: =COUNTIFS(d_type,c_type,d_rg,c_rg,d_ctry,c_country,d_genre,c_genre,d_ry,c_from,d_ry,c_to,d_ry,">="&C58,d_ry,"<="&D58) -> 0
B59: 2020 | C59: 2020 | D59: 2020 | E59: =COUNTIFS(d_type,c_type,d_rg,c_rg,d_ctry,c_country,d_genre,c_genre,d_ry,c_from,d_ry,c_to,d_ry,">="&C59,d_ry,"<="&D59) -> 0
B60: 2021 | C60: 2021 | D60: 2021 | E60: =COUNTIFS(d_type,c_type,d_rg,c_rg,d_ctry,c_country,d_genre,c_genre,d_ry,c_from,d_ry,c_to,d_ry,">="&C60,d_ry,"<="&D60) -> 0
B62: 5 · TITLES ADDED BY MONTH
B63: Month | C63: No. | D63: Titles
B64: Jan | C64: 1 | D64: =COUNTIFS(d_type,c_type,d_rg,c_rg,d_ctry,c_country,d_genre,c_genre,d_ry,c_from,d_ry,c_to,d_mo,C64) -> 2
B65: Feb | C65: 2 | D65: =COUNTIFS(d_type,c_type,d_rg,c_rg,d_ctry,c_country,d_genre,c_genre,d_ry,c_from,d_ry,c_to,d_mo,C65) -> 5
B66: Mar | C66: 3 | D66: =COUNTIFS(d_type,c_type,d_rg,c_rg,d_ctry,c_country,d_genre,c_genre,d_ry,c_from,d_ry,c_to,d_mo,C66) -> 8
B67: Apr | C67: 4 | D67: =COUNTIFS(d_type,c_type,d_rg,c_rg,d_ctry,c_country,d_genre,c_genre,d_ry,c_from,d_ry,c_to,d_mo,C67) -> 8
B68: May | C68: 5 | D68: =COUNTIFS(d_type,c_type,d_rg,c_rg,d_ctry,c_country,d_genre,c_genre,d_ry,c_from,d_ry,c_to,d_mo,C68) -> 6
B69: Jun | C69: 6 | D69: =COUNTIFS(d_type,c_type,d_rg,c_rg,d_ctry,c_country,d_genre,c_genre,d_ry,c_from,d_ry,c_to,d_mo,C69) -> 2
B70: Jul | C70: 7 | D70: =COUNTIFS(d_type,c_type,d_rg,c_rg,d_ctry,c_country,d_genre,c_genre,d_ry,c_from,d_ry,c_to,d_mo,C70) -> 6
B71: Aug | C71: 8 | D71: =COUNTIFS(d_type,c_type,d_rg,c_rg,d_ctry,c_country,d_genre,c_genre,d_ry,c_from,d_ry,c_to,d_mo,C71) -> 13
B72: Sep | C72: 9 | D72: =COUNTIFS(d_type,c_type,d_rg,c_rg,d_ctry,c_country,d_genre,c_genre,d_ry,c_from,d_ry,c_to,d_mo,C72) -> 6
B73: Oct | C73: 10 | D73: =COUNTIFS(d_type,c_type,d_rg,c_rg,d_ctry,c_country,d_genre,c_genre,d_ry,c_from,d_ry,c_to,d_mo,C73) -> 17
B74: Nov | C74: 11 | D74: =COUNTIFS(d_type,c_type,d_rg,c_rg,d_ctry,c_country,d_genre,c_genre,d_ry,c_from,d_ry,c_to,d_mo,C74) -> 8
B75: Dec | C75: 12 | D75: =COUNTIFS(d_type,c_type,d_rg,c_rg,d_ctry,c_country,d_genre,c_genre,d_ry,c_from,d_ry,c_to,d_mo,C75) -> 11
B78: 6 · MOVIE RUNTIME BANDS (minutes)
B79: Band | C79: From | D79: To | E79: Movies
B80: < 60 min | C80: 0 | D80: 59 | E80: =COUNTIFS(d_type,c_type,d_rg,c_rg,d_ctry,c_country,d_genre,c_genre,d_ry,c_from,d_ry,c_to,d_type,"Movie",d_dv,">="&C80,d_dv,"<="&D80) -> 0
B81: 60-89 | C81: 60 | D81: 89 | E81: =COUNTIFS(d_type,c_type,d_rg,c_rg,d_ctry,c_country,d_genre,c_genre,d_ry,c_from,d_ry,c_to,d_type,"Movie",d_dv,">="&C81,d_dv,"<="&D81) -> 0
B82: 90-119 | C82: 90 | D82: 119 | E82: =COUNTIFS(d_type,c_type,d_rg,c_rg,d_ctry,c_country,d_genre,c_genre,d_ry,c_from,d_ry,c_to,d_type,"Movie",d_dv,">="&C82,d_dv,"<="&D82) -> 10
B83: 120-149 | C83: 120 | D83: 149 | E83: =COUNTIFS(d_type,c_type,d_rg,c_rg,d_ctry,c_country,d_genre,c_genre,d_ry,c_from,d_ry,c_to,d_type,"Movie",d_dv,">="&C83,d_dv,"<="&D83) -> 47
B84: 150-179 | C84: 150 | D84: 179 | E84: =COUNTIFS(d_type,c_type,d_rg,c_rg,d_ctry,c_country,d_genre,c_genre,d_ry,c_from,d_ry,c_to,d_type,"Movie",d_dv,">="&C84,d_dv,"<="&D84) -> 34
B85: 180+ | C85: 180 | D85: 9999 | E85: =COUNTIFS(d_type,c_type,d_rg,c_rg,d_ctry,c_country,d_genre,c_genre,d_ry,c_from,d_ry,c_to,d_type,"Movie",d_dv,">="&C85,d_dv,"<="&D85) -> 1
B87: 7 · TV SHOW SEASONS
B88: Band | C88: From | D88: To | E88: TV Shows
B89: 1 Season | C89: 1 | D89: 1 | E89: =COUNTIFS(d_type,c_type,d_rg,c_rg,d_ctry,c_country,d_genre,c_genre,d_ry,c_from,d_ry,c_to,d_type,"TV Show",d_dv,">="&C89,d_dv,"<="&D89) -> 0
B90: 2 Seasons | C90: 2 | D90: 2 | E90: =COUNTIFS(d_type,c_type,d_rg,c_rg,d_ctry,c_country,d_genre,c_genre,d_ry,c_from,d_ry,c_to,d_type,"TV Show",d_dv,">="&C90,d_dv,"<="&D90) -> 0
B91: 3 Seasons | C91: 3 | D91: 3 | E91: =COUNTIFS(d_type,c_type,d_rg,c_rg,d_ctry,c_country,d_genre,c_genre,d_ry,c_from,d_ry,c_to,d_type,"TV Show",d_dv,">="&C91,d_dv,"<="&D91) -> 0
B92: 4 Seasons | C92: 4 | D92: 4 | E92: =COUNTIFS(d_type,c_type,d_rg,c_rg,d_ctry,c_country,d_genre,c_genre,d_ry,c_from,d_ry,c_to,d_type,"TV Show",d_dv,">="&C92,d_dv,"<="&D92) -> 0
B93: 5+ Seasons | C93: 5 | D93: 99 | E93: =COUNTIFS(d_type,c_type,d_rg,c_rg,d_ctry,c_country,d_genre,c_genre,d_ry,c_from,d_ry,c_to,d_type,"TV Show",d_dv,">="&C93,d_dv,"<="&D93) -> 0
B95: 8 · AVERAGES
B96: Avg movie runtime (min) | C96: =IFERROR(ROUND(AVERAGEIFS(d_dv,d_type,"Movie",d_type,c_type,d_rg,c_rg,d_ctry,c_country,d_genre,c_genre,d_ry,c_from,d_ry,c_to),0),"n/a") -> 144
B97: Avg TV seasons | C97: =IFERROR(ROUND(AVERAGEIFS(d_dv,d_type,"TV Show",d_type,c_type,d_rg,c_rg,d_ctry,c_country,d_genre,c_genre,d_ry,c_from,d_ry,c_to),1),"n/a") -> n/a
B102: 9 · COUNTRIES
B103: Country | C103: Titles | D103: Score
B104: United States | C104: =COUNTIFS(d_type,c_type,d_rg,c_rg,d_ctry,c_country,d_genre,c_genre,d_ry,c_from,d_ry,c_to,d_ctry,"*|"&B104&"|*") -> 2 | D104: =IF(B104="Unknown",-1,C104)-ROW()/1000000 -> 1.999896
B105: India | C105: =COUNTIFS(d_type,c_type,d_rg,c_rg,d_ctry,c_country,d_genre,c_genre,d_ry,c_from,d_ry,c_to,d_ctry,"*|"&B105&"|*") -> 92 | D105: =IF(B105="Unknown",-1,C105)-ROW()/1000000 -> 91.999895
B106: Unknown | C106: =COUNTIFS(d_type,c_type,d_rg,c_rg,d_ctry,c_country,d_genre,c_genre,d_ry,c_from,d_ry,c_to,d_ctry,"*|"&B106&"|*") -> 0 | D106: =IF(B106="Unknown",-1,C106)-ROW()/1000000 -> -1.000106
B107: United Kingdom | C107: =COUNTIFS(d_type,c_type,d_rg,c_rg,d_ctry,c_country,d_genre,c_genre,d_ry,c_from,d_ry,c_to,d_ctry,"*|"&B107&"|*") -> 0 | D107: =IF(B107="Unknown",-1,C107)-ROW()/1000000 -> -0.000107
B108: Canada | C108: =COUNTIFS(d_type,c_type,d_rg,c_rg,d_ctry,c_country,d_genre,c_genre,d_ry,c_from,d_ry,c_to,d_ctry,"*|"&B108&"|*") -> 1 | D108: =IF(B108="Unknown",-1,C108)-ROW()/1000000 -> 0.999892
B109: France | C109: =COUNTIFS(d_type,c_type,d_rg,c_rg,d_ctry,c_country,d_genre,c_genre,d_ry,c_from,d_ry,c_to,d_ctry,"*|"&B109&"|*") -> 0 | D109: =IF(B109="Unknown",-1,C109)-ROW()/1000000 -> -0.000109
B110: Japan | C110: =COUNTIFS(d_type,c_type,d_rg,c_rg,d_ctry,c_country,d_genre,c_genre,d_ry,c_from,d_ry,c_to,d_ctry,"*|"&B110&"|*") -> 0 | D110: =IF(B110="Unknown",-1,C110)-ROW()/1000000 -> -0.00011
B111: Spain | C111: =COUNTIFS(d_type,c_type,d_rg,c_rg,d_ctry,c_country,d_genre,c_genre,d_ry,c_from,d_ry,c_to,d_ctry,"*|"&B111&"|*") -> 0 | D111: =IF(B111="Unknown",-1,C111)-ROW()/1000000 -> -0.000111
B112: South Korea | C112: =COUNTIFS(d_type,c_type,d_rg,c_rg,d_ctry,c_country,d_genre,c_genre,d_ry,c_from,d_ry,c_to,d_ctry,"*|"&B112&"|*") -> 0 | D112: =IF(B112="Unknown",-1,C112)-ROW()/1000000 -> -0.000112
B113: Germany | C113: =COUNTIFS(d_type,c_type,d_rg,c_rg,d_ctry,c_country,d_genre,c_genre,d_ry,c_from,d_ry,c_to,d_ctry,"*|"&B113&"|*") -> 1 | D113: =IF(B113="Unknown",-1,C113)-ROW()/1000000 -> 0.999887
B114: Mexico | C114: =COUNTIFS(d_type,c_type,d_rg,c_rg,d_ctry,c_country,d_genre,c_genre,d_ry,c_from,d_ry,c_to,d_ctry,"*|"&B114&"|*") -> 0 | D114: =IF(B114="Unknown",-1,C114)-ROW()/1000000 -> -0.000114
B115: China | C115: =COUNTIFS(d_type,c_type,d_rg,c_rg,d_ctry,c_country,d_genre,c_genre,d_ry,c_from,d_ry,c_to,d_ctry,"*|"&B115&"|*") -> 0 | D115: =IF(B115="Unknown",-1,C115)-ROW()/1000000 -> -0.000115
... B226: Montenegro | C226: =COUNTIFS(d_type,c_type,d_rg,c_rg,d_ctry,c_country,d_genre,c_genre,d_ry,c_from,d_ry,c_to,d_ctry,"*|"&B226&"|*") -> 0 | D226: =IF(B226="Unknown",-1,C226)-ROW()/1000000 -> -0.000226
B228: 9 · TOP 10
...

Sheet Data
A1: show_id | B1: type | C1: title | D1: director | E1: cast | F1: country | G1: date_added | H1: release_year | I1: rating | J1: duration | K1: listed_in | L1: description | M1: Year Added | N1: Month Added | O1: Rating Group | P1: Duration Value | Q1: Primary Country | R1: Countries Key | S1: Genres Key | T1: Directors Key | U1: Cast Key
A2: s1 | B2: Movie | C2: Dick Johnson Is Dead | D2: Kirsten Johnson | E2: Unknown | F2: United States | G2: 44464 | H2: 2020 | I2: PG-13 | J2: 90 min | K2: Documentaries | L2: As her father nears the end of his life, filmmaker Kirsten Johnson stages his death in inventive and comical ways to help them both face the inevitable. | M2: =IF(G2="","",YEAR(G2)) -> 2021 | N2: =IF(G2="","",MONTH(G2)) -> 9 | O2: =IFERROR(VLOOKUP(I2,Lists!$F$2:$G$16,2,FALSE()),"Not Rated") -> Teens | P2: =IFERROR(VALUE(LEFT(J2,FIND(" ",J2)-1)),"") -> 90 | Q2: =IFERROR(LEFT(F2,FIND(",",F2)-1),F2) -> United States | R2: ="|"&SUBSTITUTE(F2,", ","|")&"|" -> |United States| | S2: ="|"&SUBSTITUTE(K2,", ","|")&"|" -> |Documentaries| | T2: ="|"&SUBSTITUTE(D2,", ","|")&"|" -> |Kirsten Johnson| | U2: ="|"&SUBSTITUTE(E2,", ","|")&"|" -> |Unknown|
A3: s2 | B3: TV Show | C3: Blood & Water | D3: Unknown | E3: Ama Qamata, Khosi Ngema, Gail Mabalane, Thabang Molaba, Dillon Windvogel, Natasha Thahane, Arno Greeff, Xolile Tshabalala, Getmore Sithole, Cindy Mahlangu, Ryle De Morny, Greteli Fincham, Sello Maake Ka-Ncube, Odwa Gwanya, Mekaila Mathys, Sandi Schultz, Duane Williams, Shamilla Miller, Patrick Mofokeng | F3: South Africa | G3: 44463 | H3: 2021 | I3: TV-MA | J3: 2 Seasons | K3: International TV Shows, TV Dramas, TV Mysteries | L3: After crossing paths at a party, a Cape Town teen sets out to prove whether a private-school swimming star is her sister who was abducted at birth. | M3: =IF(G3="","",YEAR(G3)) -> 2021 | N3: =IF(G3="","",MONTH(G3)) -> 9 | O3: =IFERROR(VLOOKUP(I3,Lists!$F$2:$G$16,2,FALSE()),"Not Rated") -> Adults | P3: =IFERROR(VALUE(LEFT(J3,FIND(" ",J3)-1)),"") -> 2 | Q3: =IFERROR(LEFT(F3,FIND(",",F3)-1),F3) -> South Africa | R3: ="|"&SUBSTITUTE(F3,", ","|")&"|" -> |South Africa| | S3: ="|"&SUBSTITUTE(K3,", ","|")&"|" -> |International TV Shows|TV Dramas|TV Mysteries| | T3: ="|"&SUBSTITUTE(D3,", ","|")&"|" -> |Unknown| | U3: ="|"&SUBSTITUTE(E3,", ","|")&"|" -> |Ama Qamata|Khosi Ngema|Gail Mabalane|Thabang Molaba|Dillon Windvogel|Natasha Thahane|Arno Greeff|Xolile Tshabalala|Getmore Sithole|Cindy Mahlangu|Ryle De Morny|Greteli Fincham|Sello Maake Ka-Ncube|Odwa Gwanya|Mekaila Mathys|Sandi Schultz|Duane Williams|Shamilla Miller|Patrick Mofokeng|
A4: s3 | B4: TV Show | C4: Ganglands | D4: Julien Leclercq | E4: Sami Bouajila, Tracy Gotoas, Samuel Jouy, Nabiha Akkari, Sofia Lesaffre, Salim Kechiouche, Noureddine Farihi, Geert Van Rampelberg, Bakary Diombera | F4: Unknown | G4: 44463 | H4: 2021 | I4: TV-MA | J4: 1 Season | K4: Crime TV Shows, International TV Shows, TV Action & Adventure | L4: To protect his family from a powerful drug lord, skilled thief Mehdi and his expert team of robbers are pulled into a violent and deadly turf war. | M4: =IF(G4="","",YEAR(G4)) -> 2021 | N4: =IF(G4="","",MONTH(G4)) -> 9 | O4: =IFERROR(VLOOKUP(I4,Lists!$F$2:$G$16,2,FALSE()),"Not Rated") -> Adults | P4: =IFERROR(VALUE(LEFT(J4,FIND(" ",J4)-1)),"") -> 1 | Q4: =IFERROR(LEFT(F4,FIND(",",F4)-1),F4) -> Unknown | R4: ="|"&SUBSTITUTE(F4,", ","|")&"|" -> |Unknown| | S4: ="|"&SUBSTITUTE(K4,", ","|")&"|" -> |Crime TV Shows|International TV Shows|TV Action & Adventure| | T4: ="|"&SUBSTITUTE(D4,", ","|")&"|" -> |Julien Leclercq| | U4: ="|"&SUBSTITUTE(E4,", ","|")&"|" -> |Sami Bouajila|Tracy Gotoas|Samuel Jouy|Nabiha Akkari|Sofia Lesaffre|Salim Kechiouche|Noureddine Farihi|Geert Van Rampelberg|Bakary Diombera|
A5: s4 | B5: TV Show | C5: Jailbirds New Orleans | D5: Unknown | E5: Unknown | F5: Unknown | G5: 44463 | H5: 2021 | I5: TV-MA | J5: 1 Season | K5: Docuseries, Reality TV | L5: Feuds, flirtations and toilet talk go down among the incarcerated women at the Orleans Justice Center in New Orleans on this gritty reality series. | M5: =IF(G5="","",YEAR(G5)) -> 2021 | N5: =IF(G5="","",MONTH(G5)) -> 9 | O5: =IFERROR(VLOOKUP(I5,Lists!$F$2:$G$16,2,FALSE()),"Not Rated") -> Adults | P5: =IFERROR(VALUE(LEFT(J5,FIND(" ",J5)-1)),"") -> 1 | Q5: =IFERROR(LEFT(F5,FIND(",",F5)-1),F5) -> Unknown | R5: ="|"&SUBSTITUTE(F5,", ","|")&"|" -> |Unknown| | S5: ="|"&SUBSTITUTE(K5,", ","|")&"|" -> |Docuseries|Reality TV| | T5: ="|"&SUBSTITUTE(D5,", ","|")&"|" -> |Unknown| | U5: ="|"&SUBSTITUTE(E5,", ","|")&"|" -> |Unknown|
A6: s5 | B6: TV Show | C6: Kota Factory | D6: Unknown | E6: Mayur More, Jitendra Kumar, Ranjan Raj, Alam Khan, Ahsaas Channa, Revathi Pillai, Urvi Singh, Arun Kumar | F6: India | G6: 44463 | H6: 2021 | I6: TV-MA | J6: 2 Seasons | K6: International TV Shows, Romantic TV Shows, TV Comedies | L6: In a city of coaching centers known to train India’s finest collegiate minds, an earnest but unexceptional student and his friends navigate campus life. | M6: =IF(G6="","",YEAR(G6)) -> 2021 | N6: =IF(G6="","",MONTH(G6)) -> 9 | O6: =IFERROR(VLOOKUP(I6,Lists!$F$2:$G$16,2,FALSE()),"Not Rated") -> Adults | P6: =IFERROR(VALUE(LEFT(J6,FIND(" ",J6)-1)),"") -> 2 | Q6: =IFERROR(LEFT(F6,FIND(",",F6)-1),F6) -> India | R6: ="|"&SUBSTITUTE(F6,", ","|")&"|" -> |India| | S6: ="|"&SUBSTITUTE(K6,", ","|")&"|" -> |International TV Shows|Romantic TV Shows|TV Comedies| | T6: ="|"&SUBSTITUTE(D6,", ","|")&"|" -> |Unknown| | U6: ="|"&SUBSTITUTE(E6,", ","|")&"|" -> |Mayur More|Jitendra Kumar|Ranjan Raj|Alam Khan|Ahsaas Channa|Revathi Pillai|Urvi Singh|Arun Kumar|
A7: s6 | B7: TV Show | C7: Midnight Mass | D7: Mike Flanagan | E7: Kate Siegel, Zach Gilford, Hamish Linklater, Henry Thomas, Kristin Lehman, Samantha Sloyan, Igby Rigney, Rahul Kohli, Annarah Cymone, Annabeth Gish, Alex Essoe, Rahul Abburi, Matt Biedel, Michael Trucco, Crystal Balint, Louis Oliver | F7: Unknown | G7: 44463 | H7: 2021 | I7: TV-MA | J7: 1 Season | K7: TV Dramas, TV Horror, TV Mysteries | L7: The arrival of a charismatic young priest brings glorious miracles, ominous mysteries and renewed religious fervor to a dying town desperate to believe. | M7: =IF(G7="","",YEAR(G7)) -> 2021 | N7: =IF(G7="","",MONTH(G7)) -> 9 | O7: =IFERROR(VLOOKUP(I7,Lists!$F$2:$G$16,2,FALSE()),"Not Rated") -> Adults | P7: =IFERROR(VALUE(LEFT(J7,FIND(" ",J7)-1)),"") -> 1 | Q7: =IFERROR(LEFT(F7,FIND(",",F7)-1),F7) -> Unknown | R7: ="|"&SUBSTITUTE(F7,", ","|")&"|" -> |Unknown| | S7: ="|"&SUBSTITUTE(K7,", ","|")&"|" -> |TV Dramas|TV Horror|TV Mysteries| | T7: ="|"&SUBSTITUTE(D7,", ","|")&"|" -> |Mike Flanagan| | U7: ="|"&SUBSTITUTE(E7,", ","|")&"|" -> |Kate Siegel|Zach Gilford|Hamish Linklater|Henry Thomas|Kristin Lehman|Samantha Sloyan|Igby Rigney|Rahul Kohli|Annarah Cymone|Annabeth Gish|Alex Essoe|Rahul Abburi|Matt Biedel|Michael Trucco|Crystal Balint|Louis Oliver|
A8: s7 | B8: Movie | C8: My Little Pony: A New Generation | D8: Robert Cullen, José Luis Ucha | E8: Vanessa Hudgens, Kimiko Glenn, James Marsden, Sofia Carson, Liza Koshy, Ken Jeong, Elizabeth Perkins, Jane Krakowski, Michael McKean, Phil LaMarr | F8: Unknown | G8: 44463 | H8: 2021 | I8: PG | J8: 91 min | K8: Children & Family Movies | L8: Equestria's divided. But a bright-eyed hero believes Earth Ponies, Pegasi and Unicorns should be pals — and, hoof to heart, she’s determined to prove it. | M8: =IF(G8="","",YEAR(G8)) -> 2021 | N8: =IF(G8="","",MONTH(G8)) -> 9 | O8: =IFERROR(VLOOKUP(I8,Lists!$F$2:$G$16,2,FALSE()),"Not Rated") -> Older Kids | P8: =IFERROR(VALUE(LEFT(J8,FIND(" ",J8)-1)),"") -> 91 | Q8: =IFERROR(LEFT(F8,FIND(",",F8)-1),F8) -> Unknown | R8: ="|"&SUBSTITUTE(F8,", ","|")&"|" -> |Unknown| | S8: ="|"&SUBSTITUTE(K8,", ","|")&"|" -> |Children & Family Movies| | T8: ="|"&SUBSTITUTE(D8,", ","|")&"|" -> |Robert Cullen|José Luis Ucha| | U8: ="|"&SUBSTITUTE(E8,", ","|")&"|" -> |Vanessa Hudgens|Kimiko Glenn|James Marsden|Sofia Carson|Liza Koshy|Ken Jeong|Elizabeth Perkins|Jane Krakowski|Michael McKean|Phil LaMarr|
A9: s8 | B9: Movie | C9: Sankofa | D9: Haile Gerima | E9: Kofi Ghanaba, Oyafunmike Ogunlano, Alexandra Duah, Nick Medley, Mutabaruka, Afemo Omilami, Reggie Carter, Mzuri | F9: United States, Ghana, Burkina Faso, United Kingdom, Germany, Ethiopia | G9: 44463 | H9: 1993 | I9: TV-MA | J9: 125 min | K9: Dramas, Independent Movies, International Movies | L9: On a photo shoot in Ghana, an American model slips back in time, becomes enslaved on a plantation and bears witness to the agony of her ancestral past. | M9: =IF(G9="","",YEAR(G9)) -> 2021 | N9: =IF(G9="","",MONTH(G9)) -> 9 | O9: =IFERROR(VLOOKUP(I9,Lists!$F$2:$G$16,2,FALSE()),"Not Rated") -> Adults | P9: =IFERROR(VALUE(LEFT(J9,FIND(" ",J9)-1)),"") -> 125 | Q9: =IFERROR(LEFT(F9,FIND(",",F9)-1),F9) -> United States | R9: ="|"&SUBSTITUTE(F9,", ","|")&"|" -> |United States|Ghana|Burkina Faso|United Kingdom|Germany|Ethiopia| | S9: ="|"&SUBSTITUTE(K9,", ","|")&"|" -> |Dramas|Independent Movies|International Movies| | T9: ="|"&SUBSTITUTE(D9,", ","|")&"|" -> |Haile Gerima| | U9: ="|"&SUBSTITUTE(E9,", ","|")&"|" -> |Kofi Ghanaba|Oyafunmike Ogunlano|Alexandra Duah|Nick Medley|Mutabaruka|Afemo Omilami|Reggie Carter|Mzuri|
A10: s9 | B10: TV Show | C10: The Great British Baking Show | D10: Andy Devonshire | E10: Mel Giedroyc, Sue Perkins, Mary Berry, Paul Hollywood | F10: United Kingdom | G10: 44463 | H10: 2021 | I10: TV-14 | J10: 9 Seasons | K10: British TV Shows, Reality TV | L10: A talented batch of amateur bakers face off in a 10-week competition, whipping up their best dishes in the hopes of being named the U.K.'s best. | M10: =IF(G10="","",YEAR(G10)) -> 2021 | N10: =IF(G10="","",MONTH(G10)) -> 9 | O10: =IFERROR(VLOOKUP(I10,Lists!$F$2:$G$16,2,FALSE()),"Not Rated") -> Teens | P10: =IFERROR(VALUE(LEFT(J10,FIND(" ",J10)-1)),"") -> 9 | Q10: =IFERROR(LEFT(F10,FIND(",",F10)-1),F10) -> United Kingdom | R10: ="|"&SUBSTITUTE(F10,", ","|")&"|" -> |United Kingdom| | S10: ="|"&SUBSTITUTE(K10,", ","|")&"|" -> |British TV Shows|Reality TV| | T10: ="|"&SUBSTITUTE(D10,", ","|")&"|" -> |Andy Devonshire| | U10: ="|"&SUBSTITUTE(E10,", ","|")&"|" -> |Mel Giedroyc|Sue Perkins|Mary Berry|Paul Hollywood|
A11: s10 | B11: Movie | C11: The Starling | D11: Theodore Melfi | E11: Melissa McCarthy, Chris O'Dowd, Kevin Kline, Timothy Olyphant, Daveed Diggs, Skyler Gisondo, Laura Harrier, Rosalind Chao, Kimberly Quinn, Loretta Devine, Ravi Kapoor | F11: United States | G11: 44463 | H11: 2021 | I11: PG-13 | J11: 104 min | K11: Comedies, Dramas | L11: A woman adjusting to life after a loss contends with a feisty bird that's taken over her garden — and a husband who's struggling to find a way forward. | M11: =IF(G11="","",YEAR(G11)) -> 2021 | N11: =IF(G11="","",MONTH(G11)) -> 9 | O11: =IFERROR(VLOOKUP(I11,Lists!$F$2:$G$16,2,FALSE()),"Not Rated") -> Teens | P11: =IFERROR(VALUE(LEFT(J11,FIND(" ",J11)-1)),"") -> 104 | Q11: =IFERROR(LEFT(F11,FIND(",",F11)-1),F11) -> United States | R11: ="|"&SUBSTITUTE(F11,", ","|")&"|" -> |United States| | S11: ="|"&SUBSTITUTE(K11,", ","|")&"|" -> |Comedies|Dramas| | T11: ="|"&SUBSTITUTE(D11,", ","|")&"|" -> |Theodore Melfi| | U11: ="|"&SUBSTITUTE(E11,", ","|")&"|" -> |Melissa McCarthy|Chris O'Dowd|Kevin Kline|Timothy Olyphant|Daveed Diggs|Skyler Gisondo|Laura Harrier|Rosalind Chao|Kimberly Quinn|Loretta Devine|Ravi Kapoor|
A12: s11 | B12: TV Show | C12: Vendetta: Truth, Lies and The Mafia | D12: Unknown | E12: Unknown | F12: Unknown | G12: 44463 | H12: 2021 | I12: TV-MA | J12: 1 Season | K12: Crime TV Shows, Docuseries, International TV Shows | L12: Sicily boasts a bold "Anti-Mafia" coalition. But what happens when those trying to bring down organized crime are accused of being criminals themselves? | M12: =IF(G12="","",YEAR(G12)) -> 2021 | N12: =IF(G12="","",MONTH(G12)) -> 9 | O12: =IFERROR(VLOOKUP(I12,Lists!$F$2:$G$16,2,FALSE()),"Not Rated") -> Adults | P12: =IFERROR(VALUE(LEFT(J12,FIND(" ",J12)-1)),"") -> 1 | Q12: =IFERROR(LEFT(F12,FIND(",",F12)-1),F12) -> Unknown | R12: ="|"&SUBSTITUTE(F12,", ","|")&"|" -> |Unknown| | S12: ="|"&SUBSTITUTE(K12,", ","|")&"|" -> |Crime TV Shows|Docuseries|International TV Shows| | T12: ="|"&SUBSTITUTE(D12,", ","|")&"|" -> |Unknown| | U12: ="|"&SUBSTITUTE(E12,", ","|")&"|" -> |Unknown|
A13: s12 | B13: TV Show | C13: Bangkok Breaking | D13: Kongkiat Komesiri | E13: Sukollawat Kanarot, Sushar Manaying, Pavarit Mongkolpisit, Sahajak Boonthanakit, Suthipongse Thatphithakkul, Bhasaworn Bawronkirati, Daweerit Chullasapya, Waratthaya Wongchayaporn, Kittiphoom Wongpentak, Abhicha Thanachanun, Nophand Boonyai, Kittipong Khamsat, Arisara Wongchalee, Jaytiya Naiwattanakul, Pantipa Arunwattanachai, Panupan Jantanawong, Kungtap Saelim, Phumphat Chartsuriyakiat, Issara Veranitinunt, Keerati Sivakuae, Panjai Sirisuwan, Supranee Charoenpol, Suda Chuenban, Visaka Banhansupavat, Pitchatorn Santinatornkul | F13: Unknown | G13: 44462 | H13: 2021 | I13: TV-MA | J13: 1 Season | K13: Crime TV Shows, International TV Shows, TV Action & Adventure | L13: Struggling to earn a living in Bangkok, a man joins an emergency rescue service and realizes he must unravel a citywide conspiracy. | M13: =IF(G13="","",YEAR(G13)) -> 2021 | N13: =IF(G13="","",MONTH(G13)) -> 9 | O13: =IFERROR(VLOOKUP(I13,Lists!$F$2:$G$16,2,FALSE()),"Not Rated") -> Adults | P13: =IFERROR(VALUE(LEFT(J13,FIND(" ",J13)-1)),"") -> 1 | Q13: =IFERROR(LEFT(F13,FIND(",",F13)-1),F13) -> Unknown | R13: ="|"&SUBSTITUTE(F13,", ","|")&"|" -> |Unknown| | S13: ="|"&SUBSTITUTE(K13,", ","|")&"|" -> |Crime TV Shows|International TV Shows|TV Action & Adventure| | T13: ="|"&SUBSTITUTE(D13,", ","|")&"|" -> |Kongkiat Komesiri| | U13: ="|"&SUBSTITUTE(E13,", ","|")&"|" -> |Sukollawat Kanarot|Sushar Manaying|Pavarit Mongkolpisit|Sahajak Boonthanakit|Suthipongse Thatphithakkul|Bhasaworn Bawronkirati|Daweerit Chullasapya|Waratthaya Wongchayaporn|Kittiphoom Wongpentak|Abhicha Thanachanun|Nophand Boonyai|Kittipong Khamsat|Arisara Wongchalee|Jaytiya Naiwattanakul|Pantipa Arunwattanachai|Panupan Jantanawong|Kungtap Saelim|Phumphat Chartsuriyakiat|Issara Veranitinunt|Keerati Sivakuae|Panjai Sirisuwan|Supranee Charoenpol|Suda Chuenban|Visaka Banhansupavat|Pitchatorn Santinatornkul|
... A6067: s6066 | B6067: Movie | C6067: A Wrinkle in Time | D6067: Ava DuVernay | E6067: Storm Reid, Oprah Winfrey, Reese Witherspoon, Mindy Kaling, Deric McCabe, Levi Miller, Chris Pine, Gugu Mbatha-Raw, Zach Galifianakis, Michael Peña, Bellamy Young, André Holland, Will McCormack, Rowan Blanchard, Daniel MacPherson | F6067: United States | G6067: 43368 | H6067: 2018 | I6067: PG | J6067: 110 min | K6067: Children & Family Movies | L6067: Years after their father disappears, Meg and her younger brother Charles Wallace cross galaxies on a quest to save him from the heart of darkness. | M6067: =IF(G6067="","",YEAR(G6067)) -> 2018 | N6067: =IF(G6067="","",MONTH(G6067)) -> 9 | O6067: =IFERROR(VLOOKUP(I6067,Lists!$F$2:$G$16,2,FALSE()),"Not Rated") -> Older Kids | P6067: =IFERROR(VALUE(LEFT(J6067,FIND(" ",J6067)-1)),"") -> 110 | Q6067: =IFERROR(LEFT(F6067,FIND(",",F6067)-1),F6067) -> United States | R6067: ="|"&SUBSTITUTE(F6067,", ","|")&"|" -> |United States| | S6067: ="|"&SUBSTITUTE(K6067,", ","|")&"|" -> |Children & Family Movies| | T6067: ="|"&SUBSTITUTE(D6067,", ","|")&"|" -> |Ava DuVernay| | U6067: ="|"&SUBSTITUTE(E6067,", ","|")&"|" -> |Storm Reid|Oprah Winfrey|Reese Witherspoon|Mindy Kaling|Deric McCabe|Levi Miller|Chris Pine|Gugu Mbatha-Raw|Zach Galifianakis|Michael Peña|Bellamy Young|André Holland|Will McCormack|Rowan Blanchard|Daniel MacPherson|
A6068: s6067 | B6068: TV Show | C6068: A Young Doctor's Notebook and Other Stories | D6068: Unknown | E6068: Daniel Radcliffe, Jon Hamm, Adam Godley, Christopher Godwin, Rosie Cavaliero, Vicki Pepperdine, Margaret Clunie, Tim Steed, Shaun Pye | F6068: United Kingdom | H6068: 2013 | I6068: TV-MA | J6068: 2 Seasons | K6068: British TV Shows, TV Comedies, TV Dramas | L6068: Set during the Russian Revolution, this comic miniseries is based on a doctor's memories of his early career working in an out-of-the-way village. | M6068: =IF(G6068="","",YEAR(G6068)) | N6068: =IF(G6068="","",MONTH(G6068)) | O6068: =IFERROR(VLOOKUP(I6068,Lists!$F$2:$G$16,2,FALSE()),"Not Rated") -> Adults | P6068: =IFERROR(VALUE(LEFT(J6068,FIND(" ",J6068)-1)),"") -> 2 | Q6068: =IFERROR(LEFT(F6068,FIND(",",F6068)-1),F6068) -> United Kingdom | R6068: ="|"&SUBSTITUTE(F6068,", ","|")&"|" -> |United Kingdom| | S6068: ="|"&SUBSTITUTE(K6068,", ","|")&"|" -> |British TV Shows|TV Comedies|TV Dramas| | T6068: ="|"&SUBSTITUTE(D6068,", ","|")&"|" -> |Unknown| | U6068: ="|"&SUBSTITUTE(E6068,", ","|")&"|" -> |Daniel Radcliffe|Jon Hamm|Adam Godley|Christopher Godwin|Rosie Cavaliero|Vicki Pepperdine|Margaret Clunie|Tim Steed|Shaun Pye|
A6069: s6068 | B6069: TV Show | C6069: A.D. Kingdom and Empire | D6069: Unknown | E6069: Juan Pablo Di Pace, Adam Levy, Chipo Chung, Babou Ceesay, Emmett Scanlan, Will Thorp, Richard Coyle, Vincent Regan, Greta Scacchi, James Callis, Joanne Whalley, Jodhi May, Chris Brazier, Fraser Ayres, Jóhannes Haukur Jóhannesson, Ken Bones, Kenneth Collard | F6069: United States | G6069: 43084 | H6069: 2015 | I6069: TV-14 | J6069: 1 Season | K6069: TV Dramas | L6069: In the wake of Jesus Christ's crucifixion, his apostles dedicate themselves to spreading his message, risking their freedom and their lives. | M6069: =IF(G6069="","",YEAR(G6069)) -> 2017 | N6069: =IF(G6069="","",MONTH(G6069)) -> 12 | O6069: =IFERROR(VLOOKUP(I6069,Lists!$F$2:$G$16,2,FALSE()),"Not Rated") -> Teens | P6069: =IFERROR(VALUE(LEFT(J6069,FIND(" ",J6069)-1)),"") -> 1 | Q6069: =IFERROR(LEFT(F6069,FIND(",",F6069)-1),F6069) -> United States | R6069: ="|"&SUBSTITUTE(F6069,", ","|")&"|" -> |United States| | S6069: ="|"&SUBSTITUTE(K6069,", ","|")&"|" -> |TV Dramas| | T6069: ="|"&SUBSTITUTE(D6069,", ","|")&"|" -> |Unknown| | U6069: ="|"&SUBSTITUTE(E6069,", ","|")&"|" -> |Juan Pablo Di Pace|Adam Levy|Chipo Chung|Babou Ceesay|Emmett Scanlan|Will Thorp|Richard Coyle|Vincent Regan|Greta Scacchi|James Callis|Joanne Whalley|Jodhi May|Chris Brazier|Fraser Ayres|Jóhannes Haukur Jóhannesson|Ken Bones|Kenneth Collard|
A6070: s6069 | B6070: Movie | C6070: A.M.I. | D6070: Rusty Nixon | E6070: Debs Howard, Philip Granger, Sam Robert Muik, Havana Guppy, Bonnie Hay, Veronica Hampson, Lori Triolo, Andrew Coghlan, Laura Mitchell, Elinet Louicius | F6070: Canada | G6070: 44105 | H6070: 2019 | I6070: TV-MA | J6070: 77 min | K6070: Horror Movies | L6070: After losing her mother, a teenage girl bonds with her phone’s artificial intelligence app, a relationship that soon takes a dark and violent turn. | M6070: =IF(G6070="","",YEAR(G6070)) -> 2020 | N6070: =IF(G6070="","",MONTH(G6070)) -> 10 | O6070: =IFERROR(VLOOKUP(I6070,Lists!$F$2:$G$16,2,FALSE()),"Not Rated") -> Adults | P6070: =IFERROR(VALUE(LEFT(J6070,FIND(" ",J6070)-1)),"") -> 77 | Q6070: =IFERROR(LEFT(F6070,FIND(",",F6070)-1),F6070) -> Canada | R6070: ="|"&SUBSTITUTE(F6070,", ","|")&"|" -> |Canada| | S6070: ="|"&SUBSTITUTE(K6070,", ","|")&"|" -> |Horror Movies| | T6070: ="|"&SUBSTITUTE(D6070,", ","|")&"|" -> |Rusty Nixon| | U6070: ="|"&SUBSTITUTE(E6070,", ","|")&"|" -> |Debs Howard|Philip Granger|Sam Robert Muik|Havana Guppy|Bonnie Hay|Veronica Hampson|Lori Triolo|Andrew Coghlan|Laura Mitchell|Elinet Louicius|
A6071: s6070 | B6071: Movie | C6071: A.X.L. | D6071: Oliver Daly | E6071: Alex Neustaedter, Becky G., Alex MacNicoll, Dominic Rains, Thomas Jane, Lou Taylor Pucci, Patricia De Leon, Niko Guardado, Ted McGinley, Marie-Françoise Theodore, Eric Etebari, Dorian Kingi | F6071: United States | G6071: 43544 | H6071: 2018 | I6071: PG | J6071: 99 min | K6071: Action & Adventure, Children & Family Movies, Independent Movies | L6071: Young motocross racer Miles Hill helps a top-secret robotic combat dog evade its ruthless creator and the military, who are in hot pursuit. | M6071: =IF(G6071="","",YEAR(G6071)) -> 2019 | N6071: =IF(G6071="","",MONTH(G6071)) -> 3 | O6071: =IFERROR(VLOOKUP(I6071,Lists!$F$2:$G$16,2,FALSE()),"Not Rated") -> Older Kids | P6071: =IFERROR(VALUE(LEFT(J6071,FIND(" ",J6071)-1)),"") -> 99 | Q6071: =IFERROR(LEFT(F6071,FIND(",",F6071)-1),F6071) -> United States | R6071: ="|"&SUBSTITUTE(F6071,", ","|")&"|" -> |United States| | S6071: ="|"&SUBSTITUTE(K6071,", ","|")&"|" -> |Action & Adventure|Children & Family Movies|Independent Movies| | T6071: ="|"&SUBSTITUTE(D6071,", ","|")&"|" -> |Oliver Daly| | U6071: ="|"&SUBSTITUTE(E6071,", ","|")&"|" -> |Alex Neustaedter|Becky G.|Alex MacNicoll|Dominic Rains|Thomas Jane|Lou Taylor Pucci|Patricia De Leon|Niko Guardado|Ted McGinley|Marie-Françoise Theodore|Eric Etebari|Dorian Kingi|
A6072: s6071 | B6072: Movie | C6072: Aşk Tesadüfleri Sever | D6072: Ömer Faruk Sorak | E6072: Mehmet Günsür, Belçim Bilgin, Ayda Aksel, Altan Erkekli, Sebnem Sönmez, Hüseyin Avni Danyal, Berna Konur, Ümit Bülent Dinçer | F6072: Turkey | G6072: 43194 | H6072: 2011 | I6072: TV-MA | J6072: 122 min | K6072: Dramas, International Movies, Romantic Movies | L6072: A series of coincidences brings two star-crossed lovers together, but fate pulls them apart until they encounter each other again in Istanbul. | M6072: =IF(G6072="","",YEAR(G6072)) -> 2018 | N6072: =IF(G6072="","",MONTH(G6072)) -> 4 | O6072: =IFERROR(VLOOKUP(I6072,Lists!$F$2:$G$16,2,FALSE()),"Not Rated") -> Adults | P6072: =IFERROR(VALUE(LEFT(J6072,FIND(" ",J6072)-1)),"") -> 122 | Q6072: =IFERROR(LEFT(F6072,FIND(",",F6072)-1),F6072) -> Turkey | R6072: ="|"&SUBSTITUTE(F6072,", ","|")&"|" -> |Turkey| | S6072: ="|"&SUBSTITUTE(K6072,", ","|")&"|" -> |Dramas|International Movies|Romantic Movies| | T6072: ="|"&SUBSTITUTE(D6072,", ","|")&"|" -> |Ömer Faruk Sorak| | U6072: ="|"&SUBSTITUTE(E6072,", ","|")&"|" -> |Mehmet Günsür|Belçim Bilgin|Ayda Aksel|Altan Erkekli|Sebnem Sönmez|Hüseyin Avni Danyal|Berna Konur|Ümit Bülent Dinçer|
A6073: s6072 | B6073: Movie | C6073: Aadu 2 | D6073: Midhun Manuel Thomas | E6073: Jayasurya, Vinayakan, Sunny Wayne, Vijay Babu, Saiju Kurup, Vineeth Mohan, Unni Rajan P. Dev, Dharmajan Bolgatty, Indrans | F6073: India | G6073: 43235 | H6073: 2017 | I6073: TV-MA | J6073: 150 min | K6073: Comedies, International Movies | L6073: When Shaji Pappan and his gang of goofy outlaws find themselves low on funds, they plan to once again win a hefty prize in a tug-of-war competition. | M6073: =IF(G6073="","",YEAR(G6073)) -> 2018 | N6073: =IF(G6073="","",MONTH(G6073)) -> 5 | O6073: =IFERROR(VLOOKUP(I6073,Lists!$F$2:$G$16,2,FALSE()),"Not Rated") -> Adults | P6073: =IFERROR(VALUE(LEFT(J6073,FIND(" ",J6073)-1)),"") -> 150 | Q6073: =IFERROR(LEFT(F6073,FIND(",",F6073)-1),F6073) -> India | R6073: ="|"&SUBSTITUTE(F6073,", ","|")&"|" -> |India| | S6073: ="|"&SUBSTITUTE(K6073,", ","|")&"|" -> |Comedies|International Movies| | T6073: ="|"&SUBSTITUTE(D6073,", ","|")&"|" -> |Midhun Manuel Thomas| | U6073: ="|"&SUBSTITUTE(E6073,", ","|")&"|" -> |Jayasurya|Vinayakan|Sunny Wayne|Vijay Babu|Saiju Kurup|Vineeth Mohan|Unni Rajan P. Dev|Dharmajan Bolgatty|Indrans|
A6074: s6073 | B6074: Movie | C6074: Aajcha Divas Majha | D6074: Chandrakant Kulkarni | E6074: Sachin Khedekar, Ashwini Bhave, Mahesh Manjrekar, Hrishikesh Joshi, Satish Alekar, Sunil Tawde, Pushkar Shrotri, Anand Ingle | F6074: India | G6074: 43101 | H6074: 2013 | I6074: TV-PG | J6074: 126 min | K6074: Comedies, Dramas, International Movies | L6074: A conscientious politician helps an elderly singer overcome the obstacles placed in his path a by a powerful bureaucracy. | M6074: =IF(G6074="","",YEAR(G6074)) -> 2018 | N6074: =IF(G6074="","",MONTH(G6074)) -> 1 | O6074: =IFERROR(VLOOKUP(I6074,Lists!$F$2:$G$16,2,FALSE()),"Not Rated") -> Older Kids | P6074: =IFERROR(VALUE(LEFT(J6074,FIND(" ",J6074)-1)),"") -> 126 | Q6074: =IFERROR(LEFT(F6074,FIND(",",F6074)-1),F6074) -> India | R6074: ="|"&SUBSTITUTE(F6074,", ","|")&"|" -> |India| | S6074: ="|"&SUBSTITUTE(K6074,", ","|")&"|" -> |Comedies|Dramas|International Movies| | T6074: ="|"&SUBSTITUTE(D6074,", ","|")&"|" -> |Chandrakant Kulkarni| | U6074: ="|"&SUBSTITUTE(E6074,", ","|")&"|" -> |Sachin Khedekar|Ashwini Bhave|Mahesh Manjrekar|Hrishikesh Joshi|Satish Alekar|Sunil Tawde|Pushkar Shrotri|Anand Ingle|
A6075: s6074 | B6075: Movie | C6075: Aarakshan | D6075: Prakash Jha | E6075: Amitabh Bachchan, Saif Ali Khan, Manoj Bajpayee, Deepika Padukone, Prateik, Tanvi Azmi, Saurabh Shukla, Darshan Jariwala, Yashpal Sharma, Mukesh Tiwari | F6075: India | G6075: 43830 | H6075: 2011 | I6075: TV-14 | J6075: 164 min | K6075: Dramas, International Movies | L6075: The decision by India's supreme court to establish caste-based reservations for jobs in education causes conflict between a teacher and his mentor. | M6075: =IF(G6075="","",YEAR(G6075)) -> 2019 | N6075: =IF(G6075="","",MONTH(G6075)) -> 12 | O6075: =IFERROR(VLOOKUP(I6075,Lists!$F$2:$G$16,2,FALSE()),"Not Rated") -> Teens | P6075: =IFERROR(VALUE(LEFT(J6075,FIND(" ",J6075)-1)),"") -> 164 | Q6075: =IFERROR(LEFT(F6075,FIND(",",F6075)-1),F6075) -> India | R6075: ="|"&SUBSTITUTE(F6075,", ","|")&"|" -> |India| | S6075: ="|"&SUBSTITUTE(K6075,", ","|")&"|" -> |Dramas|International Movies| | T6075: ="|"&SUBSTITUTE(D6075,", ","|")&"|" -> |Prakash Jha| | U6075: ="|"&SUBSTITUTE(E6075,", ","|")&"|" -> |Amitabh Bachchan|Saif Ali Khan|Manoj Bajpayee|Deepika Padukone|Prateik|Tanvi Azmi|Saurabh Shukla|Darshan Jariwala|Yashpal Sharma|Mukesh Tiwari|
A6076: s6075 | B6076: Movie | C6076: Aashayein | D6076: Nagesh Kukunoor | E6076: John Abraham, Sonal Sehgal, Prateeksha Lonkar, Girish Karnad, Farida Jalal, Ashwin Chitale, Anaitha Nair, Vikram Inamdar, Vipin Bhali, Poonam Chitale, Nagesh Kukunoor | F6076: India | G6076: 43030 | H6076: 2010 | I6076: TV-14 | J6076: 115 min | K6076: Dramas, International Movies | L6076: When he learns he has terminal cancer, a cynical gambler and chronic smoker ditches his fiancée, snubs doctors and checks into a nursing home to die. | M6076: =IF(G6076="","",YEAR(G6076)) -> 2017 | N6076: =IF(G6076="","",MONTH(G6076)) -> 10 | O6076: =IFERROR(VLOOKUP(I6076,Lists!$F$2:$G$16,2,FALSE()),"Not Rated") -> Teens | P6076: =IFERROR(VALUE(LEFT(J6076,FIND(" ",J6076)-1)),"") -> 115 | Q6076: =IFERROR(LEFT(F6076,FIND(",",F6076)-1),F6076) -> India | R6076: ="|"&SUBSTITUTE(F6076,", ","|")&"|" -> |India| | S6076: ="|"&SUBSTITUTE(K6076,", ","|")&"|" -> |Dramas|International Movies| | T6076: ="|"&SUBSTITUTE(D6076,", ","|")&"|" -> |Nagesh Kukunoor| | U6076: ="|"&SUBSTITUTE(E6076,", ","|")&"|" -> |John Abraham|Sonal Sehgal|Prateeksha Lonkar|Girish Karnad|Farida Jalal|Ashwin Chitale|Anaitha Nair|Vikram Inamdar|Vipin Bhali|Poonam Chitale|Nagesh Kukunoor|
A6077: s6076 | B6077: Movie | C6077: Aata Pita | D6077: Uttung Shelar | E6077: Sanjay Narvekar, Bharat Jadhav, Satish Phulekar, Ashwini Apte | F6077: India | G6077: 43101 | H6077: 2010 | I6077: TV-14 | J6077: 133 min | K6077: Comedies, Dramas, International Movies | L6077: A municipal clerk with literary ambitions stalks a loan recovery officer on whom he has decided to base his story's central character. | M6077: =IF(G6077="","",YEAR(G6077)) -> 2018 | N6077: =IF(G6077="","",MONTH(G6077)) -> 1 | O6077: =IFERROR(VLOOKUP(I6077,Lists!$F$2:$G$16,2,FALSE()),"Not Rated") -> Teens | P6077: =IFERROR(VALUE(LEFT(J6077,FIND(" ",J6077)-1)),"") -> 133 | Q6077: =IFERROR(LEFT(F6077,FIND(",",F6077)-1),F6077) -> India | R6077: ="|"&SUBSTITUTE(F6077,", ","|")&"|" -> |India| | S6077: ="|"&SUBSTITUTE(K6077,", ","|")&"|" -> |Comedies|Dramas|International Movies| | T6077: ="|"&SUBSTITUTE(D6077,", ","|")&"|" -> |Uttung Shelar| | U6077: ="|"&SUBSTITUTE(E6077,", ","|")&"|" -> |Sanjay Narvekar|Bharat Jadhav|Satish Phulekar|Ashwini Apte|
A6078: s6077 | B6078: Movie | C6078: Abby Sen | D6078: Atanu Ghosh | E6078: Abir Chatterjee, Raima Sen, Arunima Ghosh, Priyanka Sarkar, Sujan Mukherjee, Kanchan Mullick, Biswanath Basu, Bhaswar Chatterjee, Swagata Basu, Tuhin Mitra, Paran Banerjee, Kharaj Mukherjee, Chiranjit | F6078: India | G6078: 42856 | H6078: 2015 | I6078: TV-PG | J6078: 127 min | K6078: Comedies, Dramas, International Movies | L6078: After losing his seventh job in a row, a TV producer and sci-fi buff travels back in time to 1980, where his employment prospects improve. | M6078: =IF(G6078="","",YEAR(G6078)) -> 2017 | N6078: =IF(G6078="","",MONTH(G6078)) -> 5 | O6078: =IFERROR(VLOOKUP(I6078,Lists!$F$2:$G$16,2,FALSE()),"Not Rated") -> Older Kids | P6078: =IFERROR(VALUE(LEFT(J6078,FIND(" ",J6078)-1)),"") -> 127 | Q6078: =IFERROR(LEFT(F6078,FIND(",",F6078)-1),F6078) -> India | R6078: ="|"&SUBSTITUTE(F6078,", ","|")&"|" -> |India| | S6078: ="|"&SUBSTITUTE(K6078,", ","|")&"|" -> |Comedies|Dramas|International Movies| | T6078: ="|"&SUBSTITUTE(D6078,", ","|")&"|" -> |Atanu Ghosh| | U6078: ="|"&SUBSTITUTE(E6078,", ","|")&"|" -> |Abir Chatterjee|Raima Sen|Arunima Ghosh|Priyanka Sarkar|Sujan Mukherjee|Kanchan Mullick|Biswanath Basu|Bhaswar Chatterjee|Swagata Basu|Tuhin Mitra|Paran Banerjee|Kharaj Mukherjee|Chiranjit|
A6079: s6078 | B6079: Movie | C6079: Abdo Mota | D6079: Unknown | E6079: Mohamed Ramadan | F6079: Egypt | G6079: 43574 | H6079: 2012 | I6079: TV-MA | J6079: 100 min | K6079: Action & Adventure, Dramas, International Movies | L6079: Following the mysterious death of his parents, a young man finds himself enmeshed in the dark world of drugs and crime. | M6079: =IF(G6079="","",YEAR(G6079)) -> 2019 | N6079: =IF(G6079="","",MONTH(G6079)) -> 4 | O6079: =IFERROR(VLOOKUP(I6079,Lists!$F$2:$G$16,2,FALSE()),"Not Rated") -> Adults | P6079: =IFERROR(VALUE(LEFT(J6079,FIND(" ",J6079)-1)),"") -> 100 | Q6079: =IFERROR(LEFT(F6079,FIND(",",F6079)-1),F6079) -> Egypt | R6079: ="|"&SUBSTITUTE(F6079,", ","|")&"|" -> |Egypt| | S6079: ="|"&SUBSTITUTE(K6079,", ","|")&"|" -> |Action & Adventure|Dramas|International Movies| | T6079: ="|"&SUBSTITUTE(D6079,", ","|")&"|" -> |Unknown| | U6079: ="|"&SUBSTITUTE(E6079,", ","|")&"|" -> |Mohamed Ramadan|
A6080: s6079 | B6080: Movie | C6080: Abhinetri | D6080: A. L. Vijay | E6080: Tamannaah Bhatia, Prabhu Deva, Sonu Sood, Sapthagiri, Murli Sharma, R.V. Udhaykumar, Joy Mathew, Hema | F6080: India | G6080: 43221 | H6080: 2016 | I6080: TV-14 | J6080: 131 min | K6080: Comedies, International Movies, Sci-Fi & Fantasy | L6080: Due to family pressure, a corporate man reluctantly marries a woman from the village, but in their new home, she abruptly assumes a different persona. | M6080: =IF(G6080="","",YEAR(G6080)) -> 2018 | N6080: =IF(G6080="","",MONTH(G6080)) -> 5 | O6080: =IFERROR(VLOOKUP(I6080,Lists!$F$2:$G$16,2,FALSE()),"Not Rated") -> Teens | P6080: =IFERROR(VALUE(LEFT(J6080,FIND(" ",J6080)-1)),"") -> 131 | Q6080: =IFERROR(LEFT(F6080,FIND(",",F6080)-1),F6080) -> India | R6080: ="|"&SUBSTITUTE(F6080,", ","|")&"|" -> |India| | S6080: ="|"&SUBSTITUTE(K6080,", ","|")&"|" -> |Comedies|International Movies|Sci-Fi & Fantasy| | T6080: ="|"&SUBSTITUTE(D6080,", ","|")&"|" -> |A. L. Vijay| | U6080: ="|"&SUBSTITUTE(E6080,", ","|")&"|" -> |Tamannaah Bhatia|Prabhu Deva|Sonu Sood|Sapthagiri|Murli Sharma|R.V. Udhaykumar|Joy Mathew|Hema|
... A6175: s6174 | B6175: Movie | C6175: Antariksha Ke Rakhwale | D6175: Anirban Majumder | E6175: Sonal Kaushal, Rupa Bhimani, Julie Tejwani, Sabina Malik, Jigna Bharadhwaj, Rajesh Kawa | F6175: Unknown | G6175: 43634 | H6175: 2018 | I6175: TV-Y7 | J6175: 65 min | K6175: Children & Family Movies | L6175: Space villains have abducted all the superheroes! It’s up to Bheem and his trusty team to save the others. | M6175: =IF(G6175="","",YEAR(G6175)) -> 2019 | N6175: =IF(G6175="","",MONTH(G6175)) -> 6 | O6175: =IFERROR(VLOOKUP(I6175,Lists!$F$2:$G$16,2,FALSE()),"Not Rated") -> Kids | P6175: =IFERROR(VALUE(LEFT(J6175,FIND(" ",J6175)-1)),"") -> 65 | Q6175: =IFERROR(LEFT(F6175,FIND(",",F6175)-1),F6175) -> Unknown | R6175: ="|"&SUBSTITUTE(F6175,", ","|")&"|" -> |Unknown| | S6175: ="|"&SUBSTITUTE(K6175,", ","|")&"|" -> |Children & Family Movies| | T6175: ="|"&SUBSTITUTE(D6175,", ","|")&"|" -> |Anirban Majumder| | U6175: ="|"&SUBSTITUTE(E6175,", ","|")&"|" -> |Sonal Kaushal|Rupa Bhimani|Julie Tejwani|Sabina Malik|Jigna Bharadhwaj|Rajesh Kawa|
A6176: s6175 | B6176: TV Show | C6176: Anthony Bourdain: Parts Unknown | D6176: Unknown | E6176: Anthony Bourdain | F6176: United States | H6176: 2018 | I6176: TV-PG | J6176: 5 Seasons | K6176: Docuseries | L6176: This CNN original series has chef Anthony Bourdain traveling to extraordinary locations around the globe to sample a variety of local cuisines. | M6176: =IF(G6176="","",YEAR(G6176)) | N6176: =IF(G6176="","",MONTH(G6176)) | O6176: =IFERROR(VLOOKUP(I6176,Lists!$F$2:$G$16,2,FALSE()),"Not Rated") -> Older Kids | P6176: =IFERROR(VALUE(LEFT(J6176,FIND(" ",J6176)-1)),"") -> 5 | Q6176: =IFERROR(LEFT(F6176,FIND(",",F6176)-1),F6176) -> United States | R6176: ="|"&SUBSTITUTE(F6176,", ","|")&"|" -> |United States| | S6176: ="|"&SUBSTITUTE(K6176,", ","|")&"|" -> |Docuseries| | T6176: ="|"&SUBSTITUTE(D6176,", ","|")&"|" -> |Unknown| | U6176: ="|"&SUBSTITUTE(E6176,", ","|")&"|" -> |Anthony Bourdain|
A6177: s6176 | B6177: Movie | C6177: Antidote | D6177: Ken Barbet | E6177: Randy Couture, Chuck Zito, Wil Traval, Celeste Thornton, Rafael De La Fuente, Alyona Chekhova, Natali Yura, Thom Rivera | F6177: United States | G6177: 43569 | H6177: 2018 | I6177: TV-MA | J6177: 90 min | K6177: Action & Adventure, Horror Movies | L6177: A tough-as-nails treasure hunter protects a humanitarian doctor as she tries to cure a supernatural disease caused by a mysterious witch. | M6177: =IF(G6177="","",YEAR(G6177)) -> 2019 | N6177: =IF(G6177="","",MONTH(G6177)) -> 4 | O6177: =IFERROR(VLOOKUP(I6177,Lists!$F$2:$G$16,2,FALSE()),"Not Rated") -> Adults | P6177: =IFERROR(VALUE(LEFT(J6177,FIND(" ",J6177)-1)),"") -> 90 | Q6177: =IFERROR(LEFT(F6177,FIND(",",F6177)-1),F6177) -> United States | R6177: ="|"&SUBSTITUTE(F6177,", ","|")&"|" -> |United States| | S6177: ="|"&SUBSTITUTE(K6177,", ","|")&"|" -> |Action & Adventure|Horror Movies| | T6177: ="|"&SUBSTITUTE(D6177,", ","|")&"|" -> |Ken Barbet| | U6177: ="|"&SUBSTITUTE(E6177,", ","|")&"|" -> |Randy Couture|Chuck Zito|Wil Traval|Celeste Thornton|Rafael De La Fuente|Alyona Chekhova|Natali Yura|Thom Rivera|
A6178: s6177 | B6178: Movie | C6178: Anwar | D6178: Manish Jha | E6178: Siddharth Koirala, Nauheed Cyrusi, Manisha Koirala, Rajpal Yadav, Yashpal Sharma, Vijay Raaz, Hiten Tejwani, Sudhir Pandey, Sanjay Mishra, Lalit Tiwari | F6178: India | G6178: 43830 | H6178: 2007 | I6178: TV-14 | J6178: 134 min | K6178: Dramas, Independent Movies, International Movies | L6178: Seeking refuge in a Hindu temple after the tragic death of the girl he loved, a Muslim youth is caught by the police, who mistake him for an enemy. | M6178: =IF(G6178="","",YEAR(G6178)) -> 2019 | N6178: =IF(G6178="","",MONTH(G6178)) -> 12 | O6178: =IFERROR(VLOOKUP(I6178,Lists!$F$2:$G$16,2,FALSE()),"Not Rated") -> Teens | P6178: =IFERROR(VALUE(LEFT(J6178,FIND(" ",J6178)-1)),"") -> 134 | Q6178: =IFERROR(LEFT(F6178,FIND(",",F6178)-1),F6178) -> India | R6178: ="|"&SUBSTITUTE(F6178,", ","|")&"|" -> |India| | S6178: ="|"&SUBSTITUTE(K6178,", ","|")&"|" -> |Dramas|Independent Movies|International Movies| | T6178: ="|"&SUBSTITUTE(D6178,", ","|")&"|" -> |Manish Jha| | U6178: ="|"&SUBSTITUTE(E6178,", ","|")&"|" -> |Siddharth Koirala|Nauheed Cyrusi|Manisha Koirala|Rajpal Yadav|Yashpal Sharma|Vijay Raaz|Hiten Tejwani|Sudhir Pandey|Sanjay Mishra|Lalit Tiwari|
A6179: s6178 | B6179: TV Show | C6179: 忍者ハットリくん | D6179: Unknown | E6179: Unknown | F6179: Japan | G6179: 43457 | H6179: 2012 | I6179: TV-Y7 | J6179: 2 Seasons | K6179: Anime Series, Kids' TV | L6179: Hailing from the mountains of Iga, Kanzo Hattori moves in with elementary school student Kenichi Mitsuba and his family to hone his skills as a ninja. | M6179: =IF(G6179="","",YEAR(G6179)) -> 2018 | N6179: =IF(G6179="","",MONTH(G6179)) -> 12 | O6179: =IFERROR(VLOOKUP(I6179,Lists!$F$2:$G$16,2,FALSE()),"Not Rated") -> Kids | P6179: =IFERROR(VALUE(LEFT(J6179,FIND(" ",J6179)-1)),"") -> 2 | Q6179: =IFERROR(LEFT(F6179,FIND(",",F6179)-1),F6179) -> Japan | R6179: ="|"&SUBSTITUTE(F6179,", ","|")&"|" -> |Japan| | S6179: ="|"&SUBSTITUTE(K6179,", ","|")&"|" -> |Anime Series|Kids' TV| | T6179: ="|"&SUBSTITUTE(D6179,", ","|")&"|" -> |Unknown| | U6179: ="|"&SUBSTITUTE(E6179,", ","|")&"|" -> |Unknown|
A6180: s6179 | B6180: Movie | C6180: Apache Warrior | D6180: David Salzberg, Christian Tureaud | E6180: Unknown | F6180: United States | G6180: 43770 | H6180: 2017 | I6180: TV-MA | J6180: 89 min | K6180: Documentaries | L6180: Recovered cockpit footage and telling interviews reveal the true stories of US fighter pilots in one of the largest combat strikes in history. | M6180: =IF(G6180="","",YEAR(G6180)) -> 2019 | N6180: =IF(G6180="","",MONTH(G6180)) -> 11 | O6180: =IFERROR(VLOOKUP(I6180,Lists!$F$2:$G$16,2,FALSE()),"Not Rated") -> Adults | P6180: =IFERROR(VALUE(LEFT(J6180,FIND(" ",J6180)-1)),"") -> 89 | Q6180: =IFERROR(LEFT(F6180,FIND(",",F6180)-1),F6180) -> United States | R6180: ="|"&SUBSTITUTE(F6180,", ","|")&"|" -> |United States| | S6180: ="|"&SUBSTITUTE(K6180,", ","|")&"|" -> |Documentaries| | T6180: ="|"&SUBSTITUTE(D6180,", ","|")&"|" -> |David Salzberg|Christian Tureaud| | U6180: ="|"&SUBSTITUTE(E6180,", ","|")&"|" -> |Unknown|
A6181: s6180 | B6181: Movie | C6181: APEX: The Story of the Hypercar | D6181: J.F. Musial, Josh Vietze | E6181: Zachary Levi | F6181: United States | G6181: 42583 | H6181: 2016 | I6181: NR | J6181: 86 min | K6181: Documentaries | L6181: A visionary carmaker introduces his fuel-efficient, high-performance hypercar to a market filled with big-name competitors like Ferrari and Porsche. | M6181: =IF(G6181="","",YEAR(G6181)) -> 2016 | N6181: =IF(G6181="","",MONTH(G6181)) -> 8 | O6181: =IFERROR(VLOOKUP(I6181,Lists!$F$2:$G$16,2,FALSE()),"Not Rated") -> Not Rated | P6181: =IFERROR(VALUE(LEFT(J6181,FIND(" ",J6181)-1)),"") -> 86 | Q6181: =IFERROR(LEFT(F6181,FIND(",",F6181)-1),F6181) -> United States | R6181: ="|"&SUBSTITUTE(F6181,", ","|")&"|" -> |United States| | S6181: ="|"&SUBSTITUTE(K6181,", ","|")&"|" -> |Documentaries| | T6181: ="|"&SUBSTITUTE(D6181,", ","|")&"|" -> |J.F. Musial|Josh Vietze| | U6181: ="|"&SUBSTITUTE(E6181,", ","|")&"|" -> |Zachary Levi|
A6182: s6181 | B6182: Movie | C6182: Apollo 18 | D6182: Gonzalo López-Gallego | E6182: Warren Christie, Lloyd Owen, Ryan Robbins, Michael Kopsa, Andrew Airlie | F6182: United States, Canada | G6182: 43533 | H6182: 2011 | I6182: PG-13 | J6182: 87 min | K6182: Horror Movies, Sci-Fi & Fantasy, Thrillers | L6182: This sci-fi thriller suggests that Apollo 17, despite official statements to the contrary, wasn't NASA's last manned mission to the moon. | M6182: =IF(G6182="","",YEAR(G6182)) -> 2019 | N6182: =IF(G6182="","",MONTH(G6182)) -> 3 | O6182: =IFERROR(VLOOKUP(I6182,Lists!$F$2:$G$16,2,FALSE()),"Not Rated") -> Teens | P6182: =IFERROR(VALUE(LEFT(J6182,FIND(" ",J6182)-1)),"") -> 87 | Q6182: =IFERROR(LEFT(F6182,FIND(",",F6182)-1),F6182) -> United States | R6182: ="|"&SUBSTITUTE(F6182,", ","|")&"|" -> |United States|Canada| | S6182: ="|"&SUBSTITUTE(K6182,", ","|")&"|" -> |Horror Movies|Sci-Fi & Fantasy|Thrillers| | T6182: ="|"&SUBSTITUTE(D6182,", ","|")&"|" -> |Gonzalo López-Gallego| | U6182: ="|"&SUBSTITUTE(E6182,", ","|")&"|" -> |Warren Christie|Lloyd Owen|Ryan Robbins|Michael Kopsa|Andrew Airlie|
A6183: s6182 | B6183: Movie | C6183: April and the Extraordinary World | D6183: Christian Desmares, Franck Ekinci | E6183: Angela Galuppo, Paul Giamatti, Susan Sarandon, Tony Hale, J.K. Simmons, Tony Robinow, Mark Camacho, Tod Fennell, Carlos Alazraqui, Kari Wahlgren | F6183: France, Canada, Belgium | G6183: 43009 | H6183: 2015 | I6183: PG | J6183: 107 min | K6183: Action & Adventure, Comedies, International Movies | L6183: After the world's top scientists disappear, orphaned April secretly forges ahead with a family experiment and gets tangled up in a vast conspiracy. | M6183: =IF(G6183="","",YEAR(G6183)) -> 2017 | N6183: =IF(G6183="","",MONTH(G6183)) -> 10 | O6183: =IFERROR(VLOOKUP(I6183,Lists!$F$2:$G$16,2,FALSE()),"Not Rated") -> Older Kids | P6183: =IFERROR(VALUE(LEFT(J6183,FIND(" ",J6183)-1)),"") -> 107 | Q6183: =IFERROR(LEFT(F6183,FIND(",",F6183)-1),F6183) -> France | R6183: ="|"&SUBSTITUTE(F6183,", ","|")&"|" -> |France|Canada|Belgium| | S6183: ="|"&SUBSTITUTE(K6183,", ","|")&"|" -> |Action & Adventure|Comedies|International Movies| | T6183: ="|"&SUBSTITUTE(D6183,", ","|")&"|" -> |Christian Desmares|Franck Ekinci| | U6183: ="|"&SUBSTITUTE(E6183,", ","|")&"|" -> |Angela Galuppo|Paul Giamatti|Susan Sarandon|Tony Hale|J.K. Simmons|Tony Robinow|Mark Camacho|Tod Fennell|Carlos Alazraqui|Kari Wahlgren|
A6184: s6183 | B6184: Movie | C6184: Aram, Aram | D6184: Christopher Chambers | E6184: John Roohinian, Levon Sharafyan, Sevak Hakoyan, David Villada, Mike Ghader, Razmik Mansuryan, Lorita Meg, Amy Sanders, Alla Tumanian | F6184: United States | G6184: 42781 | H6184: 2015 | I6184: TV-14 | J6184: 79 min | K6184: Dramas, Independent Movies | L6184: Newly orphaned Aram leaves Beirut to live with his grandfather in Los Angeles, and overwhelmed by culture shock, he falls prey to an Armenian gang. | M6184: =IF(G6184="","",YEAR(G6184)) -> 2017 | N6184: =IF(G6184="","",MONTH(G6184)) -> 2 | O6184: =IFERROR(VLOOKUP(I6184,Lists!$F$2:$G$16,2,FALSE()),"Not Rated") -> Teens | P6184: =IFERROR(VALUE(LEFT(J6184,FIND(" ",J6184)-1)),"") -> 79 | Q6184: =IFERROR(LEFT(F6184,FIND(",",F6184)-1),F6184) -> United States | R6184: ="|"&SUBSTITUTE(F6184,", ","|")&"|" -> |United States| | S6184: ="|"&SUBSTITUTE(K6184,", ","|")&"|" -> |Dramas|Independent Movies| | T6184: ="|"&SUBSTITUTE(D6184,", ","|")&"|" -> |Christopher Chambers| | U6184: ="|"&SUBSTITUTE(E6184,", ","|")&"|" -> |John Roohinian|Levon Sharafyan|Sevak Hakoyan|David Villada|Mike Ghader|Razmik Mansuryan|Lorita Meg|Amy Sanders|Alla Tumanian|
A6185: s6184 | B6185: Movie | C6185: Are We Done Yet? | D6185: Khaled El Halafawy | E6185: Ahmed Eid, Ayten Amer, Ahmed Fouad Selim, Mohsen Mansour | F6185: Egypt | G6185: 43678 | H6185: 2018 | I6185: TV-14 | J6185: 87 min | K6185: Comedies, Dramas, International Movies | L6185: When authorities arrest his young son, a taxi driver must convince the courts and rabid media that he's not the criminal they seek. | M6185: =IF(G6185="","",YEAR(G6185)) -> 2019 | N6185: =IF(G6185="","",MONTH(G6185)) -> 8 | O6185: =IFERROR(VLOOKUP(I6185,Lists!$F$2:$G$16,2,FALSE()),"Not Rated") -> Teens | P6185: =IFERROR(VALUE(LEFT(J6185,FIND(" ",J6185)-1)),"") -> 87 | Q6185: =IFERROR(LEFT(F6185,FIND(",",F6185)-1),F6185) -> Egypt | R6185: ="|"&SUBSTITUTE(F6185,", ","|")&"|" -> |Egypt| | S6185: ="|"&SUBSTITUTE(K6185,", ","|")&"|" -> |Comedies|Dramas|International Movies| | T6185: ="|"&SUBSTITUTE(D6185,", ","|")&"|" -> |Khaled El Halafawy| | U6185: ="|"&SUBSTITUTE(E6185,", ","|")&"|" -> |Ahmed Eid|Ayten Amer|Ahmed Fouad Selim|Mohsen Mansour|
A6186: s6185 | B6186: Movie | C6186: Arisan 2 | D6186: Nia Dinata | E6186: Surya Saputra, Cut Mini Theo, Tora Sudiro | F6186: Indonesia | G6186: 43358 | H6186: 2011 | I6186: TV-14 | J6186: 113 min | K6186: Comedies, Dramas, International Movies | L6186: A group of friends reunites for a vacation amid nature, where they laugh about their shared history and bond over difficult truths. | M6186: =IF(G6186="","",YEAR(G6186)) -> 2018 | N6186: =IF(G6186="","",MONTH(G6186)) -> 9 | O6186: =IFERROR(VLOOKUP(I6186,Lists!$F$2:$G$16,2,FALSE()),"Not Rated") -> Teens | P6186: =IFERROR(VALUE(LEFT(J6186,FIND(" ",J6186)-1)),"") -> 113 | Q6186: =IFERROR(LEFT(F6186,FIND(",",F6186)-1),F6186) -> Indonesia | R6186: ="|"&SUBSTITUTE(F6186,", ","|")&"|" -> |Indonesia| | S6186: ="|"&SUBSTITUTE(K6186,", ","|")&"|" -> |Comedies|Dramas|International Movies| | T6186: ="|"&SUBSTITUTE(D6186,", ","|")&"|" -> |Nia Dinata| | U6186: ="|"&SUBSTITUTE(E6186,", ","|")&"|" -> |Surya Saputra|Cut Mini Theo|Tora Sudiro|
A6187: s6186 | B6187: Movie | C6187: Arthur | D6187: Jason Winer | E6187: Russell Brand, Helen Mirren, Greta Gerwig, Jennifer Garner, Geraldine James, Luis Guzmán, Nick Nolte, Christina Jacquelyn Calph, Murphy Guyer, José Ramón Rosario | F6187: United States | G6187: 43556 | H6187: 2011 | I6187: PG-13 | J6187: 110 min | K6187: Comedies, Romantic Movies | L6187: Russell Brand stars in this remake as a philanderer who must decide whether to give up an inheritance of millions for the sake of romance. | M6187: =IF(G6187="","",YEAR(G6187)) -> 2019 | N6187: =IF(G6187="","",MONTH(G6187)) -> 4 | O6187: =IFERROR(VLOOKUP(I6187,Lists!$F$2:$G$16,2,FALSE()),"Not Rated") -> Teens | P6187: =IFERROR(VALUE(LEFT(J6187,FIND(" ",J6187)-1)),"") -> 110 | Q6187: =IFERROR(LEFT(F6187,FIND(",",F6187)-1),F6187) -> United States | R6187: ="|"&SUBSTITUTE(F6187,", ","|")&"|" -> |United States| | S6187: ="|"&SUBSTITUTE(K6187,", ","|")&"|" -> |Comedies|Romantic Movies| | T6187: ="|"&SUBSTITUTE(D6187,", ","|")&"|" -> |Jason Winer| | U6187: ="|"&SUBSTITUTE(E6187,", ","|")&"|" -> |Russell Brand|Helen Mirren|Greta Gerwig|Jennifer Garner|Geraldine James|Luis Guzmán|Nick Nolte|Christina Jacquelyn Calph|Murphy Guyer|José Ramón Rosario|
A6188: s6187 | B6188: Movie | C6188: Arthur Christmas | D6188: Sarah Smith | E6188: James McAvoy, Hugh Laurie, Bill Nighy, Jim Broadbent, Imelda Staunton, Ashley Jensen, Ramona Marquez, Marc Wootton, Laura Linney, Eva Longoria, Michael Palin, Joan Cusack, Deborah Findlay, Rich Fulcher, Sarah Smith, Clint Dyer, Kerry Shale, Stewart Lee, Bronagh Gallagher, Kevin Cecil, Alistair McGowan, David Menkin, Kris Pearn, Ian Ashpitel, Rich Hall, Seeta Indrani, Jane Horrocks, Peter Baynham, Emma Kennedy, Dominic West, Jerry Lambert, Julia Davis, Robbie Coltrane, Iain McKee, Sanjeev Bhaskar, Andy Serkis, Tamsin Greig, Rhys Darby, Seamus Malone, Cody Cameron, David Schneider, Kevin Eldon, Danny John-Jules, Brian Cummings | F6188: United Kingdom, United States | G6188: 43831 | H6188: 2011 | I6188: PG | J6188: 98 min | K6188: Children & Family Movies, Comedies | L6188: At Santa Claus's super-secret toy-making facility, Mr. Claus entrusts his son, Arthur, to carry out an ultra-important Christmas mission. | M6188: =IF(G6188="","",YEAR(G6188)) -> 2020 | N6188: =IF(G6188="","",MONTH(G6188)) -> 1 | O6188: =IFERROR(VLOOKUP(I6188,Lists!$F$2:$G$16,2,FALSE()),"Not Rated") -> Older Kids | P6188: =IFERROR(VALUE(LEFT(J6188,FIND(" ",J6188)-1)),"") -> 98 | Q6188: =IFERROR(LEFT(F6188,FIND(",",F6188)-1),F6188) -> United Kingdom | R6188: ="|"&SUBSTITUTE(F6188,", ","|")&"|" -> |United Kingdom|United States| | S6188: ="|"&SUBSTITUTE(K6188,", ","|")&"|" -> |Children & Family Movies|Comedies| | T6188: ="|"&SUBSTITUTE(D6188,", ","|")&"|" -> |Sarah Smith| | U6188: ="|"&SUBSTITUTE(E6188,", ","|")&"|" -> |James McAvoy|Hugh Laurie|Bill Nighy|Jim Broadbent|Imelda Staunton|Ashley Jensen|Ramona Marquez|Marc Wootton|Laura Linney|Eva Longoria|Michael Palin|Joan Cusack|Deborah Findlay|Rich Fulcher|Sarah Smith|Clint Dyer|Kerry Shale|Stewart Lee|Bronagh Gallagher|Kevin Cecil|Alistair McGowan|David Menkin|Kris Pearn|Ian Ashpitel|Rich Hall|Seeta Indrani|Jane Horrocks|Peter Baynham|Emma Kennedy|Dominic West|Jerry Lambert|Julia Davis|Robbie Coltrane|Iain McKee|Sanjeev Bhaskar|Andy Serkis|Tamsin Greig|Rhys Darby|Seamus Malone|Cody Cameron|David Schneider|Kevin Eldon|Danny John-Jules|Brian Cummings|
... A6796: s6795 | B6796: Movie | C6796: Frances Ha | D6796: Noah Baumbach | E6796: Greta Gerwig, Mickey Sumner, Charlotte d'Amboise, Adam Driver, Hannah Dunne, Michael Esper, Grace Gummer, Patrick Heusinger, Josh Hamilton, Cindy Katz, Maya Kazan, Justine Lupe, Britta Phillips, Juliet Rylance, Dean Wareham, Michael Zegen | F6796: United States, Brazil | G6796: 43009 | H6796: 2012 | I6796: R | J6796: 86 min | K6796: Comedies, Dramas, Independent Movies | L6796: Determined to make it as a modern dancer in New York, a young woman pursues her unlikely goal with more enthusiasm than natural talent. | M6796: =IF(G6796="","",YEAR(G6796)) -> 2017 | N6796: =IF(G6796="","",MONTH(G6796)) -> 10 | O6796: =IFERROR(VLOOKUP(I6796,Lists!$F$2:$G$16,2,FALSE()),"Not Rated") -> Adults | P6796: =IFERROR(VALUE(LEFT(J6796,FIND(" ",J6796)-1)),"") -> 86 | Q6796: =IFERROR(LEFT(F6796,FIND(",",F6796)-1),F6796) -> United States | R6796: ="|"&SUBSTITUTE(F6796,", ","|")&"|" -> |United States|Brazil| | S6796: ="|"&SUBSTITUTE(K6796,", ","|")&"|" -> |Comedies|Dramas|Independent Movies| | T6796: ="|"&SUBSTITUTE(D6796,", ","|")&"|" -> |Noah Baumbach| | U6796: ="|"&SUBSTITUTE(E6796,", ","|")&"|" -> |Greta Gerwig|Mickey Sumner|Charlotte d'Amboise|Adam Driver|Hannah Dunne|Michael Esper|Grace Gummer|Patrick Heusinger|Josh Hamilton|Cindy Katz|Maya Kazan|Justine Lupe|Britta Phillips|Juliet Rylance|Dean Wareham|Michael Zegen|
A6797: s6796 | B6797: TV Show | C6797: Frasier | D6797: Unknown | E6797: Kelsey Grammer, Jane Leeves, David Hyde Pierce, Peri Gilpin, John Mahoney, Dan Butler | F6797: United States | H6797: 2003 | I6797: TV-PG | J6797: 11 Seasons | K6797: Classic & Cult TV, TV Comedies | L6797: Frasier Crane is a snooty but lovable Seattle psychiatrist who dispenses advice on his call-in radio show while ignoring it in his own relationships. | M6797: =IF(G6797="","",YEAR(G6797)) | N6797: =IF(G6797="","",MONTH(G6797)) | O6797: =IFERROR(VLOOKUP(I6797,Lists!$F$2:$G$16,2,FALSE()),"Not Rated") -> Older Kids | P6797: =IFERROR(VALUE(LEFT(J6797,FIND(" ",J6797)-1)),"") -> 11 | Q6797: =IFERROR(LEFT(F6797,FIND(",",F6797)-1),F6797) -> United States | R6797: ="|"&SUBSTITUTE(F6797,", ","|")&"|" -> |United States| | S6797: ="|"&SUBSTITUTE(K6797,", ","|")&"|" -> |Classic & Cult TV|TV Comedies| | T6797: ="|"&SUBSTITUTE(D6797,", ","|")&"|" -> |Unknown| | U6797: ="|"&SUBSTITUTE(E6797,", ","|")&"|" -> |Kelsey Grammer|Jane Leeves|David Hyde Pierce|Peri Gilpin|John Mahoney|Dan Butler|
A6798: s6797 | B6798: Movie | C6798: Freak Show | D6798: Trudie Styler | E6798: Alex Lawther, Abigail Breslin, AnnaSophia Robb, Ian Nelson, Celia Weston, Laverne Cox, Bette Midler, Willa Fitzgerald, Larry Pine, John McEnroe, Mickey Sumner, Daniel Bellomy, Wally Dunn, Marceline Hugot | F6798: United States | G6798: 44056 | H6798: 2018 | I6798: TV-MA | J6798: 91 min | K6798: Comedies, Dramas, Independent Movies | L6798: Forced to attend a new high school, a glamorous teen navigates hostile territory before taking a stand by running for homecoming queen. | M6798: =IF(G6798="","",YEAR(G6798)) -> 2020 | N6798: =IF(G6798="","",MONTH(G6798)) -> 8 | O6798: =IFERROR(VLOOKUP(I6798,Lists!$F$2:$G$16,2,FALSE()),"Not Rated") -> Adults | P6798: =IFERROR(VALUE(LEFT(J6798,FIND(" ",J6798)-1)),"") -> 91 | Q6798: =IFERROR(LEFT(F6798,FIND(",",F6798)-1),F6798) -> United States | R6798: ="|"&SUBSTITUTE(F6798,", ","|")&"|" -> |United States| | S6798: ="|"&SUBSTITUTE(K6798,", ","|")&"|" -> |Comedies|Dramas|Independent Movies| | T6798: ="|"&SUBSTITUTE(D6798,", ","|")&"|" -> |Trudie Styler| | U6798: ="|"&SUBSTITUTE(E6798,", ","|")&"|" -> |Alex Lawther|Abigail Breslin|AnnaSophia Robb|Ian Nelson|Celia Weston|Laverne Cox|Bette Midler|Willa Fitzgerald|Larry Pine|John McEnroe|Mickey Sumner|Daniel Bellomy|Wally Dunn|Marceline Hugot|
A6799: s6798 | B6799: Movie | C6799: Fred Claus | D6799: David Dobkin | E6799: Vince Vaughn, Paul Giamatti, John Michael Higgins, Miranda Richardson, Rachel Weisz, Kathy Bates, Trevor Peacock, Ludacris, Elizabeth Banks | F6799: United States | G6799: 44197 | H6799: 2007 | I6799: PG | J6799: 115 min | K6799: Children & Family Movies, Comedies | L6799: The holiday season is ruined for Santa Claus when his cranky older brother – a repo man with a sizable rap sheet – visits him at the North Pole. | M6799: =IF(G6799="","",YEAR(G6799)) -> 2021 | N6799: =IF(G6799="","",MONTH(G6799)) -> 1 | O6799: =IFERROR(VLOOKUP(I6799,Lists!$F$2:$G$16,2,FALSE()),"Not Rated") -> Older Kids | P6799: =IFERROR(VALUE(LEFT(J6799,FIND(" ",J6799)-1)),"") -> 115 | Q6799: =IFERROR(LEFT(F6799,FIND(",",F6799)-1),F6799) -> United States | R6799: ="|"&SUBSTITUTE(F6799,", ","|")&"|" -> |United States| | S6799: ="|"&SUBSTITUTE(K6799,", ","|")&"|" -> |Children & Family Movies|Comedies| | T6799: ="|"&SUBSTITUTE(D6799,", ","|")&"|" -> |David Dobkin| | U6799: ="|"&SUBSTITUTE(E6799,", ","|")&"|" -> |Vince Vaughn|Paul Giamatti|John Michael Higgins|Miranda Richardson|Rachel Weisz|Kathy Bates|Trevor Peacock|Ludacris|Elizabeth Banks|
A6800: s6799 | B6800: Movie | C6800: Free Willy | D6800: Simon Wincer | E6800: Jason James Richter, Lori Petty, Jayne Atkinson, August Schellenberg, Michael Madsen, Michael Ironside, Richard Riehle, Mykelti Williamson, Michael Bacall, Danielle Harris | F6800: United States, France, Mexico | G6800: 43831 | H6800: 1993 | I6800: PG | J6800: 112 min | K6800: Children & Family Movies, Dramas | L6800: Ordered to clean up the graffiti he painted at a marine theme park, a troubled young boy unexpectedly bonds with a killer whale on exhibit. | M6800: =IF(G6800="","",YEAR(G6800)) -> 2020 | N6800: =IF(G6800="","",MONTH(G6800)) -> 1 | O6800: =IFERROR(VLOOKUP(I6800,Lists!$F$2:$G$16,2,FALSE()),"Not Rated") -> Older Kids | P6800: =IFERROR(VALUE(LEFT(J6800,FIND(" ",J6800)-1)),"") -> 112 | Q6800: =IFERROR(LEFT(F6800,FIND(",",F6800)-1),F6800) -> United States | R6800: ="|"&SUBSTITUTE(F6800,", ","|")&"|" -> |United States|France|Mexico| | S6800: ="|"&SUBSTITUTE(K6800,", ","|")&"|" -> |Children & Family Movies|Dramas| | T6800: ="|"&SUBSTITUTE(D6800,", ","|")&"|" -> |Simon Wincer| | U6800: ="|"&SUBSTITUTE(E6800,", ","|")&"|" -> |Jason James Richter|Lori Petty|Jayne Atkinson|August Schellenberg|Michael Madsen|Michael Ironside|Richard Riehle|Mykelti Williamson|Michael Bacall|Danielle Harris|
A6801: s6800 | B6801: Movie | C6801: Freeway: Crack in the System | D6801: Marc Levin | E6801: Freeway Rick Ross | F6801: United States, Nicaragua | G6801: 43084 | H6801: 2015 | I6801: R | J6801: 103 min | K6801: Documentaries | L6801: Take in the true account of drug kingpin "Freeway" Rick Ross's empire and how the CIA helped him fuel America's devastating crack cocaine epidemic. | M6801: =IF(G6801="","",YEAR(G6801)) -> 2017 | N6801: =IF(G6801="","",MONTH(G6801)) -> 12 | O6801: =IFERROR(VLOOKUP(I6801,Lists!$F$2:$G$16,2,FALSE()),"Not Rated") -> Adults | P6801: =IFERROR(VALUE(LEFT(J6801,FIND(" ",J6801)-1)),"") -> 103 | Q6801: =IFERROR(LEFT(F6801,FIND(",",F6801)-1),F6801) -> United States | R6801: ="|"&SUBSTITUTE(F6801,", ","|")&"|" -> |United States|Nicaragua| | S6801: ="|"&SUBSTITUTE(K6801,", ","|")&"|" -> |Documentaries| | T6801: ="|"&SUBSTITUTE(D6801,", ","|")&"|" -> |Marc Levin| | U6801: ="|"&SUBSTITUTE(E6801,", ","|")&"|" -> |Freeway Rick Ross|
A6802: s6801 | B6802: Movie | C6802: Freezer's Campaign | D6802: Sameh Abdulaziz | E6802: Bayyumi Fuad, Chico, Hesham Maged, Ahmed Fathy, Nesreen Ameen, Dareen Haddad, Bushra, Samy Maghawry | F6802: Egypt | G6802: 43622 | H6802: 2016 | I6802: TV-MA | J6802: 116 min | K6802: Comedies, International Movies | L6802: When climate change makes Egypt freeze over, intelligence officers pose as a film crew on location to seek a device that can eliminate the frost. | M6802: =IF(G6802="","",YEAR(G6802)) -> 2019 | N6802: =IF(G6802="","",MONTH(G6802)) -> 6 | O6802: =IFERROR(VLOOKUP(I6802,Lists!$F$2:$G$16,2,FALSE()),"Not Rated") -> Adults | P6802: =IFERROR(VALUE(LEFT(J6802,FIND(" ",J6802)-1)),"") -> 116 | Q6802: =IFERROR(LEFT(F6802,FIND(",",F6802)-1),F6802) -> Egypt | R6802: ="|"&SUBSTITUTE(F6802,", ","|")&"|" -> |Egypt| | S6802: ="|"&SUBSTITUTE(K6802,", ","|")&"|" -> |Comedies|International Movies| | T6802: ="|"&SUBSTITUTE(D6802,", ","|")&"|" -> |Sameh Abdulaziz| | U6802: ="|"&SUBSTITUTE(E6802,", ","|")&"|" -> |Bayyumi Fuad|Chico|Hesham Maged|Ahmed Fathy|Nesreen Ameen|Dareen Haddad|Bushra|Samy Maghawry|
A6803: s6802 | B6803: Movie | C6803: French Dirty | D6803: Wade Allain-Marcus, Jesse Allain-Marcus | E6803: Wade Allain-Marcus, Arjun Gupta, Melina Lizette, Elsa Biedermann, Katie Blake, Santana Dempsey | F6803: United States | G6803: 42404 | H6803: 2015 | I6803: TV-MA | J6803: 72 min | K6803: Dramas, Independent Movies | L6803: An aimless, unemployed millennial hangs out with his pals and resists growing up, until an affair with his best friend's girl forces him to change. | M6803: =IF(G6803="","",YEAR(G6803)) -> 2016 | N6803: =IF(G6803="","",MONTH(G6803)) -> 2 | O6803: =IFERROR(VLOOKUP(I6803,Lists!$F$2:$G$16,2,FALSE()),"Not Rated") -> Adults | P6803: =IFERROR(VALUE(LEFT(J6803,FIND(" ",J6803)-1)),"") -> 72 | Q6803: =IFERROR(LEFT(F6803,FIND(",",F6803)-1),F6803) -> United States | R6803: ="|"&SUBSTITUTE(F6803,", ","|")&"|" -> |United States| | S6803: ="|"&SUBSTITUTE(K6803,", ","|")&"|" -> |Dramas|Independent Movies| | T6803: ="|"&SUBSTITUTE(D6803,", ","|")&"|" -> |Wade Allain-Marcus|Jesse Allain-Marcus| | U6803: ="|"&SUBSTITUTE(E6803,", ","|")&"|" -> |Wade Allain-Marcus|Arjun Gupta|Melina Lizette|Elsa Biedermann|Katie Blake|Santana Dempsey|
A6804: s6803 | B6804: Movie | C6804: Freshman Year | D6804: Jude Okwudiafor Johnson | E6804: Diallo Thompson, Natalia Dominguez, Benjamin A. Onyango, Gregory Alan Williams, Desalene Jones, Wynton Odd, Ed Gonzalez Moreno, Natasha Dee Davis, Cameron Schaefer, Joshua Flores-Q | F6804: United States | G6804: 43893 | H6804: 2019 | I6804: TV-PG | J6804: 104 min | K6804: Dramas, Faith & Spirituality | L6804: A devout preacher's son leaves his protective home to begin college and meets a self-reliant student who will test his faith and his heart. | M6804: =IF(G6804="","",YEAR(G6804)) -> 2020 | N6804: =IF(G6804="","",MONTH(G6804)) -> 3 | O6804: =IFERROR(VLOOKUP(I6804,Lists!$F$2:$G$16,2,FALSE()),"Not Rated") -> Older Kids | P6804: =IFERROR(VALUE(LEFT(J6804,FIND(" ",J6804)-1)),"") -> 104 | Q6804: =IFERROR(LEFT(F6804,FIND(",",F6804)-1),F6804) -> United States | R6804: ="|"&SUBSTITUTE(F6804,", ","|")&"|" -> |United States| | S6804: ="|"&SUBSTITUTE(K6804,", ","|")&"|" -> |Dramas|Faith & Spirituality| | T6804: ="|"&SUBSTITUTE(D6804,", ","|")&"|" -> |Jude Okwudiafor Johnson| | U6804: ="|"&SUBSTITUTE(E6804,", ","|")&"|" -> |Diallo Thompson|Natalia Dominguez|Benjamin A. Onyango|Gregory Alan Williams|Desalene Jones|Wynton Odd|Ed Gonzalez Moreno|Natasha Dee Davis|Cameron Schaefer|Joshua Flores-Q|
A6805: s6804 | B6805: TV Show | C6805: Friday Night Tykes | D6805: Unknown | E6805: Unknown | F6805: United States | G6805: 43117 | H6805: 2017 | I6805: TV-PG | J6805: 4 Seasons | K6805: Docuseries, Reality TV | L6805: This docuseries dives into the cutthroat world of Texas youth football, where kids face grueling demands and pressure from coaches and parents to win. | M6805: =IF(G6805="","",YEAR(G6805)) -> 2018 | N6805: =IF(G6805="","",MONTH(G6805)) -> 1 | O6805: =IFERROR(VLOOKUP(I6805,Lists!$F$2:$G$16,2,FALSE()),"Not Rated") -> Older Kids | P6805: =IFERROR(VALUE(LEFT(J6805,FIND(" ",J6805)-1)),"") -> 4 | Q6805: =IFERROR(LEFT(F6805,FIND(",",F6805)-1),F6805) -> United States | R6805: ="|"&SUBSTITUTE(F6805,", ","|")&"|" -> |United States| | S6805: ="|"&SUBSTITUTE(K6805,", ","|")&"|" -> |Docuseries|Reality TV| | T6805: ="|"&SUBSTITUTE(D6805,", ","|")&"|" -> |Unknown| | U6805: ="|"&SUBSTITUTE(E6805,", ","|")&"|" -> |Unknown|
A6806: s6805 | B6806: Movie | C6806: Friday the 13th | D6806: Marcus Nispel | E6806: Jared Padalecki, Danielle Panabaker, Amanda Righetti, Travis Van Winkle, Aaron Yoo, Derek Mears, Jonathan Sadowski, Julianna Guill, Ben Feldman, Arlen Escarpeta, Ryan Hansen | F6806: United States | G6806: 43831 | H6806: 2009 | I6806: R | J6806: 97 min | K6806: Horror Movies | L6806: A group of teenage camp counselors raises the ire of Jason Voorhees, a masked, homicidal maniac, in this remake of the classic slasher flick. | M6806: =IF(G6806="","",YEAR(G6806)) -> 2020 | N6806: =IF(G6806="","",MONTH(G6806)) -> 1 | O6806: =IFERROR(VLOOKUP(I6806,Lists!$F$2:$G$16,2,FALSE()),"Not Rated") -> Adults | P6806: =IFERROR(VALUE(LEFT(J6806,FIND(" ",J6806)-1)),"") -> 97 | Q6806: =IFERROR(LEFT(F6806,FIND(",",F6806)-1),F6806) -> United States | R6806: ="|"&SUBSTITUTE(F6806,", ","|")&"|" -> |United States| | S6806: ="|"&SUBSTITUTE(K6806,", ","|")&"|" -> |Horror Movies| | T6806: ="|"&SUBSTITUTE(D6806,", ","|")&"|" -> |Marcus Nispel| | U6806: ="|"&SUBSTITUTE(E6806,", ","|")&"|" -> |Jared Padalecki|Danielle Panabaker|Amanda Righetti|Travis Van Winkle|Aaron Yoo|Derek Mears|Jonathan Sadowski|Julianna Guill|Ben Feldman|Arlen Escarpeta|Ryan Hansen|
A6807: s6806 | B6807: Movie | C6807: Friend Request | D6807: Simon Verhoeven | E6807: Alycia Debnam-Carey, William Moseley, Connor Paolo, Brit Morgan, Brooke Markham, Sean Marquette, Liesl Ahlers, Shashawnee Hall, Susan Danford | F6807: Germany | G6807: 43208 | H6807: 2016 | I6807: R | J6807: 92 min | K6807: Horror Movies, International Movies | L6807: A popular college student's love of social media becomes her biggest regret when a mysterious account marks each of her friends for a grisly demise. | M6807: =IF(G6807="","",YEAR(G6807)) -> 2018 | N6807: =IF(G6807="","",MONTH(G6807)) -> 4 | O6807: =IFERROR(VLOOKUP(I6807,Lists!$F$2:$G$16,2,FALSE()),"Not Rated") -> Adults | P6807: =IFERROR(VALUE(LEFT(J6807,FIND(" ",J6807)-1)),"") -> 92 | Q6807: =IFERROR(LEFT(F6807,FIND(",",F6807)-1),F6807) -> Germany | R6807: ="|"&SUBSTITUTE(F6807,", ","|")&"|" -> |Germany| | S6807: ="|"&SUBSTITUTE(K6807,", ","|")&"|" -> |Horror Movies|International Movies| | T6807: ="|"&SUBSTITUTE(D6807,", ","|")&"|" -> |Simon Verhoeven| | U6807: ="|"&SUBSTITUTE(E6807,", ","|")&"|" -> |Alycia Debnam-Carey|William Moseley|Connor Paolo|Brit Morgan|Brooke Markham|Sean Marquette|Liesl Ahlers|Shashawnee Hall|Susan Danford|
A6808: s6807 | B6808: TV Show | C6808: Friends | D6808: Unknown | E6808: Jennifer Aniston, Courteney Cox, Lisa Kudrow, Matt LeBlanc, Matthew Perry, David Schwimmer | F6808: United States | H6808: 2003 | I6808: TV-14 | J6808: 10 Seasons | K6808: Classic & Cult TV, TV Comedies | L6808: This hit sitcom follows the merry misadventures of six 20-something pals as they navigate the pitfalls of work, life and love in 1990s Manhattan. | M6808: =IF(G6808="","",YEAR(G6808)) | N6808: =IF(G6808="","",MONTH(G6808)) | O6808: =IFERROR(VLOOKUP(I6808,Lists!$F$2:$G$16,2,FALSE()),"Not Rated") -> Teens | P6808: =IFERROR(VALUE(LEFT(J6808,FIND(" ",J6808)-1)),"") -> 10 | Q6808: =IFERROR(LEFT(F6808,FIND(",",F6808)-1),F6808) -> United States | R6808: ="|"&SUBSTITUTE(F6808,", ","|")&"|" -> |United States| | S6808: ="|"&SUBSTITUTE(K6808,", ","|")&"|" -> |Classic & Cult TV|TV Comedies| | T6808: ="|"&SUBSTITUTE(D6808,", ","|")&"|" -> |Unknown| | U6808: ="|"&SUBSTITUTE(E6808,", ","|")&"|" -> |Jennifer Aniston|Courteney Cox|Lisa Kudrow|Matt LeBlanc|Matthew Perry|David Schwimmer|
A6809: s6808 | B6809: Movie | C6809: From Japan to Egypt | D6809: Mahmoud Karim | E6809: Ahmed Eid, Saki Tsukamoto, Nada Moussa, Mohammed Tharwat | F6809: Egypt | G6809: 43622 | H6809: 2017 | I6809: TV-14 | J6809: 93 min | K6809: Children & Family Movies, Comedies, Dramas | L6809: After his wife relocates to her home country of Japan, an Egyptian man – and father of two rambunctious kids – tries to win her back. | M6809: =IF(G6809="","",YEAR(G6809)) -> 2019 | N6809: =IF(G6809="","",MONTH(G6809)) -> 6 | O6809: =IFERROR(VLOOKUP(I6809,Lists!$F$2:$G$16,2,FALSE()),"Not Rated") -> Teens | P6809: =IFERROR(VALUE(LEFT(J6809,FIND(" ",J6809)-1)),"") -> 93 | Q6809: =IFERROR(LEFT(F6809,FIND(",",F6809)-1),F6809) -> Egypt | R6809: ="|"&SUBSTITUTE(F6809,", ","|")&"|" -> |Egypt| | S6809: ="|"&SUBSTITUTE(K6809,", ","|")&"|" -> |Children & Family Movies|Comedies|Dramas| | T6809: ="|"&SUBSTITUTE(D6809,", ","|")&"|" -> |Mahmoud Karim| | U6809: ="|"&SUBSTITUTE(E6809,", ","|")&"|" -> |Ahmed Eid|Saki Tsukamoto|Nada Moussa|Mohammed Tharwat|
A6810: s6809 | B6810: Movie | C6810: From Paris with Love | D6810: Pierre Morel | E6810: John Travolta, Jonathan Rhys Meyers, Kasia Smutniak, Richard Durden, Bing Yin, Amber Rose Revah, Eric Godon, François Bredon, Chems Dahmani, Sami Darr, Didier Constant | F6810: France, United Kingdom, United States | G6810: 44082 | H6810: 2010 | I6810: R | J6810: 93 min | K6810: Action & Adventure, International Movies | L6810: A low-level intelligence agent gets pulled into action and espionage above his pay grade when he's ordered to assist a trigger-happy senior agent. | M6810: =IF(G6810="","",YEAR(G6810)) -> 2020 | N6810: =IF(G6810="","",MONTH(G6810)) -> 9 | O6810: =IFERROR(VLOOKUP(I6810,Lists!$F$2:$G$16,2,FALSE()),"Not Rated") -> Adults | P6810: =IFERROR(VALUE(LEFT(J6810,FIND(" ",J6810)-1)),"") -> 93 | Q6810: =IFERROR(LEFT(F6810,FIND(",",F6810)-1),F6810) -> France | R6810: ="|"&SUBSTITUTE(F6810,", ","|")&"|" -> |France|United Kingdom|United States| | S6810: ="|"&SUBSTITUTE(K6810,", ","|")&"|" -> |Action & Adventure|International Movies| | T6810: ="|"&SUBSTITUTE(D6810,", ","|")&"|" -> |Pierre Morel| | U6810: ="|"&SUBSTITUTE(E6810,", ","|")&"|" -> |John Travolta|Jonathan Rhys Meyers|Kasia Smutniak|Richard Durden|Bing Yin|Amber Rose Revah|Eric Godon|François Bredon|Chems Dahmani|Sami Darr|Didier Constant|
A6811: s6810 | B6811: Movie | C6811: Froning: The Fittest Man in History | D6811: Heber Cannon | E6811: Rich Froning | F6811: United States | G6811: 43296 | H6811: 2016 | I6811: PG | J6811: 99 min | K6811: Documentaries, International Movies, Sports Movies | L6811: Follow the grueling training regimen of Rich Froning Jr. as he sets his sights on winning an unprecedented fourth CrossFit Games title. | M6811: =IF(G6811="","",YEAR(G6811)) -> 2018 | N6811: =IF(G6811="","",MONTH(G6811)) -> 7 | O6811: =IFERROR(VLOOKUP(I6811,Lists!$F$2:$G$16,2,FALSE()),"Not Rated") -> Older Kids | P6811: =IFERROR(VALUE(LEFT(J6811,FIND(" ",J6811)-1)),"") -> 99 | Q6811: =IFERROR(LEFT(F6811,FIND(",",F6811)-1),F6811) -> United States | R6811: ="|"&SUBSTITUTE(F6811,", ","|")&"|" -> |United States| | S6811: ="|"&SUBSTITUTE(K6811,", ","|")&"|" -> |Documentaries|International Movies|Sports Movies| | T6811: ="|"&SUBSTITUTE(D6811,", ","|")&"|" -> |Heber Cannon| | U6811: ="|"&SUBSTITUTE(E6811,", ","|")&"|" -> |Rich Froning|
A6812: s6811 | B6812: TV Show | C6812: Frozen Planet | D6812: Alastair Fothergill | E6812: David Attenborough | F6812: United Kingdom, United States, Spain, Germany, Greece, Canada | G6812: 42397 | H6812: 2011 | I6812: TV-PG | J6812: 1 Season | K6812: British TV Shows, Docuseries, International TV Shows | L6812: Go on a journey through the Arctic and Antarctic with this visually stunning program that explores these wildernesses and their inhabitants. | M6812: =IF(G6812="","",YEAR(G6812)) -> 2016 | N6812: =IF(G6812="","",MONTH(G6812)) -> 1 | O6812: =IFERROR(VLOOKUP(I6812,Lists!$F$2:$G$16,2,FALSE()),"Not Rated") -> Older Kids | P6812: =IFERROR(VALUE(LEFT(J6812,FIND(" ",J6812)-1)),"") -> 1 | Q6812: =IFERROR(LEFT(F6812,FIND(",",F6812)-1),F6812) -> United Kingdom | R6812: ="|"&SUBSTITUTE(F6812,", ","|")&"|" -> |United Kingdom|United States|Spain|Germany|Greece|Canada| | S6812: ="|"&SUBSTITUTE(K6812,", ","|")&"|" -> |British TV Shows|Docuseries|International TV Shows| | T6812: ="|"&SUBSTITUTE(D6812,", ","|")&"|" -> |Alastair Fothergill| | U6812: ="|"&SUBSTITUTE(E6812,", ","|")&"|" -> |David Attenborough|
A6813: s6812 | B6813: Movie | C6813: Frozen Planet: On Thin Ice | D6813: Unknown | E6813: David Attenborough | F6813: United Kingdom, United States, Spain, Germany, Greece, Canada | G6813: 42397 | H6813: 2011 | I6813: TV-PG | J6813: 47 min | K6813: Movies | L6813: David Attenborough journeys to both polar regions to investigate what rising temperatures will mean for the people and wildlife that live there. | M6813: =IF(G6813="","",YEAR(G6813)) -> 2016 | N6813: =IF(G6813="","",MONTH(G6813)) -> 1 | O6813: =IFERROR(VLOOKUP(I6813,Lists!$F$2:$G$16,2,FALSE()),"Not Rated") -> Older Kids | P6813: =IFERROR(VALUE(LEFT(J6813,FIND(" ",J6813)-1)),"") -> 47 | Q6813: =IFERROR(LEFT(F6813,FIND(",",F6813)-1),F6813) -> United Kingdom | R6813: ="|"&SUBSTITUTE(F6813,", ","|")&"|" -> |United Kingdom|United States|Spain|Germany|Greece|Canada| | S6813: ="|"&SUBSTITUTE(K6813,", ","|")&"|" -> |Movies| | T6813: ="|"&SUBSTITUTE(D6813,", ","|")&"|" -> |Unknown| | U6813: ="|"&SUBSTITUTE(E6813,", ","|")&"|" -> |David Attenborough|
A6814: s6813 | B6814: Movie | C6814: Frozen Planet: The Epic Journey | D6814: Unknown | E6814: David Attenborough | F6814: United Kingdom, United States, Spain, Germany, Greece, Canada | G6814: 42397 | H6814: 2011 | I6814: TV-PG | J6814: 52 min | K6814: Movies | L6814: Collecting highlights from the epic documentary series that explores the entire polar year and the inhabitants, from the north to the south. | M6814: =IF(G6814="","",YEAR(G6814)) -> 2016 | N6814: =IF(G6814="","",MONTH(G6814)) -> 1 | O6814: =IFERROR(VLOOKUP(I6814,Lists!$F$2:$G$16,2,FALSE()),"Not Rated") -> Older Kids | P6814: =IFERROR(VALUE(LEFT(J6814,FIND(" ",J6814)-1)),"") -> 52 | Q6814: =IFERROR(LEFT(F6814,FIND(",",F6814)-1),F6814) -> United Kingdom | R6814: ="|"&SUBSTITUTE(F6814,", ","|")&"|" -> |United Kingdom|United States|Spain|Germany|Greece|Canada| | S6814: ="|"&SUBSTITUTE(K6814,", ","|")&"|" -> |Movies| | T6814: ="|"&SUBSTITUTE(D6814,", ","|")&"|" -> |Unknown| | U6814: ="|"&SUBSTITUTE(E6814,", ","|")&"|" -> |David Attenborough|
A6815: s6814 | B6815: Movie | C6815: Frozen River | D6815: Courtney Hunt | E6815: Melissa Leo, Misty Upham, Charlie McDermott, Michael O'Keefe, Mark Boone Junior, James Reilly, Jay Klaitz, John Canoe, Dylan Carusona, Michael Sky | F6815: United States | G6815: 43647 | H6815: 2008 | I6815: R | J6815: 97 min | K6815: Dramas, Independent Movies | L6815: On a Mohawk reservation on the Canadian border, Ray Eddy teams with a widowed tribe member to smuggle illegal immigrants into the United States. | M6815: =IF(G6815="","",YEAR(G6815)) -> 2019 | N6815: =IF(G6815="","",MONTH(G6815)) -> 7 | O6815: =IFERROR(VLOOKUP(I6815,Lists!$F$2:$G$16,2,FALSE()),"Not Rated") -> Adults | P6815: =IFERROR(VALUE(LEFT(J6815,FIND(" ",J6815)-1)),"") -> 97 | Q6815: =IFERROR(LEFT(F6815,FIND(",",F6815)-1),F6815) -> United States | R6815: ="|"&SUBSTITUTE(F6815,", ","|")&"|" -> |United States| | S6815: ="|"&SUBSTITUTE(K6815,", ","|")&"|" -> |Dramas|Independent Movies| | T6815: ="|"&SUBSTITUTE(D6815,", ","|")&"|" -> |Courtney Hunt| | U6815: ="|"&SUBSTITUTE(E6815,", ","|")&"|" -> |Melissa Leo|Misty Upham|Charlie McDermott|Michael O'Keefe|Mark Boone Junior|James Reilly|Jay Klaitz|John Canoe|Dylan Carusona|Michael Sky|
A6816: s6815 | B6816: Movie | C6816: Full Out | D6816: Sean Cisterna | E6816: Jennifer Beals, Ana Golja, Art Hindle, Jake Epstein, Ramona Milano, Trevor Tordjman, Lamar Johnson, Asha Bromfield, Sarah Fisher | F6816: Canada, United States | G6816: 42614 | H6816: 2015 | I6816: TV-PG | J6816: 88 min | K6816: Children & Family Movies, Dramas, Sports Movies | L6816: After a debilitating accident ends her Olympic dreams, gymnast Ariana Berlin finds recovery and hope in the world of hip-hop and college athletics. | M6816: =IF(G6816="","",YEAR(G6816)) -> 2016 | N6816: =IF(G6816="","",MONTH(G6816)) -> 9 | O6816: =IFERROR(VLOOKUP(I6816,Lists!$F$2:$G$16,2,FALSE()),"Not Rated") -> Older Kids | P6816: =IFERROR(VALUE(LEFT(J6816,FIND(" ",J6816)-1)),"") -> 88 | Q6816: =IFERROR(LEFT(F6816,FIND(",",F6816)-1),F6816) -> Canada | R6816: ="|"&SUBSTITUTE(F6816,", ","|")&"|" -> |Canada|United States| | S6816: ="|"&SUBSTITUTE(K6816,", ","|")&"|" -> |Children & Family Movies|Dramas|Sports Movies| | T6816: ="|"&SUBSTITUTE(D6816,", ","|")&"|" -> |Sean Cisterna| | U6816: ="|"&SUBSTITUTE(E6816,", ","|")&"|" -> |Jennifer Beals|Ana Golja|Art Hindle|Jake Epstein|Ramona Milano|Trevor Tordjman|Lamar Johnson|Asha Bromfield|Sarah Fisher|
A6817: s6816 | B6817: Movie | C6817: Functional Fitness | D6817: Bob Rose | E6817: Unknown | F6817: United States | G6817: 43101 | H6817: 2016 | I6817: TV-MA | J6817: 106 min | K6817: Documentaries | L6817: This documentary explores the challenging, transformative world of high-intensity fitness programs through the eyes of the people who've embraced them. | M6817: =IF(G6817="","",YEAR(G6817)) -> 2018 | N6817: =IF(G6817="","",MONTH(G6817)) -> 1 | O6817: =IFERROR(VLOOKUP(I6817,Lists!$F$2:$G$16,2,FALSE()),"Not Rated") -> Adults | P6817: =IFERROR(VALUE(LEFT(J6817,FIND(" ",J6817)-1)),"") -> 106 | Q6817: =IFERROR(LEFT(F6817,FIND(",",F6817)-1),F6817) -> United States | R6817: ="|"&SUBSTITUTE(F6817,", ","|")&"|" -> |United States| | S6817: ="|"&SUBSTITUTE(K6817,", ","|")&"|" -> |Documentaries| | T6817: ="|"&SUBSTITUTE(D6817,", ","|")&"|" -> |Bob Rose| | U6817: ="|"&SUBSTITUTE(E6817,", ","|")&"|" -> |Unknown|
A6818: s6817 | B6818: Movie | C6818: Furie | D6818: Le Van Kiet | E6818: Ngo Thanh Van, Phan Thanh Nhien, Mai Cat Vi, Thanh Hoa, Pham Anh Khoa | F6818: Vietnam | G6818: 43733 | H6818: 2019 | I6818: TV-MA | J6818: 97 min | K6818: Action & Adventure, Dramas, International Movies | L6818: When traffickers kidnap her daughter from their village, vengeful Hai Phuong returns to Saigon – and her outlaw roots – to take down the abductors. | M6818: =IF(G6818="","",YEAR(G6818)) -> 2019 | N6818: =IF(G6818="","",MONTH(G6818)) -> 9 | O6818: =IFERROR(VLOOKUP(I6818,Lists!$F$2:$G$16,2,FALSE()),"Not Rated") -> Adults | P6818: =IFERROR(VALUE(LEFT(J6818,FIND(" ",J6818)-1)),"") -> 97 | Q6818: =IFERROR(LEFT(F6818,FIND(",",F6818)-1),F6818) -> Vietnam | R6818: ="|"&SUBSTITUTE(F6818,", ","|")&"|" -> |Vietnam| | S6818: ="|"&SUBSTITUTE(K6818,", ","|")&"|" -> |Action & Adventure|Dramas|International Movies| | T6818: ="|"&SUBSTITUTE(D6818,", ","|")&"|" -> |Le Van Kiet| | U6818: ="|"&SUBSTITUTE(E6818,", ","|")&"|" -> |Ngo Thanh Van|Phan Thanh Nhien|Mai Cat Vi|Thanh Hoa|Pham Anh Khoa|
A6819: s6818 | B6819: Movie | C6819: Furthest Witness | D6819: Adam Del Giudice | E6819: Aaron Stanford, Teri Reeves, Sean Patrick Flanery, Forrest Fyre, Steven Michael Quezada, Paul Blott, Travis Hammer, Ryan Begay, Jermaine Washington, Vincent McDaniel | F6819: United States, United Kingdom | G6819: 43579 | H6819: 2017 | I6819: TV-MA | J6819: 88 min | K6819: Dramas, Thrillers | L6819: Kyle helps people disappear, but when a crazed killer starts hunting down his latest client, he has to decide what he's willing to do to keep her safe. | M6819: =IF(G6819="","",YEAR(G6819)) -> 2019 | N6819: =IF(G6819="","",MONTH(G6819)) -> 4 | O6819: =IFERROR(VLOOKUP(I6819,Lists!$F$2:$G$16,2,FALSE()),"Not Rated") -> Adults | P6819: =IFERROR(VALUE(LEFT(J6819,FIND(" ",J6819)-1)),"") -> 88 | Q6819: =IFERROR(LEFT(F6819,FIND(",",F6819)-1),F6819) -> United States | R6819: ="|"&SUBSTITUTE(F6819,", ","|")&"|" -> |United States|United Kingdom| | S6819: ="|"&SUBSTITUTE(K6819,", ","|")&"|" -> |Dramas|Thrillers| | T6819: ="|"&SUBSTITUTE(D6819,", ","|")&"|" -> |Adam Del Giudice| | U6819: ="|"&SUBSTITUTE(E6819,", ","|")&"|" -> |Aaron Stanford|Teri Reeves|Sean Patrick Flanery|Forrest Fyre|Steven Michael Quezada|Paul Blott|Travis Hammer|Ryan Begay|Jermaine Washington|Vincent McDaniel|
A6820: s6819 | B6820: Movie | C6820: G-Force | D6820: Hoyt Yeatman | E6820: Bill Nighy, Will Arnett, Zach Galifianakis, Kelli Garner, Tyler Patrick Jones, Piper Mackenzie Harris, Gabriel Casseus, Jack Conley, Niecy Nash, Justin Mentell, Nicolas Cage, Sam Rockwell, Jon Favreau, Penélope Cruz, Steve Buscemi, Tracy Morgan | F6820: United States | G6820: 43539 | H6820: 2009 | I6820: PG | J6820: 88 min | K6820: Children & Family Movies, Comedies | L6820: When a billionaire sets out to take over the world, only one special forces unit can handle the job – a squad of highly trained guinea pigs. | M6820: =IF(G6820="","",YEAR(G6820)) -> 2019 | N6820: =IF(G6820="","",MONTH(G6820)) -> 3 | O6820: =IFERROR(VLOOKUP(I6820,Lists!$F$2:$G$16,2,FALSE()),"Not Rated") -> Older Kids | P6820: =IFERROR(VALUE(LEFT(J6820,FIND(" ",J6820)-1)),"") -> 88 | Q6820: =IFERROR(LEFT(F6820,FIND(",",F6820)-1),F6820) -> United States | R6820: ="|"&SUBSTITUTE(F6820,", ","|")&"|" -> |United States| | S6820: ="|"&SUBSTITUTE(K6820,", ","|")&"|" -> |Children & Family Movies|Comedies| | T6820: ="|"&SUBSTITUTE(D6820,", ","|")&"|" -> |Hoyt Yeatman| | U6820: ="|"&SUBSTITUTE(E6820,", ","|")&"|" -> |Bill Nighy|Will Arnett|Zach Galifianakis|Kelli Garner|Tyler Patrick Jones|Piper Mackenzie Harris|Gabriel Casseus|Jack Conley|Niecy Nash|Justin Mentell|Nicolas Cage|Sam Rockwell|Jon Favreau|Penélope Cruz|Steve Buscemi|Tracy Morgan|
... A6902: s6901 | B6902: Movie | C6902: Gun Runners | D6902: Anjali Nayar | E6902: Unknown | F6902: Canada | G6902: 42767 | H6902: 2015 | I6902: TV-PG | J6902: 90 min | K6902: Documentaries, International Movies, Sports Movies | L6902: Two roaming Kenyan bandits attempt to change the course of their lives by exchanging their rifles for running shoes. | M6902: =IF(G6902="","",YEAR(G6902)) -> 2017 | N6902: =IF(G6902="","",MONTH(G6902)) -> 2 | O6902: =IFERROR(VLOOKUP(I6902,Lists!$F$2:$G$16,2,FALSE()),"Not Rated") -> Older Kids | P6902: =IFERROR(VALUE(LEFT(J6902,FIND(" ",J6902)-1)),"") -> 90 | Q6902: =IFERROR(LEFT(F6902,FIND(",",F6902)-1),F6902) -> Canada | R6902: ="|"&SUBSTITUTE(F6902,", ","|")&"|" -> |Canada| | S6902: ="|"&SUBSTITUTE(K6902,", ","|")&"|" -> |Documentaries|International Movies|Sports Movies| | T6902: ="|"&SUBSTITUTE(D6902,", ","|")&"|" -> |Anjali Nayar| | U6902: ="|"&SUBSTITUTE(E6902,", ","|")&"|" -> |Unknown|
A6903: s6902 | B6903: TV Show | C6903: Gunslinger Girl | D6903: Unknown | E6903: Yuuka Nanri, Kanako Mitsuhashi, Eri Sendai, Ami Koshimizu, Hidenobu Kiuchi, Mitsuru Miyamoto, Masashi Ebara, Norihiro Inoue, Rie Nakagawa, Masami Iwasaki, Laura Bailey, Luci Christian, Caitlin Glass, Alese Johnson, Monica Rial, Jerry Jewell, Stephanie Young, Mike McFarland | F6903: Japan | H6903: 2008 | I6903: TV-14 | J6903: 2 Seasons | K6903: Anime Series, Crime TV Shows | L6903: On the surface, the Social Welfare Agency appears to help orphaned schoolgirls, but it's actually turning them into lethal agents. | M6903: =IF(G6903="","",YEAR(G6903)) | N6903: =IF(G6903="","",MONTH(G6903)) | O6903: =IFERROR(VLOOKUP(I6903,Lists!$F$2:$G$16,2,FALSE()),"Not Rated") -> Teens | P6903: =IFERROR(VALUE(LEFT(J6903,FIND(" ",J6903)-1)),"") -> 2 | Q6903: =IFERROR(LEFT(F6903,FIND(",",F6903)-1),F6903) -> Japan | R6903: ="|"&SUBSTITUTE(F6903,", ","|")&"|" -> |Japan| | S6903: ="|"&SUBSTITUTE(K6903,", ","|")&"|" -> |Anime Series|Crime TV Shows| | T6903: ="|"&SUBSTITUTE(D6903,", ","|")&"|" -> |Unknown| | U6903: ="|"&SUBSTITUTE(E6903,", ","|")&"|" -> |Yuuka Nanri|Kanako Mitsuhashi|Eri Sendai|Ami Koshimizu|Hidenobu Kiuchi|Mitsuru Miyamoto|Masashi Ebara|Norihiro Inoue|Rie Nakagawa|Masami Iwasaki|Laura Bailey|Luci Christian|Caitlin Glass|Alese Johnson|Monica Rial|Jerry Jewell|Stephanie Young|Mike McFarland|
A6904: s6903 | B6904: Movie | C6904: Guy Martin: Last Flight of the Vulcan Bomber | D6904: James Woodroffe | E6904: Guy Martin, Kevin Stone, Shaun Dooley | F6904: United Kingdom | G6904: 43672 | H6904: 2015 | I6904: TV-G | J6904: 57 min | K6904: Documentaries, International Movies | L6904: Guy Martin assists in preparing the last airworthy Vulcan bomber for a farewell tour while revealing the stories behind the iconic aircraft. | M6904: =IF(G6904="","",YEAR(G6904)) -> 2019 | N6904: =IF(G6904="","",MONTH(G6904)) -> 7 | O6904: =IFERROR(VLOOKUP(I6904,Lists!$F$2:$G$16,2,FALSE()),"Not Rated") -> Kids | P6904: =IFERROR(VALUE(LEFT(J6904,FIND(" ",J6904)-1)),"") -> 57 | Q6904: =IFERROR(LEFT(F6904,FIND(",",F6904)-1),F6904) -> United Kingdom | R6904: ="|"&SUBSTITUTE(F6904,", ","|")&"|" -> |United Kingdom| | S6904: ="|"&SUBSTITUTE(K6904,", ","|")&"|" -> |Documentaries|International Movies| | T6904: ="|"&SUBSTITUTE(D6904,", ","|")&"|" -> |James Woodroffe| | U6904: ="|"&SUBSTITUTE(E6904,", ","|")&"|" -> |Guy Martin|Kevin Stone|Shaun Dooley|
A6905: s6904 | B6905: Movie | C6905: Héroes | D6905: Esteban Vidal | E6905: Fabrizio Copano, Juanita Ringeling, Fernando Alarcón, Delfina Guzmán, Paty Cofré, Andrés Rillón, Julio Jung, Nicolás Oyarzún | F6905: Chile | G6905: 43331 | H6905: 2015 | I6905: TV-MA | J6905: 91 min | K6905: Comedies, International Movies | L6905: When an earthquake hits Chile, rescue workers must put aside their differences to save the country from a businessman's evil scheme. | M6905: =IF(G6905="","",YEAR(G6905)) -> 2018 | N6905: =IF(G6905="","",MONTH(G6905)) -> 8 | O6905: =IFERROR(VLOOKUP(I6905,Lists!$F$2:$G$16,2,FALSE()),"Not Rated") -> Adults | P6905: =IFERROR(VALUE(LEFT(J6905,FIND(" ",J6905)-1)),"") -> 91 | Q6905: =IFERROR(LEFT(F6905,FIND(",",F6905)-1),F6905) -> Chile | R6905: ="|"&SUBSTITUTE(F6905,", ","|")&"|" -> |Chile| | S6905: ="|"&SUBSTITUTE(K6905,", ","|")&"|" -> |Comedies|International Movies| | T6905: ="|"&SUBSTITUTE(D6905,", ","|")&"|" -> |Esteban Vidal| | U6905: ="|"&SUBSTITUTE(E6905,", ","|")&"|" -> |Fabrizio Copano|Juanita Ringeling|Fernando Alarcón|Delfina Guzmán|Paty Cofré|Andrés Rillón|Julio Jung|Nicolás Oyarzún|
A6906: s6905 | B6906: Movie | C6906: Hükümet Kadin | D6906: Sermiyan Midyat | E6906: Demet Akbağ, Sermiyan Midyat, Mahir İpek, Gülhan Tekin, Burcu Gönder, Cezmi Baskın, Renan Bilek, Ayberk Attila, Rıza Akın, Bülent Çolak | F6906: Turkey | G6906: 42804 | H6906: 2013 | I6906: TV-MA | J6906: 100 min | K6906: Comedies, International Movies | L6906: When an uneducated mother of eight suddenly becomes mayor, she uses the skills she's learned as a housewife to keep her town running like clockwork. | M6906: =IF(G6906="","",YEAR(G6906)) -> 2017 | N6906: =IF(G6906="","",MONTH(G6906)) -> 3 | O6906: =IFERROR(VLOOKUP(I6906,Lists!$F$2:$G$16,2,FALSE()),"Not Rated") -> Adults | P6906: =IFERROR(VALUE(LEFT(J6906,FIND(" ",J6906)-1)),"") -> 100 | Q6906: =IFERROR(LEFT(F6906,FIND(",",F6906)-1),F6906) -> Turkey | R6906: ="|"&SUBSTITUTE(F6906,", ","|")&"|" -> |Turkey| | S6906: ="|"&SUBSTITUTE(K6906,", ","|")&"|" -> |Comedies|International Movies| | T6906: ="|"&SUBSTITUTE(D6906,", ","|")&"|" -> |Sermiyan Midyat| | U6906: ="|"&SUBSTITUTE(E6906,", ","|")&"|" -> |Demet Akbağ|Sermiyan Midyat|Mahir İpek|Gülhan Tekin|Burcu Gönder|Cezmi Baskın|Renan Bilek|Ayberk Attila|Rıza Akın|Bülent Çolak|
A6907: s6906 | B6907: Movie | C6907: Hükümet Kadin 2 | D6907: Sermiyan Midyat | E6907: Demet Akbağ, Sermiyan Midyat, Mahir İpek, Gülhan Tekin, Burcu Gönder, Mine Şenhuy Teber, Osman Alkaş, Bülent Çolak, Olgun Toker, Doğukan Polat | F6907: Turkey | G6907: 42804 | H6907: 2013 | I6907: TV-14 | J6907: 101 min | K6907: Comedies, International Movies | L6907: In 1949, with freedoms threatened, housewife Hükümet is unaware of her future life in politics as she faces off with liar and mayoral hopeful Faruk. | M6907: =IF(G6907="","",YEAR(G6907)) -> 2017 | N6907: =IF(G6907="","",MONTH(G6907)) -> 3 | O6907: =IFERROR(VLOOKUP(I6907,Lists!$F$2:$G$16,2,FALSE()),"Not Rated") -> Teens | P6907: =IFERROR(VALUE(LEFT(J6907,FIND(" ",J6907)-1)),"") -> 101 | Q6907: =IFERROR(LEFT(F6907,FIND(",",F6907)-1),F6907) -> Turkey | R6907: ="|"&SUBSTITUTE(F6907,", ","|")&"|" -> |Turkey| | S6907: ="|"&SUBSTITUTE(K6907,", ","|")&"|" -> |Comedies|International Movies| | T6907: ="|"&SUBSTITUTE(D6907,", ","|")&"|" -> |Sermiyan Midyat| | U6907: ="|"&SUBSTITUTE(E6907,", ","|")&"|" -> |Demet Akbağ|Sermiyan Midyat|Mahir İpek|Gülhan Tekin|Burcu Gönder|Mine Şenhuy Teber|Osman Alkaş|Bülent Çolak|Olgun Toker|Doğukan Polat|
A6908: s6907 | B6908: TV Show | C6908: Ha Unlimited | D6908: Unknown | E6908: Tuck Boriboon, Ball Chernyim, Na’Kom Chuanchuen | F6908: Unknown | G6908: 43231 | H6908: 2016 | I6908: TV-MA | J6908: 2 Seasons | K6908: International TV Shows, TV Comedies | L6908: Three comedians launch a company designed to spread happiness far and wide in this Thai sitcom packed with gags, sound effects and special guests. | M6908: =IF(G6908="","",YEAR(G6908)) -> 2018 | N6908: =IF(G6908="","",MONTH(G6908)) -> 5 | O6908: =IFERROR(VLOOKUP(I6908,Lists!$F$2:$G$16,2,FALSE()),"Not Rated") -> Adults | P6908: =IFERROR(VALUE(LEFT(J6908,FIND(" ",J6908)-1)),"") -> 2 | Q6908: =IFERROR(LEFT(F6908,FIND(",",F6908)-1),F6908) -> Unknown | R6908: ="|"&SUBSTITUTE(F6908,", ","|")&"|" -> |Unknown| | S6908: ="|"&SUBSTITUTE(K6908,", ","|")&"|" -> |International TV Shows|TV Comedies| | T6908: ="|"&SUBSTITUTE(D6908,", ","|")&"|" -> |Unknown| | U6908: ="|"&SUBSTITUTE(E6908,", ","|")&"|" -> |Tuck Boriboon|Ball Chernyim|Na’Kom Chuanchuen|
A6909: s6908 | B6909: Movie | C6909: Haapus | D6909: Unknown | E6909: Makarand Anaspure, Madhura Velankar, Subodh Bhave | F6909: India | G6909: 43174 | H6909: 2010 | I6909: TV-14 | J6909: 138 min | K6909: Comedies, Dramas, International Movies | L6909: The son of an astrologer faces opposition from his superstitious father regarding his scheme of launching a mango business. | M6909: =IF(G6909="","",YEAR(G6909)) -> 2018 | N6909: =IF(G6909="","",MONTH(G6909)) -> 3 | O6909: =IFERROR(VLOOKUP(I6909,Lists!$F$2:$G$16,2,FALSE()),"Not Rated") -> Teens | P6909: =IFERROR(VALUE(LEFT(J6909,FIND(" ",J6909)-1)),"") -> 138 | Q6909: =IFERROR(LEFT(F6909,FIND(",",F6909)-1),F6909) -> India | R6909: ="|"&SUBSTITUTE(F6909,", ","|")&"|" -> |India| | S6909: ="|"&SUBSTITUTE(K6909,", ","|")&"|" -> |Comedies|Dramas|International Movies| | T6909: ="|"&SUBSTITUTE(D6909,", ","|")&"|" -> |Unknown| | U6909: ="|"&SUBSTITUTE(E6909,", ","|")&"|" -> |Makarand Anaspure|Madhura Velankar|Subodh Bhave|
A6910: s6909 | B6910: Movie | C6910: Hadi İnşallah | D6910: Ali Taner Baltacı | E6910: Büşra Pekin, Murat Boz, Cezmi Baskın, Şinasi Yurtsever, İdil Dizdar, Hülya Gülsen Irmak, Canan Özer, Şenay Bozoklar, Emrah Kaman, Müjde Uzman | F6910: Turkey | G6910: 43194 | H6910: 2014 | I6910: TV-14 | J6910: 95 min | K6910: Comedies, International Movies, Romantic Movies | L6910: A young woman recovering poorly from a bad romance gets a new lease on life after encountering a handsome man during a job interview. | M6910: =IF(G6910="","",YEAR(G6910)) -> 2018 | N6910: =IF(G6910="","",MONTH(G6910)) -> 4 | O6910: =IFERROR(VLOOKUP(I6910,Lists!$F$2:$G$16,2,FALSE()),"Not Rated") -> Teens | P6910: =IFERROR(VALUE(LEFT(J6910,FIND(" ",J6910)-1)),"") -> 95 | Q6910: =IFERROR(LEFT(F6910,FIND(",",F6910)-1),F6910) -> Turkey | R6910: ="|"&SUBSTITUTE(F6910,", ","|")&"|" -> |Turkey| | S6910: ="|"&SUBSTITUTE(K6910,", ","|")&"|" -> |Comedies|International Movies|Romantic Movies| | T6910: ="|"&SUBSTITUTE(D6910,", ","|")&"|" -> |Ali Taner Baltacı| | U6910: ="|"&SUBSTITUTE(E6910,", ","|")&"|" -> |Büşra Pekin|Murat Boz|Cezmi Baskın|Şinasi Yurtsever|İdil Dizdar|Hülya Gülsen Irmak|Canan Özer|Şenay Bozoklar|Emrah Kaman|Müjde Uzman|
A6911: s6910 | B6911: Movie | C6911: Hairspray | D6911: Adam Shankman | E6911: Nikki Blonsky, John Travolta, Michelle Pfeiffer, Christopher Walken, Amanda Bynes, James Marsden, Queen Latifah, Zac Efron, Brittany Snow, Allison Janney, Elijah Kelley, Jerry Stiller | F6911: United States, United Kingdom, Canada | G6911: 43831 | H6911: 2007 | I6911: PG | J6911: 116 min | K6911: Children & Family Movies, Comedies, Music & Musicals | L6911: In 1962, ambitious plus-size teen Tracy Turnblad tries to integrate a racially divided Baltimore one Watusi at a time. | M6911: =IF(G6911="","",YEAR(G6911)) -> 2020 | N6911: =IF(G6911="","",MONTH(G6911)) -> 1 | O6911: =IFERROR(VLOOKUP(I6911,Lists!$F$2:$G$16,2,FALSE()),"Not Rated") -> Older Kids | P6911: =IFERROR(VALUE(LEFT(J6911,FIND(" ",J6911)-1)),"") -> 116 | Q6911: =IFERROR(LEFT(F6911,FIND(",",F6911)-1),F6911) -> United States | R6911: ="|"&SUBSTITUTE(F6911,", ","|")&"|" -> |United States|United Kingdom|Canada| | S6911: ="|"&SUBSTITUTE(K6911,", ","|")&"|" -> |Children & Family Movies|Comedies|Music & Musicals| | T6911: ="|"&SUBSTITUTE(D6911,", ","|")&"|" -> |Adam Shankman| | U6911: ="|"&SUBSTITUTE(E6911,", ","|")&"|" -> |Nikki Blonsky|John Travolta|Michelle Pfeiffer|Christopher Walken|Amanda Bynes|James Marsden|Queen Latifah|Zac Efron|Brittany Snow|Allison Janney|Elijah Kelley|Jerry Stiller|
A6912: s6911 | B6912: Movie | C6912: HALO Legends | D6912: Shinji Aramaki, Mamoru Oshii, Hideki Futamura, Toshiyuki Kanno, Tomoki Kyoda, Koichi Mashimo, Yasushi Muraki, Daisuke Nishio, Frank O'Connor, Koji Sawai, Joseph Chou, Hiroshi Yamazaki | E6912: Andy McAvin, James Faulkner, Luci Christian, John Swasey | F6912: United States, Japan | G6912: 42856 | H6912: 2009 | I6912: PG-13 | J6912: 117 min | K6912: Action & Adventure, Anime Features, Sci-Fi & Fantasy | L6912: This anthology features seven independent anime shorts from renowned directors, delving into the futuristic universe of the video game franchise Halo. | M6912: =IF(G6912="","",YEAR(G6912)) -> 2017 | N6912: =IF(G6912="","",MONTH(G6912)) -> 5 | O6912: =IFERROR(VLOOKUP(I6912,Lists!$F$2:$G$16,2,FALSE()),"Not Rated") -> Teens | P6912: =IFERROR(VALUE(LEFT(J6912,FIND(" ",J6912)-1)),"") -> 117 | Q6912: =IFERROR(LEFT(F6912,FIND(",",F6912)-1),F6912) -> United States | R6912: ="|"&SUBSTITUTE(F6912,", ","|")&"|" -> |United States|Japan| | S6912: ="|"&SUBSTITUTE(K6912,", ","|")&"|" -> |Action & Adventure|Anime Features|Sci-Fi & Fantasy| | T6912: ="|"&SUBSTITUTE(D6912,", ","|")&"|" -> |Shinji Aramaki|Mamoru Oshii|Hideki Futamura|Toshiyuki Kanno|Tomoki Kyoda|Koichi Mashimo|Yasushi Muraki|Daisuke Nishio|Frank O'Connor|Koji Sawai|Joseph Chou|Hiroshi Yamazaki| | U6912: ="|"&SUBSTITUTE(E6912,", ","|")&"|" -> |Andy McAvin|James Faulkner|Luci Christian|John Swasey|
A6913: s6912 | B6913: Movie | C6913: Halo: The Fall of Reach | D6913: Ian Kirby | E6913: Jen Taylor, Steve Downes, Michelle Lukes, Britt Baron, Travis Willingham, John Bently, Todd Haberkorn, Cole Jensen | F6913: United States | G6913: 42436 | H6913: 2015 | I6913: TV-14 | J6913: 65 min | K6913: Action & Adventure, Sci-Fi & Fantasy | L6913: Witness the origins of Master Chief and the Spartan program as a group of children transform into enhanced soldiers and fight a powerful alien threat. | M6913: =IF(G6913="","",YEAR(G6913)) -> 2016 | N6913: =IF(G6913="","",MONTH(G6913)) -> 3 | O6913: =IFERROR(VLOOKUP(I6913,Lists!$F$2:$G$16,2,FALSE()),"Not Rated") -> Teens | P6913: =IFERROR(VALUE(LEFT(J6913,FIND(" ",J6913)-1)),"") -> 65 | Q6913: =IFERROR(LEFT(F6913,FIND(",",F6913)-1),F6913) -> United States | R6913: ="|"&SUBSTITUTE(F6913,", ","|")&"|" -> |United States| | S6913: ="|"&SUBSTITUTE(K6913,", ","|")&"|" -> |Action & Adventure|Sci-Fi & Fantasy| | T6913: ="|"&SUBSTITUTE(D6913,", ","|")&"|" -> |Ian Kirby| | U6913: ="|"&SUBSTITUTE(E6913,", ","|")&"|" -> |Jen Taylor|Steve Downes|Michelle Lukes|Britt Baron|Travis Willingham|John Bently|Todd Haberkorn|Cole Jensen|
A6914: s6913 | B6914: Movie | C6914: Hamara Dil Aapke Paas Hai | D6914: Satish Kaushik | E6914: Anil Kapoor, Aishwarya Rai Bachchan, Sonali Bendre, Puru Rajkumar, Anupam Kher, Satish Kaushik, Mukesh Rishi, Jaspal Bhatti, Razak Khan, Himani Shivpuri, Smita Jaykar, Tanaaz Currim Irani | F6914: India | G6914: 43160 | H6914: 2000 | I6914: TV-14 | J6914: 158 min | K6914: Dramas, International Movies, Music & Musicals | L6914: Love blooms when kind-hearted Avinash takes in Preeti, a woman shunned by society, but the unorthodox living situation creates quite a stir among the neighbors. | M6914: =IF(G6914="","",YEAR(G6914)) -> 2018 | N6914: =IF(G6914="","",MONTH(G6914)) -> 3 | O6914: =IFERROR(VLOOKUP(I6914,Lists!$F$2:$G$16,2,FALSE()),"Not Rated") -> Teens | P6914: =IFERROR(VALUE(LEFT(J6914,FIND(" ",J6914)-1)),"") -> 158 | Q6914: =IFERROR(LEFT(F6914,FIND(",",F6914)-1),F6914) -> India | R6914: ="|"&SUBSTITUTE(F6914,", ","|")&"|" -> |India| | S6914: ="|"&SUBSTITUTE(K6914,", ","|")&"|" -> |Dramas|International Movies|Music & Musicals| | T6914: ="|"&SUBSTITUTE(D6914,", ","|")&"|" -> |Satish Kaushik| | U6914: ="|"&SUBSTITUTE(E6914,", ","|")&"|" -> |Anil Kapoor|Aishwarya Rai Bachchan|Sonali Bendre|Puru Rajkumar|Anupam Kher|Satish Kaushik|Mukesh Rishi|Jaspal Bhatti|Razak Khan|Himani Shivpuri|Smita Jaykar|Tanaaz Currim Irani|
A6915: s6914 | B6915: Movie | C6915: Hamburger Hill | D6915: John Irvin | E6915: Anthony Barille, Michael Boatman, Don Cheadle, Michael Dolan, Don James, Dylan McDermott, Michael A. Nickles, Harry O'Reilly, Daniel O'Shea, Tim Quill, Tommy Swerdlow, Courtney B. Vance, Steven Weber, Tegan West | F6915: United States | G6915: 43792 | H6915: 1987 | I6915: R | J6915: 110 min | K6915: Action & Adventure, Dramas | L6915: The Vietnam War's horrors come brutally to life through the eyes of American soldiers trying to take a heavily fortified hill under Vietcong control. | M6915: =IF(G6915="","",YEAR(G6915)) -> 2019 | N6915: =IF(G6915="","",MONTH(G6915)) -> 11 | O6915: =IFERROR(VLOOKUP(I6915,Lists!$F$2:$G$16,2,FALSE()),"Not Rated") -> Adults | P6915: =IFERROR(VALUE(LEFT(J6915,FIND(" ",J6915)-1)),"") -> 110 | Q6915: =IFERROR(LEFT(F6915,FIND(",",F6915)-1),F6915) -> United States | R6915: ="|"&SUBSTITUTE(F6915,", ","|")&"|" -> |United States| | S6915: ="|"&SUBSTITUTE(K6915,", ","|")&"|" -> |Action & Adventure|Dramas| | T6915: ="|"&SUBSTITUTE(D6915,", ","|")&"|" -> |John Irvin| | U6915: ="|"&SUBSTITUTE(E6915,", ","|")&"|" -> |Anthony Barille|Michael Boatman|Don Cheadle|Michael Dolan|Don James|Dylan McDermott|Michael A. Nickles|Harry O'Reilly|Daniel O'Shea|Tim Quill|Tommy Swerdlow|Courtney B. Vance|Steven Weber|Tegan West|
... A7197: s7196 | B7197: Movie | C7197: Kidnapping Mr. Heineken | D7197: Daniel Alfredson | E7197: Jim Sturgess, Sam Worthington, Ryan Kwanten, Anthony Hopkins, Mark van Eeuwen, Thomas Cocquerel, Jemima West, David Dencik | F7197: Netherlands, Belgium, United Kingdom, United States | G7197: 42986 | H7197: 2015 | I7197: R | J7197: 95 min | K7197: Action & Adventure, Dramas, International Movies | L7197: When beer magnate Alfred "Freddy" Heineken is kidnapped in 1983, his abductors make the largest ransom demand in history. | M7197: =IF(G7197="","",YEAR(G7197)) -> 2017 | N7197: =IF(G7197="","",MONTH(G7197)) -> 9 | O7197: =IFERROR(VLOOKUP(I7197,Lists!$F$2:$G$16,2,FALSE()),"Not Rated") -> Adults | P7197: =IFERROR(VALUE(LEFT(J7197,FIND(" ",J7197)-1)),"") -> 95 | Q7197: =IFERROR(LEFT(F7197,FIND(",",F7197)-1),F7197) -> Netherlands | R7197: ="|"&SUBSTITUTE(F7197,", ","|")&"|" -> |Netherlands|Belgium|United Kingdom|United States| | S7197: ="|"&SUBSTITUTE(K7197,", ","|")&"|" -> |Action & Adventure|Dramas|International Movies| | T7197: ="|"&SUBSTITUTE(D7197,", ","|")&"|" -> |Daniel Alfredson| | U7197: ="|"&SUBSTITUTE(E7197,", ","|")&"|" -> |Jim Sturgess|Sam Worthington|Ryan Kwanten|Anthony Hopkins|Mark van Eeuwen|Thomas Cocquerel|Jemima West|David Dencik|
A7198: s7197 | B7198: TV Show | C7198: Kikoriki | D7198: Unknown | E7198: Igor Dmitriev | F7198: Unknown | H7198: 2010 | I7198: TV-Y | J7198: 2 Seasons | K7198: Kids' TV | L7198: A wacky rabbit and his gang of animal pals have fun solving problems, sharing stories and exploring their sometimes magical, always special world. | M7198: =IF(G7198="","",YEAR(G7198)) | N7198: =IF(G7198="","",MONTH(G7198)) | O7198: =IFERROR(VLOOKUP(I7198,Lists!$F$2:$G$16,2,FALSE()),"Not Rated") -> Kids | P7198: =IFERROR(VALUE(LEFT(J7198,FIND(" ",J7198)-1)),"") -> 2 | Q7198: =IFERROR(LEFT(F7198,FIND(",",F7198)-1),F7198) -> Unknown | R7198: ="|"&SUBSTITUTE(F7198,", ","|")&"|" -> |Unknown| | S7198: ="|"&SUBSTITUTE(K7198,", ","|")&"|" -> |Kids' TV| | T7198: ="|"&SUBSTITUTE(D7198,", ","|")&"|" -> |Unknown| | U7198: ="|"&SUBSTITUTE(E7198,", ","|")&"|" -> |Igor Dmitriev|
A7199: s7198 | B7199: Movie | C7199: Kill Bill: Vol. 1 | D7199: Quentin Tarantino | E7199: Uma Thurman, Lucy Liu, Vivica A. Fox, Daryl Hannah, David Carradine, Michael Madsen, Julie Dreyfus, Chiaki Kuriyama, Sonny Chiba, Gordon Liu | F7199: United States, Japan | G7199: 43831 | H7199: 2003 | I7199: R | J7199: 111 min | K7199: Action & Adventure | L7199: An assassin is shot by her ruthless employer, Bill, and other members of their assassination circle. But she lives – and plots her vengeance. | M7199: =IF(G7199="","",YEAR(G7199)) -> 2020 | N7199: =IF(G7199="","",MONTH(G7199)) -> 1 | O7199: =IFERROR(VLOOKUP(I7199,Lists!$F$2:$G$16,2,FALSE()),"Not Rated") -> Adults | P7199: =IFERROR(VALUE(LEFT(J7199,FIND(" ",J7199)-1)),"") -> 111 | Q7199: =IFERROR(LEFT(F7199,FIND(",",F7199)-1),F7199) -> United States | R7199: ="|"&SUBSTITUTE(F7199,", ","|")&"|" -> |United States|Japan| | S7199: ="|"&SUBSTITUTE(K7199,", ","|")&"|" -> |Action & Adventure| | T7199: ="|"&SUBSTITUTE(D7199,", ","|")&"|" -> |Quentin Tarantino| | U7199: ="|"&SUBSTITUTE(E7199,", ","|")&"|" -> |Uma Thurman|Lucy Liu|Vivica A. Fox|Daryl Hannah|David Carradine|Michael Madsen|Julie Dreyfus|Chiaki Kuriyama|Sonny Chiba|Gordon Liu|
A7200: s7199 | B7200: Movie | C7200: Kill Bill: Vol. 2 | D7200: Quentin Tarantino | E7200: Uma Thurman, David Carradine, Michael Madsen, Daryl Hannah, Gordon Liu, Michael Parks, Perla Haney-Jardine, Helen Kim, Claire Smithies, Clark Middleton | F7200: United States | G7200: 43831 | H7200: 2004 | I7200: R | J7200: 137 min | K7200: Action & Adventure | L7200: The Bride has three left on her rampage list: Budd, Elle Driver and Bill himself. But when she arrives at Bill's house, she's in for a surprise. | M7200: =IF(G7200="","",YEAR(G7200)) -> 2020 | N7200: =IF(G7200="","",MONTH(G7200)) -> 1 | O7200: =IFERROR(VLOOKUP(I7200,Lists!$F$2:$G$16,2,FALSE()),"Not Rated") -> Adults | P7200: =IFERROR(VALUE(LEFT(J7200,FIND(" ",J7200)-1)),"") -> 137 | Q7200: =IFERROR(LEFT(F7200,FIND(",",F7200)-1),F7200) -> United States | R7200: ="|"&SUBSTITUTE(F7200,", ","|")&"|" -> |United States| | S7200: ="|"&SUBSTITUTE(K7200,", ","|")&"|" -> |Action & Adventure| | T7200: ="|"&SUBSTITUTE(D7200,", ","|")&"|" -> |Quentin Tarantino| | U7200: ="|"&SUBSTITUTE(E7200,", ","|")&"|" -> |Uma Thurman|David Carradine|Michael Madsen|Daryl Hannah|Gordon Liu|Michael Parks|Perla Haney-Jardine|Helen Kim|Claire Smithies|Clark Middleton|
A7201: s7200 | B7201: Movie | C7201: Kill Command | D7201: Steven Gomez | E7201: Vanessa Kirby, David Ajala, Mike Noble, Bentley Kalu, Tom McKay, Kelly Gough, Osi Okerafor, Damian Kell, Tim Ahern, Deborah Rosan, Thure Lindhardt | F7201: United Kingdom | G7201: 42789 | H7201: 2016 | I7201: TV-MA | J7201: 100 min | K7201: Action & Adventure, Independent Movies, Sci-Fi & Fantasy | L7201: On a remote island, elite soldiers discover their training exercise is actually an experimental death trap teeming with efficiently lethal robots. | M7201: =IF(G7201="","",YEAR(G7201)) -> 2017 | N7201: =IF(G7201="","",MONTH(G7201)) -> 2 | O7201: =IFERROR(VLOOKUP(I7201,Lists!$F$2:$G$16,2,FALSE()),"Not Rated") -> Adults | P7201: =IFERROR(VALUE(LEFT(J7201,FIND(" ",J7201)-1)),"") -> 100 | Q7201: =IFERROR(LEFT(F7201,FIND(",",F7201)-1),F7201) -> United Kingdom | R7201: ="|"&SUBSTITUTE(F7201,", ","|")&"|" -> |United Kingdom| | S7201: ="|"&SUBSTITUTE(K7201,", ","|")&"|" -> |Action & Adventure|Independent Movies|Sci-Fi & Fantasy| | T7201: ="|"&SUBSTITUTE(D7201,", ","|")&"|" -> |Steven Gomez| | U7201: ="|"&SUBSTITUTE(E7201,", ","|")&"|" -> |Vanessa Kirby|David Ajala|Mike Noble|Bentley Kalu|Tom McKay|Kelly Gough|Osi Okerafor|Damian Kell|Tim Ahern|Deborah Rosan|Thure Lindhardt|
A7202: s7201 | B7202: Movie | C7202: Kill Hitler! The Luck of the Devil | D7202: Frédéric Tonolli | E7202: Jean-Baptiste Marcenac | F7202: France | G7202: 43586 | H7202: 2015 | I7202: TV-14 | J7202: 53 min | K7202: Documentaries, International Movies | L7202: From politicians to officers, many attempted to kill Hitler – and failed. This documentary delves into the details of how their plots unraveled. | M7202: =IF(G7202="","",YEAR(G7202)) -> 2019 | N7202: =IF(G7202="","",MONTH(G7202)) -> 5 | O7202: =IFERROR(VLOOKUP(I7202,Lists!$F$2:$G$16,2,FALSE()),"Not Rated") -> Teens | P7202: =IFERROR(VALUE(LEFT(J7202,FIND(" ",J7202)-1)),"") -> 53 | Q7202: =IFERROR(LEFT(F7202,FIND(",",F7202)-1),F7202) -> France | R7202: ="|"&SUBSTITUTE(F7202,", ","|")&"|" -> |France| | S7202: ="|"&SUBSTITUTE(K7202,", ","|")&"|" -> |Documentaries|International Movies| | T7202: ="|"&SUBSTITUTE(D7202,", ","|")&"|" -> |Frédéric Tonolli| | U7202: ="|"&SUBSTITUTE(E7202,", ","|")&"|" -> |Jean-Baptiste Marcenac|
A7203: s7202 | B7203: Movie | C7203: Kill Ratio | D7203: Paul Tanter | E7203: Tom Hopper, Amy Huberman, Lacy Moore, Brian McGuinness, Luke Pierucci, Nick Dunning | F7203: United States | G7203: 42783 | H7203: 2016 | I7203: TV-MA | J7203: 87 min | K7203: Action & Adventure | L7203: Posing as a telecom salesman at a business conference, a CIA agent fights to protect a fledgling Eastern European democracy from a military coup. | M7203: =IF(G7203="","",YEAR(G7203)) -> 2017 | N7203: =IF(G7203="","",MONTH(G7203)) -> 2 | O7203: =IFERROR(VLOOKUP(I7203,Lists!$F$2:$G$16,2,FALSE()),"Not Rated") -> Adults | P7203: =IFERROR(VALUE(LEFT(J7203,FIND(" ",J7203)-1)),"") -> 87 | Q7203: =IFERROR(LEFT(F7203,FIND(",",F7203)-1),F7203) -> United States | R7203: ="|"&SUBSTITUTE(F7203,", ","|")&"|" -> |United States| | S7203: ="|"&SUBSTITUTE(K7203,", ","|")&"|" -> |Action & Adventure| | T7203: ="|"&SUBSTITUTE(D7203,", ","|")&"|" -> |Paul Tanter| | U7203: ="|"&SUBSTITUTE(E7203,", ","|")&"|" -> |Tom Hopper|Amy Huberman|Lacy Moore|Brian McGuinness|Luke Pierucci|Nick Dunning|
A7204: s7203 | B7204: Movie | C7204: Kill the Irishman | D7204: Jonathan Hensleigh | E7204: Ray Stevenson, Vincent D'Onofrio, Val Kilmer, Christopher Walken, Linda Cardellini, Fionnula Flanagan, Jason Butler Harner, Vinnie Jones, Paul Sorvino, Marcus Thomas, Tony Darrow | F7204: United States | G7204: 44064 | H7204: 2011 | I7204: R | J7204: 106 min | K7204: Action & Adventure, Dramas, Independent Movies | L7204: This true crime tale charts the rise and fall of mobster Danny Greene, who faced down the Mafia to gain control of organized crime in 1970s Cleveland. | M7204: =IF(G7204="","",YEAR(G7204)) -> 2020 | N7204: =IF(G7204="","",MONTH(G7204)) -> 8 | O7204: =IFERROR(VLOOKUP(I7204,Lists!$F$2:$G$16,2,FALSE()),"Not Rated") -> Adults | P7204: =IFERROR(VALUE(LEFT(J7204,FIND(" ",J7204)-1)),"") -> 106 | Q7204: =IFERROR(LEFT(F7204,FIND(",",F7204)-1),F7204) -> United States | R7204: ="|"&SUBSTITUTE(F7204,", ","|")&"|" -> |United States| | S7204: ="|"&SUBSTITUTE(K7204,", ","|")&"|" -> |Action & Adventure|Dramas|Independent Movies| | T7204: ="|"&SUBSTITUTE(D7204,", ","|")&"|" -> |Jonathan Hensleigh| | U7204: ="|"&SUBSTITUTE(E7204,", ","|")&"|" -> |Ray Stevenson|Vincent D'Onofrio|Val Kilmer|Christopher Walken|Linda Cardellini|Fionnula Flanagan|Jason Butler Harner|Vinnie Jones|Paul Sorvino|Marcus Thomas|Tony Darrow|
A7205: s7204 | B7205: Movie | C7205: Killer Klowns from Outer Space | D7205: Stephen Chiodo | E7205: Grant Cramer, Suzanne Snyder, John Allen Nelson, John Vernon, Michael S. Siegel, Peter Licassi, Royal Dano, Christopher Titus, Irene Michaels, Karla Sue Krull | F7205: United States | G7205: 43922 | H7205: 1988 | I7205: PG-13 | J7205: 86 min | K7205: Comedies, Cult Movies, Horror Movies | L7205: An alien band of killer clowns descends from the cosmos to harvest scores of small-town victims, cocooning their prey in cotton candy to eat later. | M7205: =IF(G7205="","",YEAR(G7205)) -> 2020 | N7205: =IF(G7205="","",MONTH(G7205)) -> 4 | O7205: =IFERROR(VLOOKUP(I7205,Lists!$F$2:$G$16,2,FALSE()),"Not Rated") -> Teens | P7205: =IFERROR(VALUE(LEFT(J7205,FIND(" ",J7205)-1)),"") -> 86 | Q7205: =IFERROR(LEFT(F7205,FIND(",",F7205)-1),F7205) -> United States | R7205: ="|"&SUBSTITUTE(F7205,", ","|")&"|" -> |United States| | S7205: ="|"&SUBSTITUTE(K7205,", ","|")&"|" -> |Comedies|Cult Movies|Horror Movies| | T7205: ="|"&SUBSTITUTE(D7205,", ","|")&"|" -> |Stephen Chiodo| | U7205: ="|"&SUBSTITUTE(E7205,", ","|")&"|" -> |Grant Cramer|Suzanne Snyder|John Allen Nelson|John Vernon|Michael S. Siegel|Peter Licassi|Royal Dano|Christopher Titus|Irene Michaels|Karla Sue Krull|
A7206: s7205 | B7206: Movie | C7206: Killers | D7206: Robert Luketic | E7206: Katherine Heigl, Ashton Kutcher, Tom Selleck, Catherine O'Hara, Katheryn Winnick, Kevin Sussman, Lisa Ann Walter, Casey Wilson, Rob Riggle, Martin Mull, Alex Borstein | F7206: United States | G7206: 44197 | H7206: 2010 | I7206: PG-13 | J7206: 100 min | K7206: Action & Adventure, Comedies, Romantic Movies | L7206: After a whirlwind romance, Jen and Spencer settle into married life — until Spencer's secret past as a hit man shakes up their suburban bliss. | M7206: =IF(G7206="","",YEAR(G7206)) -> 2021 | N7206: =IF(G7206="","",MONTH(G7206)) -> 1 | O7206: =IFERROR(VLOOKUP(I7206,Lists!$F$2:$G$16,2,FALSE()),"Not Rated") -> Teens | P7206: =IFERROR(VALUE(LEFT(J7206,FIND(" ",J7206)-1)),"") -> 100 | Q7206: =IFERROR(LEFT(F7206,FIND(",",F7206)-1),F7206) -> United States | R7206: ="|"&SUBSTITUTE(F7206,", ","|")&"|" -> |United States| | S7206: ="|"&SUBSTITUTE(K7206,", ","|")&"|" -> |Action & Adventure|Comedies|Romantic Movies| | T7206: ="|"&SUBSTITUTE(D7206,", ","|")&"|" -> |Robert Luketic| | U7206: ="|"&SUBSTITUTE(E7206,", ","|")&"|" -> |Katherine Heigl|Ashton Kutcher|Tom Selleck|Catherine O'Hara|Katheryn Winnick|Kevin Sussman|Lisa Ann Walter|Casey Wilson|Rob Riggle|Martin Mull|Alex Borstein|
A7207: s7206 | B7207: Movie | C7207: Kills on Wheels | D7207: Attila Till | E7207: Szabolcs Thuróczy, Zoltán Fenyvesi, Adám Fekete, Dusan Vitanovic, Mónika Balsai, Lidia Danis, Zoltán Mucsi | F7207: Hungary | G7207: 43174 | H7207: 2016 | I7207: TV-MA | J7207: 103 min | K7207: Action & Adventure, Dramas, International Movies | L7207: Two young men with disabilities befriend a hitman in a wheelchair and become his helpers, only to wind up in the crosshairs of a Serbian mobster. | M7207: =IF(G7207="","",YEAR(G7207)) -> 2018 | N7207: =IF(G7207="","",MONTH(G7207)) -> 3 | O7207: =IFERROR(VLOOKUP(I7207,Lists!$F$2:$G$16,2,FALSE()),"Not Rated") -> Adults | P7207: =IFERROR(VALUE(LEFT(J7207,FIND(" ",J7207)-1)),"") -> 103 | Q7207: =IFERROR(LEFT(F7207,FIND(",",F7207)-1),F7207) -> Hungary | R7207: ="|"&SUBSTITUTE(F7207,", ","|")&"|" -> |Hungary| | S7207: ="|"&SUBSTITUTE(K7207,", ","|")&"|" -> |Action & Adventure|Dramas|International Movies| | T7207: ="|"&SUBSTITUTE(D7207,", ","|")&"|" -> |Attila Till| | U7207: ="|"&SUBSTITUTE(E7207,", ","|")&"|" -> |Szabolcs Thuróczy|Zoltán Fenyvesi|Adám Fekete|Dusan Vitanovic|Mónika Balsai|Lidia Danis|Zoltán Mucsi|
A7208: s7207 | B7208: Movie | C7208: Kilo Two Bravo | D7208: Paul Katis | E7208: David Elliot, Mark Stanley, Scott Kyle, Benjamin O'Mahony, Bryan Parry, Liam Ainsworth, Andy Gibbins, John Doughty, Paul Luebke, Thomas Davison, Grant Kilburn, Robert Mitchell, Jon-Paul Bell, Malachi Kirby, Ali Cook | F7208: United Kingdom | G7208: 43525 | H7208: 2014 | I7208: R | J7208: 109 min | K7208: Dramas, Independent Movies, Thrillers | L7208: On patrol in Afghanistan, a British paratrooper unit unwittingly ventures into a dry riverbed that turns out to be littered with land mines. | M7208: =IF(G7208="","",YEAR(G7208)) -> 2019 | N7208: =IF(G7208="","",MONTH(G7208)) -> 3 | O7208: =IFERROR(VLOOKUP(I7208,Lists!$F$2:$G$16,2,FALSE()),"Not Rated") -> Adults | P7208: =IFERROR(VALUE(LEFT(J7208,FIND(" ",J7208)-1)),"") -> 109 | Q7208: =IFERROR(LEFT(F7208,FIND(",",F7208)-1),F7208) -> United Kingdom | R7208: ="|"&SUBSTITUTE(F7208,", ","|")&"|" -> |United Kingdom| | S7208: ="|"&SUBSTITUTE(K7208,", ","|")&"|" -> |Dramas|Independent Movies|Thrillers| | T7208: ="|"&SUBSTITUTE(D7208,", ","|")&"|" -> |Paul Katis| | U7208: ="|"&SUBSTITUTE(E7208,", ","|")&"|" -> |David Elliot|Mark Stanley|Scott Kyle|Benjamin O'Mahony|Bryan Parry|Liam Ainsworth|Andy Gibbins|John Doughty|Paul Luebke|Thomas Davison|Grant Kilburn|Robert Mitchell|Jon-Paul Bell|Malachi Kirby|Ali Cook|
A7209: s7208 | B7209: Movie | C7209: King Jack | D7209: Felix Thompson | E7209: Charlie Plummer, Cory Nichols, Christian Madsen, Danny Flaherty, Erin Davie, Chloe Levine | F7209: United States | G7209: 42552 | H7209: 2015 | I7209: NR | J7209: 81 min | K7209: Dramas, Independent Movies | L7209: Already coping with a bully, a mercurial older brother and summer school, 15-year-old Jack is saddled with his young cousin for an eventful weekend. | M7209: =IF(G7209="","",YEAR(G7209)) -> 2016 | N7209: =IF(G7209="","",MONTH(G7209)) -> 7 | O7209: =IFERROR(VLOOKUP(I7209,Lists!$F$2:$G$16,2,FALSE()),"Not Rated") -> Not Rated | P7209: =IFERROR(VALUE(LEFT(J7209,FIND(" ",J7209)-1)),"") -> 81 | Q7209: =IFERROR(LEFT(F7209,FIND(",",F7209)-1),F7209) -> United States | R7209: ="|"&SUBSTITUTE(F7209,", ","|")&"|" -> |United States| | S7209: ="|"&SUBSTITUTE(K7209,", ","|")&"|" -> |Dramas|Independent Movies| | T7209: ="|"&SUBSTITUTE(D7209,", ","|")&"|" -> |Felix Thompson| | U7209: ="|"&SUBSTITUTE(E7209,", ","|")&"|" -> |Charlie Plummer|Cory Nichols|Christian Madsen|Danny Flaherty|Erin Davie|Chloe Levine|
A7210: s7209 | B7210: Movie | C7210: King's Ransom | D7210: Jeffrey W. Byrd | E7210: Anthony Anderson, Jay Mohr, Kellita Smith, Nicole Ari Parker, Regina Hall, Loretta Devine, Donald Faison, Leila Arcieri, Charlie Murphy, Brooke D'Orsay | F7210: United States, Canada | G7210: 43770 | H7210: 2005 | I7210: PG-13 | J7210: 98 min | K7210: Action & Adventure, Comedies | L7210: A wealthy, despicable businessman comes to the realization that he may lose half his fortune to the obnoxious wife he's trying to divorce. So, he decides to arrange his own kidnapping in order to wipe himself out and claim poverty. | M7210: =IF(G7210="","",YEAR(G7210)) -> 2019 | N7210: =IF(G7210="","",MONTH(G7210)) -> 11 | O7210: =IFERROR(VLOOKUP(I7210,Lists!$F$2:$G$16,2,FALSE()),"Not Rated") -> Teens | P7210: =IFERROR(VALUE(LEFT(J7210,FIND(" ",J7210)-1)),"") -> 98 | Q7210: =IFERROR(LEFT(F7210,FIND(",",F7210)-1),F7210) -> United States | R7210: ="|"&SUBSTITUTE(F7210,", ","|")&"|" -> |United States|Canada| | S7210: ="|"&SUBSTITUTE(K7210,", ","|")&"|" -> |Action & Adventure|Comedies| | T7210: ="|"&SUBSTITUTE(D7210,", ","|")&"|" -> |Jeffrey W. Byrd| | U7210: ="|"&SUBSTITUTE(E7210,", ","|")&"|" -> |Anthony Anderson|Jay Mohr|Kellita Smith|Nicole Ari Parker|Regina Hall|Loretta Devine|Donald Faison|Leila Arcieri|Charlie Murphy|Brooke D'Orsay|
... A7255: s7254 | B7255: Movie | C7255: La Coppia dei Campioni | D7255: Giulio Base | E7255: Massimo Boldi, Massimiliano Tortora, Anna Maria Barbera, Massimo Ceccherini, Pia Lanciotti, Flora Canto | F7255: Italy | G7255: 42781 | H7255: 2016 | I7255: TV-MA | J7255: 88 min | K7255: Comedies, International Movies | L7255: After winning a shared trip to a soccer match, two colleagues who hold opposite world views find they're stuck traveling together for the duration. | M7255: =IF(G7255="","",YEAR(G7255)) -> 2017 | N7255: =IF(G7255="","",MONTH(G7255)) -> 2 | O7255: =IFERROR(VLOOKUP(I7255,Lists!$F$2:$G$16,2,FALSE()),"Not Rated") -> Adults | P7255: =IFERROR(VALUE(LEFT(J7255,FIND(" ",J7255)-1)),"") -> 88 | Q7255: =IFERROR(LEFT(F7255,FIND(",",F7255)-1),F7255) -> Italy | R7255: ="|"&SUBSTITUTE(F7255,", ","|")&"|" -> |Italy| | S7255: ="|"&SUBSTITUTE(K7255,", ","|")&"|" -> |Comedies|International Movies| | T7255: ="|"&SUBSTITUTE(D7255,", ","|")&"|" -> |Giulio Base| | U7255: ="|"&SUBSTITUTE(E7255,", ","|")&"|" -> |Massimo Boldi|Massimiliano Tortora|Anna Maria Barbera|Massimo Ceccherini|Pia Lanciotti|Flora Canto|
A7256: s7255 | B7256: TV Show | C7256: La Familia P. Luche | D7256: Unknown | E7256: Eugenio Derbez, Consuelo Duval, Luis Manuel Ávila, Regina Blandón, Miguel Perez, Barbara Torres, Dalilah Polanco, Pierre Angelo | F7256: United States | H7256: 2012 | I7256: TV-14 | J7256: 3 Seasons | K7256: International TV Shows, Spanish-Language TV Shows, TV Comedies | L7256: This irreverent sitcom featues Ludovico, Federica and their three children Bibi, Junior and Ludoviquito, living in Ciudad P. Luche. | M7256: =IF(G7256="","",YEAR(G7256)) | N7256: =IF(G7256="","",MONTH(G7256)) | O7256: =IFERROR(VLOOKUP(I7256,Lists!$F$2:$G$16,2,FALSE()),"Not Rated") -> Teens | P7256: =IFERROR(VALUE(LEFT(J7256,FIND(" ",J7256)-1)),"") -> 3 | Q7256: =IFERROR(LEFT(F7256,FIND(",",F7256)-1),F7256) -> United States | R7256: ="|"&SUBSTITUTE(F7256,", ","|")&"|" -> |United States| | S7256: ="|"&SUBSTITUTE(K7256,", ","|")&"|" -> |International TV Shows|Spanish-Language TV Shows|TV Comedies| | T7256: ="|"&SUBSTITUTE(D7256,", ","|")&"|" -> |Unknown| | U7256: ="|"&SUBSTITUTE(E7256,", ","|")&"|" -> |Eugenio Derbez|Consuelo Duval|Luis Manuel Ávila|Regina Blandón|Miguel Perez|Barbara Torres|Dalilah Polanco|Pierre Angelo|
A7257: s7256 | B7257: TV Show | C7257: La Femme | D7257: Unknown | E7257: Zoe Tay, Ann Kok, Tiffany Leong, Tay Ping Hui, Yao Wenlong, Shaun Chen, Paige Chua, Nat Ho, Desmond Sim | F7257: Unknown | G7257: 43024 | H7257: 2016 | I7257: TV-14 | J7257: 1 Season | K7257: International TV Shows, TV Dramas | L7257: Personal desires guide the lives of a marriage-averse entrepreneur, a housewife coping with infidelity and a career woman who leaves her spouse. | M7257: =IF(G7257="","",YEAR(G7257)) -> 2017 | N7257: =IF(G7257="","",MONTH(G7257)) -> 10 | O7257: =IFERROR(VLOOKUP(I7257,Lists!$F$2:$G$16,2,FALSE()),"Not Rated") -> Teens | P7257: =IFERROR(VALUE(LEFT(J7257,FIND(" ",J7257)-1)),"") -> 1 | Q7257: =IFERROR(LEFT(F7257,FIND(",",F7257)-1),F7257) -> Unknown | R7257: ="|"&SUBSTITUTE(F7257,", ","|")&"|" -> |Unknown| | S7257: ="|"&SUBSTITUTE(K7257,", ","|")&"|" -> |International TV Shows|TV Dramas| | T7257: ="|"&SUBSTITUTE(D7257,", ","|")&"|" -> |Unknown| | U7257: ="|"&SUBSTITUTE(E7257,", ","|")&"|" -> |Zoe Tay|Ann Kok|Tiffany Leong|Tay Ping Hui|Yao Wenlong|Shaun Chen|Paige Chua|Nat Ho|Desmond Sim|
A7258: s7257 | B7258: TV Show | C7258: La Piloto | D7258: Unknown | E7258: Livia Brito, Juan Eduardo Colucho, Arap Bethke, María Fernanda Yépes, Alejandro Nones, María De La Fuente, Verónica Montes, Natasha Domínguez, María Fernanda García, Mauricio Aspe, Stephanie Salas, Tommy Vasquez, Macarena Achaga | F7258: Mexico | G7258: 43192 | H7258: 2017 | I7258: TV-MA | J7258: 1 Season | K7258: Crime TV Shows, International TV Shows, Spanish-Language TV Shows | L7258: Dreaming her whole life of becoming a pilot, Yolanda finds work as a flight attendant, unaware she'll soon be thrust into a drug smuggling operation. | M7258: =IF(G7258="","",YEAR(G7258)) -> 2018 | N7258: =IF(G7258="","",MONTH(G7258)) -> 4 | O7258: =IFERROR(VLOOKUP(I7258,Lists!$F$2:$G$16,2,FALSE()),"Not Rated") -> Adults | P7258: =IFERROR(VALUE(LEFT(J7258,FIND(" ",J7258)-1)),"") -> 1 | Q7258: =IFERROR(LEFT(F7258,FIND(",",F7258)-1),F7258) -> Mexico | R7258: ="|"&SUBSTITUTE(F7258,", ","|")&"|" -> |Mexico| | S7258: ="|"&SUBSTITUTE(K7258,", ","|")&"|" -> |Crime TV Shows|International TV Shows|Spanish-Language TV Shows| | T7258: ="|"&SUBSTITUTE(D7258,", ","|")&"|" -> |Unknown| | U7258: ="|"&SUBSTITUTE(E7258,", ","|")&"|" -> |Livia Brito|Juan Eduardo Colucho|Arap Bethke|María Fernanda Yépes|Alejandro Nones|María De La Fuente|Verónica Montes|Natasha Domínguez|María Fernanda García|Mauricio Aspe|Stephanie Salas|Tommy Vasquez|Macarena Achaga|
A7259: s7258 | B7259: TV Show | C7259: La Rosa de Guadalupe | D7259: Unknown | E7259: Milia Nader, Francisco Avendaño, Diego Lara, Sandra Itzel, Marisol del Olmo, Aleyda Gallardo, Gerardo Murguía, Roxana Saucedo, Emmanuel Orenday, Maru Dueñas | F7259: Mexico | G7259: 43480 | H7259: 2010 | I7259: TV-PG | J7259: 1 Season | K7259: Classic & Cult TV, Crime TV Shows, International TV Shows | L7259: This series responds to the need to believe in miracles, dreams, love stories and happy endings, with positive characters. | M7259: =IF(G7259="","",YEAR(G7259)) -> 2019 | N7259: =IF(G7259="","",MONTH(G7259)) -> 1 | O7259: =IFERROR(VLOOKUP(I7259,Lists!$F$2:$G$16,2,FALSE()),"Not Rated") -> Older Kids | P7259: =IFERROR(VALUE(LEFT(J7259,FIND(" ",J7259)-1)),"") -> 1 | Q7259: =IFERROR(LEFT(F7259,FIND(",",F7259)-1),F7259) -> Mexico | R7259: ="|"&SUBSTITUTE(F7259,", ","|")&"|" -> |Mexico| | S7259: ="|"&SUBSTITUTE(K7259,", ","|")&"|" -> |Classic & Cult TV|Crime TV Shows|International TV Shows| | T7259: ="|"&SUBSTITUTE(D7259,", ","|")&"|" -> |Unknown| | U7259: ="|"&SUBSTITUTE(E7259,", ","|")&"|" -> |Milia Nader|Francisco Avendaño|Diego Lara|Sandra Itzel|Marisol del Olmo|Aleyda Gallardo|Gerardo Murguía|Roxana Saucedo|Emmanuel Orenday|Maru Dueñas|
A7260: s7259 | B7260: TV Show | C7260: La Viuda Negra | D7260: Alejandro Lozano | E7260: Ana Serradilla, Julián Román, Ramiro Meneses, Juan Pablo Gamboa, Eileen Moreno, Luis Alfredo Velasco, Margarita Reyes, Alexander Gil, Luis Roberto Guzmán, Raúl Méndez | F7260: Colombia, Mexico, United States | G7260: 43480 | H7260: 2016 | I7260: TV-14 | J7260: 1 Season | K7260: Crime TV Shows, International TV Shows, Spanish-Language TV Shows | L7260: Beautiful and ruthless Griselda Blanco, known as the queen of cocaine, becomes Pablo Escobar's boss and governs a world of deceit and death. | M7260: =IF(G7260="","",YEAR(G7260)) -> 2019 | N7260: =IF(G7260="","",MONTH(G7260)) -> 1 | O7260: =IFERROR(VLOOKUP(I7260,Lists!$F$2:$G$16,2,FALSE()),"Not Rated") -> Teens | P7260: =IFERROR(VALUE(LEFT(J7260,FIND(" ",J7260)-1)),"") -> 1 | Q7260: =IFERROR(LEFT(F7260,FIND(",",F7260)-1),F7260) -> Colombia | R7260: ="|"&SUBSTITUTE(F7260,", ","|")&"|" -> |Colombia|Mexico|United States| | S7260: ="|"&SUBSTITUTE(K7260,", ","|")&"|" -> |Crime TV Shows|International TV Shows|Spanish-Language TV Shows| | T7260: ="|"&SUBSTITUTE(D7260,", ","|")&"|" -> |Alejandro Lozano| | U7260: ="|"&SUBSTITUTE(E7260,", ","|")&"|" -> |Ana Serradilla|Julián Román|Ramiro Meneses|Juan Pablo Gamboa|Eileen Moreno|Luis Alfredo Velasco|Margarita Reyes|Alexander Gil|Luis Roberto Guzmán|Raúl Méndez|
...

Sheet Lists
A1: Type | B1: Rating Group | C1: Country | D1: Genre | E1: Year | F1: Rating | G1: Rating → Group
A2: All | B2: All | C2: All | D2: All | E2: 1925 | F2: TV-MA | G2: Adults
A3: Movie | B3: Adults | C3: United States | D3: International Movies | E3: 1926 | F3: TV-14 | G3: Teens
A4: TV Show | B4: Teens | C4: India | D4: Dramas | E4: 1927 | F4: TV-PG | G4: Older Kids
B5: Older Kids | C5: Unknown | D5: Comedies | E5: 1928 | F5: R | G5: Adults
B6: Kids | C6: United Kingdom | D6: International TV Shows | E6: 1929 | F6: PG-13 | G6: Teens
B7: Not Rated | C7: Canada | D7: Documentaries | E7: 1930 | F7: TV-Y7 | G7: Kids
C8: France | D8: Action & Adventure | E8: 1931 | F8: TV-Y | G8: Kids
C9: Japan | D9: TV Dramas | E9: 1932 | F9: PG | G9: Older Kids
C10: Spain | D10: Independent Movies | E10: 1933 | F10: TV-G | G10: Kids
C11: South Korea | D11: Children & Family Movies | E11: 1934 | F11: NR | G11: Not Rated
C12: Germany | D12: Romantic Movies | E12: 1935 | F12: G | G12: Kids
C13: Mexico | D13: TV Comedies | E13: 1936 | F13: Not Rated | G13: Not Rated
C14: China | D14: Thrillers | E14: 1937 | F14: TV-Y7-FV | G14: Kids
C15: Australia | D15: Crime TV Shows | E15: 1938 | F15: NC-17 | G15: Adults
C16: Egypt | D16: Kids' TV | E16: 1939 | F16: UR | G16: Not Rated
C17: Turkey | D17: Docuseries | E17: 1940
C18: Hong Kong | D18: Music & Musicals | E18: 1941
C19: Nigeria | D19: Romantic TV Shows | E19: 1942
C20: Italy | D20: Horror Movies | E20: 1943
C21: Brazil | D21: Stand-Up Comedy | E21: 1944
C22: Argentina | D22: Reality TV | E22: 1945
C23: Belgium | D23: British TV Shows | E23: 1946
C24: Indonesia | D24: Sci-Fi & Fantasy | E24: 1947
C25: Taiwan | D25: Sports Movies | E25: 1948
C26: Philippines | D26: Anime Series | E26: 1949
C27: Thailand | D27: Spanish-Language TV Shows | E27: 1950
C28: South Africa | D28: TV Action & Adventure | E28: 1951
... C44: Pakistan | D44: TV Shows | E44: 1967
C45: Czech Republic | E45: 1968
C46: Switzerland | E46: 1969
C47: Romania | E47: 1970
C48: Uruguay | E48: 1971
C49: Saudi Arabia | E49: 1972
C50: Austria | E50: 1973
C51: Luxembourg | E51: 1974
C52: Finland | E52: 1975
C53: Greece | E53: 1976
C54: Hungary | E54: 1977
C55: Iceland | E55: 1978
C56: Bulgaria | E56: 1979
... C98: Paraguay | E98: 2021
C99: Albania
C100: Slovakia
C101: Bermuda
C102: Ecuador
C103: Armenia
C104: Mongolia
C105: Bahamas
C106: Sri Lanka
C107: Latvia
C108: Liechtenstein
C109: Cuba
C110: Nicaragua
... C125: Montenegro
